Workbook

Sheet Anford_QZBW_zert_spez
A1: ID | B1: Programm | C1: Akteur | D1: Rolle | E1: Prozesskategorie | F1: Administrative Tätigkeit (Objekt + Verb) | G1: Fachliche Anforderung / erforderlicher Nachweis | H1: Häufigkeit | I1: Fallzahl / Bezugsgröße | J1: Zeitaufwand je Vorgang (Min.) | K1: Gesamter Zeitaufwand (Std.) | L1: Stundensatz (EUR/Std.) | M1: Arbeitszeitkosten (EUR) | N1: Quelldokument | O1: Genaue Fundstelle | P1: Wörtliches Zitat
A2: QZ-0001 | B2: QZBW | C2: Traubenerzeuger / landwirtschaftlicher Betrieb | D2: Traubenerzeuger; Bezugsform: Gruppe | E2: Verträge | F2: Teilnahmevereinbarung mit der Erzeugergruppe prüfen, unterzeichnen und übermitteln | G2: Unterzeichnete Teilnahmevereinbarung zwischen Traubenerzeuger und Erzeugergruppe | H2: einmalig | I2: 1 | J2: 15 | K2: 0.25 | L2: 50 | M2: 12.5 | N2: QZBW – Teilnahmevereinbarung Gruppenzertifizierung (pflanzliche Bereiche), Stand 2023 | O2: S. 1, Ziff. I.1; S. 2, Ziff. I.11 | P2: Der Erzeugerbetrieb erklärt seine Teilnahme am Gruppenzertifizierungssystem des oben genannten gruppenführenden Unternehmens. […] Mit dieser Erklärung treten alle früheren einzelbetrieblichen Teilnahmevereinbarungen des Erzeugers gegenüber einem Lizenznehmer […] außer Kraft.
A3: QZ-0002 | B3: QZBW | C3: Traubenerzeuger / landwirtschaftlicher Betrieb | D3: Traubenerzeuger; Bezugsform: Gruppe | E3: Ausfüllen von Checklisten und Formulare | F3: Eigenkontroll-Checkliste des landwirtschaftlichen Betriebs ausfüllen und ablegen | G3: Vollständig bearbeitete Eigenkontroll-Checkliste des landwirtschaftlichen Betriebs | H3: einmalig | I3: 1 | J3: 30 | K3: 0.5 | L3: 50 | M3: 25 | N3: QZBW – Programmbestimmungen, Stand 01.01.2025 | O3: Programmbestimmungen QZBW 2025, S. 14, Abschnitt 5.5 | P3: Die Eigenkontrolle ist obligatorischer Bestandteil des Qualitätssicherungskonzeptes im „System Qualitätszeichen Baden-Württemberg“. Alle Teilnehmer müssen die Durchführung der Eigenkontrolle dokumentieren und nachweisen.
A4: QZ-0003 | B4: QZBW | C4: Traubenerzeuger / landwirtschaftlicher Betrieb | D4: Traubenerzeuger; Bezugsform: Gruppe | E4: Ausfüllen von Checklisten und Formulare | F4: GVO-Freiheitsbescheinigung ausfüllen beziehungsweise einholen und zusammen mit den zugehörigen Nachweisen ablegen | G4: Vollständiger Nachweis der GVO-Freiheit einschließlich Bescheinigung und zugehöriger Unterlagen | H4: einmalig | I4: 1 | J4: 60 | K4: 1 | L4: 50 | M4: 50 | N4: QZBW – Zusatzanforderungen Wein 2025; Bescheinigung über GVO-Freiheit | O4: QZBW ZA Wein 2025, S. 3, Abschnitt Gentechnik | P4: Produkte mit dem Qualitätszeichen müssen die Anforderungen für die Kennzeichnung „Ohne Gentechnik“ erfüllen.
A5: QZ-0004 | B5: QZBW | C5: Traubenerzeuger / landwirtschaftlicher Betrieb | D5: Traubenerzeuger; Bezugsform: Gruppe | E5: Ausfüllen von Checklisten und Formulare | F5: Datenschutzhinweise zur Teilnahmevereinbarung lesen und unterzeichnen | G5: Dokumentierte Kenntnisnahme der Datenschutzhinweise zur Teilnahmevereinbarung | H5: einmalig | I5: 1 | J5: 15 | K5: 0.25 | L5: 50 | M5: 12.5 | N5: QZBW – Datenschutzhinweise zur Teilnahmevereinbarung, Stand 02.07.2021 | O5: Datenschutzhinweise Teilnahmevereinbarung QZBW, S. 1, Abschnitt 4 | P5: Ihre personenbezogenen Daten werden erhoben, um die Teilnahmevereinbarung abschließen und erfüllen zu können.
A6: QZ-0016 | B6: QZBW | C6: Genossenschaft / zentrale Einrichtung / Zeichennutzer | D6: Administrative Tätigkeiten im QMS der Erzeugergruppe | E6: Verträge | F6: Teilnahmevereinbarung mit dem Gruppenmitglied ausfüllen, unterzeichnen und ablegen | G6: Unterzeichnete Teilnahmevereinbarung mit dem Gruppenmitglied | H6: einmalig | I6: 1 | J6: 15 | K6: 0.25 | L6: 50 | M6: 12.5 | N6: QZBW – Anforderungen an Erzeugergruppen, Stand 01.01.2023 | O6: Anforderungen an Erzeugergruppen 2023, S. 5, Abschnitt 3.2.1 | P6: Die Erzeugergruppe hat mit jedem Mitglied eine gültige Teilnahmevereinbarung QZBW abgeschlossen.
A7: QZ-0017 | B7: QZBW | C7: Genossenschaft / zentrale Einrichtung / Zeichennutzer | D7: Administrative Tätigkeiten als Zeichennutzer | E7: Verträge | F7: Zeichennutzungsvertrag lesen, unterzeichnen und ablegen | G7: Unterzeichneter Zeichennutzungsvertrag | H7: einmalig | I7: 1 | J7: 30 | K7: 0.5 | L7: 50 | M7: 25 | N7: QZBW – Programmbestimmungen, Stand 01.01.2025 | O7: Programmbestimmungen QZBW 2025, S. 34, Abschnitt 10.2 | P7: Die Teilnahme als Zeichennutzer ist nur auf der Grundlage eines Zeichennutzungsvertrages mit einem Lizenznehmer möglich.
A8: QZ-0018 | B8: QZBW | C8: Genossenschaft / zentrale Einrichtung / Zeichennutzer | D8: Administrative Tätigkeiten als Zeichennutzer | E8: Ausfüllen von Checklisten und Formulare | F8: Datenschutzhinweise zum Zeichennutzungsvertrag lesen und unterzeichnen | G8: Dokumentierte Kenntnisnahme der Datenschutzhinweise zum Zeichennutzungsvertrag | H8: einmalig | I8: 1 | J8: 7.5 | K8: 0.125 | L8: 50 | M8: 6.25 | N8: QZBW – Datenschutzhinweise zum Zeichennutzungsvertrag, Stand 02.07.2021 | O8: Datenschutzhinweise Zeichennutzungsvertrag QZBW, S. 1, Abschnitt 4 | P8: Ihre personenbezogenen Daten werden verarbeitet, um den Zeichennutzungsvertrag abschließen und erfüllen zu können.
A9: QZ-0019 | B9: QZBW | C9: Genossenschaft / zentrale Einrichtung / Zeichennutzer | D9: Administrative Tätigkeiten im QMS der Erzeugergruppe | E9: Ausfüllen von Checklisten und Formulare | F9: Excel-Meldedatei für jedes Gruppenmitglied ausfüllen und übermitteln | G9: Vollständige Excel-Meldedatei für jedes Gruppenmitglied | H9: einmalig | I9: 1 | J9: 240 | K9: 4 | L9: 30 | M9: 120 | N9: QZBW – Anforderungen an Erzeugergruppen, Stand 01.01.2023 | O9: Anforderungen an Erzeugergruppen 2023, S. 6, Abschnitt 3.2.3. Die Richtlinie verlangt das aktuelle Mitgliederverzeichnis, jedoch nicht wörtlich das Dateiformat Excel. | P9: Die Erzeugergruppe hat ein Mitgleiderverzeichnis mit folgenden Stammdaten zu führen: […]
A10: QZ-0020 | B10: QZBW | C10: Genossenschaft / zentrale Einrichtung / Zeichennutzer | D10: Administrative Tätigkeiten als Zeichennutzer | E10: Eigenkontrolle als Zeichennutzer | F10: Eigenkontrollcheckliste des Zeichennutzers ausfüllen und ablegen | G10: Vollständig bearbeitete Eigenkontrollcheckliste des Zeichennutzers | H10: einmalig | I10: 1 | J10: 60 | K10: 1 | L10: 30 | M10: 30 | N10: QZBW – Eigenkontrolle Zeichennutzer: Wein, Sekt und Perlwein, Version 2024 | O10: Eigenkontrolle Zeichennutzer – Wein 2024, S. 1, Abschnitt 1.2 | P10: Zur Einhaltung der QZBW-Bestimmungen regelmäßig (mind. jährlich) durchgeführt und dokumentiert (Eigenkontrollchecklisten aufbewahrt).
A11: QZ-0021 | B11: QZBW | C11: Genossenschaft / zentrale Einrichtung / Zeichennutzer | D11: Administrative Tätigkeiten im QMS der Erzeugergruppe | E11: Interne Prüfungen innerhalb der Gruppe | F11: Eigenkontrollcheckliste des Traubenerzeugers prüfen und Prüfergebnis dokumentieren | G11: Geprüfte Eigenkontrollcheckliste des Traubenerzeugers | H11: einmalig | I11: 1 | J11: 120 | K11: 2 | L11: 30 | M11: 60 | N11: QZBW – Anforderungen an Erzeugergruppen, Stand 01.01.2023 | O11: Anforderungen an Erzeugergruppen 2023, S. 8, Abschnitt 4.1.1 | P11: Die Einhaltung der Anforderungen muss über ein qualifiziertes internes Audit bzw. Kontrolle mindestens einmal je Kalenderjahr überprüft und anhand einer Checkliste dokumentiert werden.
A12: QZ-0022 | B12: QZBW | C12: Genossenschaft / zentrale Einrichtung / Zeichennutzer | D12: Administrative Tätigkeiten im QMS der Erzeugergruppe | E12: Interne Prüfungen innerhalb der Gruppe | F12: Maßnahmenpläne prüfen und Prüfergebnis dokumentieren | G12: Geprüfte Maßnahmenpläne | H12: einmalig | I12: 1 | J12: 30 | K12: 0.5 | L12: 30 | M12: 15 | N12: QZBW – Anforderungen an Erzeugergruppen, Stand 01.01.2023 | O12: Anforderungen an Erzeugergruppen 2023, S. 9, Abschnitt 4.2.1; Schreibweise „inklusiv“ entspricht dem Original | P12: Für alle in internen Audits/Kontrollen festgestellten C- und D-Bewertungen sind Korrekturmaßnahmen inklusiv angemessener Fristen eingetragen.
A13: QZ-0023 | B13: QZBW | C13: Genossenschaft / zentrale Einrichtung / Zeichennutzer | D13: Administrative Tätigkeiten im QMS der Erzeugergruppe | E13: Interne Prüfungen innerhalb der Gruppe | F13: Pflanzenschutzaufzeichnungen prüfen und Prüfergebnis dokumentieren | G13: Geprüfte Pflanzenschutzaufzeichnungen | H13: einmalig | I13: 1 | J13: 60 | K13: 1 | L13: 30 | M13: 30 | N13: QZBW – Anforderungen an Erzeugergruppen, Stand 01.01.2023 | O13: Anforderungen an Erzeugergruppen 2023, S. 8, Abschnitt 4.1.2; umfasst die anwendbaren Pflanzenschutzanforderungen | P13: Interne Checklisten müssen alle anwendbaren Standardanforderungen enthalten.
... A26: QZ-0045 | B26: QZBW | C26: Genossenschaft / zentrale Einrichtung / Zeichennutzer | D26: Administrative Tätigkeiten im QMS der Erzeugergruppe | E26: QMS-Dokumentation und -lenkung | F26: QMS-Verfahren, Arbeitsanweisungen, Formulare und Aufzeichnungen ablegen, auf Aktualität prüfen und pflegen | G26: Aktuelle, versionierte und vollständig abgelegte QMS-Unterlagen der Erzeugergruppe | H26: fortlaufend | I26: 1 | J26: 240 | K26: 4 | L26: 30 | M26: 120 | N26: QZBW – Anforderungen an Erzeugergruppen, Stand 01.01.2023 | O26: S. 10-11, Abschnitte 7.1.1 und 7.1.2 | P26: Das QMS muss durch Verfahren, Arbeitsanweisungen, Formulare und ggf. weitere Aufzeichnungen entsprechend seiner Größe angemessen dokumentiert sein. Die Dokumente werden regelmäßig auf Aktualität überprüft.
A27: QZ-0046 | B27: QZBW | C27: Kontroll-/Zertifizierungsstelle | D27: Externe Kontrolle; Bezugsform: Gruppe | E27: Stichprobenkontrollen | F27: QMS einschließlich interner Kontrollen anhand der Unterlagen verifizieren und Ergebnis dokumentieren | G27: Verifiziertes QMS einschließlich interner Kontrollen | H27: jährlich; gruppenfix, anteilig je Mitglied (n=150) | I27: =1/Annahmen!$C$77 -> 0.0066666667 | J27: 240 | K27: =I27*J27/60 -> 0.026666667 | L27: 30 | M27: =K27*L27 -> 0.8 | N27: QZBW – Anforderungen an Erzeugergruppen, Stand 01.01.2023 | O27: Anforderungen an Erzeugergruppen 2023, S. 5, Abschnitt 3.1.4 | P27: Das interne Kontrollsystem ist wirksam. Es stellt sicher, dass alle Standorte und alle Mitglieder die Standardanforderungen erfüllen.
A28: QZ-0047 | B28: QZBW | C28: Kontroll-/Zertifizierungsstelle | D28: Externe Kontrolle; Bezugsform: Gruppe | E28: Ausfüllen von Checklisten und Formulare | F28: Prüfergebnisse dokumentieren, an auditierten Betrieb und Lizenznehmer übermitteln sowie Quartalsbericht an die MBW erstellen | G28: Prüfbericht beziehungsweise Auditprotokoll je Audit und zusammenfassender elektronischer Quartalsbericht | H28: fortlaufend und vierteljährlich; 240 Min. als Gesamtmodellwert je Jahr; gruppenfix, anteilig je Mitglied (n=150) | I28: =1/Annahmen!$C$77 -> 0.0066666667 | J28: 240 | K28: =I28*J28/60 -> 0.026666667 | L28: 30 | M28: =K28*L28 -> 0.8 | N28: QZBW – Programmbestimmungen, Stand 01.01.2026 | O28: S. 40, Abschnitt 12.5 | P28: Über die Zertifizierungstätigkeit ist regelmäßig zum Quartalsende ein zusammenfassender Bericht zu erstellen.
A29: QZ-0052 | B29: QZBW | C29: Genossenschaft / zentrale Einrichtung / Zeichennutzer | D29: Administrative Tätigkeiten als Zeichennutzer | E29: Archivierung von Nachweisen | F29: QZBW-Qualitätsnachweis beschaffen und für die Eigen- beziehungsweise Zertifizierungskontrolle bereithalten | G29: QZBW-Qualitätsnachweis für Wein, Sekt und Perlwein durch Gütezeichen beziehungsweise Qualitätsprüfung gemäß den Zusatzanforderungen Wein | H29: jährlich | I29: 1 | J29: 30 | K29: 0.5 | L29: 30 | M29: 15 | N29: QZBW – Zusatzanforderungen Wein 2025 | O29: S. 7, Abschnitt Qualitätsprüfungen | P29: „Der Qualitätsnachweis … erfolgt regelmäßig durch ein Gütezeichen bzw. durch die Qualitätsprüfung.“
A30: QZ-0053 | B30: QZBW | C30: Genossenschaft / zentrale Einrichtung / Zeichennutzer | D30: Administrative Tätigkeiten im QMS der Erzeugergruppe | E30: Mitglieder- und Zulassungsmanagement | F30: Verfahren zur Aufnahme neuer Mitglieder pflegen und Neuaufnahme dokumentieren | G30: Dokumentiertes Verfahren und vollständiger Nachweis der Aufnahme neuer Mitgliedsbetriebe | H30: bei Aufnahme | I30: 1 | J30: 30 | K30: 0.5 | L30: 30 | M30: 15 | N30: QZBW - Anforderungen an Erzeugergruppen, Stand 01.01.2023 | O30: S. 6, Abschnitt 3.2.4 | P30: Es muss ein dokumentiertes Verfahren über die Aufnahme neuer Mitgliedsbetriebe geben.
A31: QZ-0054 | B31: QZBW | C31: Genossenschaft / zentrale Einrichtung / Zeichennutzer | D31: Administrative Tätigkeiten im QMS der Erzeugergruppe | E31: Qualifikation und Schulung | F31: Qualifikations-, Zulassungs- und Begleitnachweise interner Auditoren und Kontrolleure pflegen | G31: Aktuelle Qualifikations-, Zulassungs- und Begleitnachweise der internen Auditoren und Kontrolleure | H31: bei Benennung und Änderung | I31: 1 | J31: 30 | K31: 0.5 | L31: 30 | M31: 15 | N31: QZBW - Anforderungen an Erzeugergruppen, Stand 01.01.2023 | O31: S. 6-7, Abschnitte 3.3.1 und 3.3.2 | P31: Bevor interne Audits/Kontrollen selbstständig durchgeführt werden, muss der interne Auditor/Kontrolleur mindestens ein/e Audit/Kontrolle als Beobachter begleitet haben.
A32: QZ-0055 | B32: QZBW | C32: Genossenschaft / zentrale Einrichtung / Zeichennutzer | D32: Administrative Tätigkeiten im QMS der Erzeugergruppe | E32: Qualifikation und Schulung | F32: Schulungen planen sowie Inhalte und Teilnehmende dokumentieren | G32: Regelmäßige und vollständig dokumentierte Schulungen für Personal und Mitglieder | H32: jährlich | I32: 1 | J32: 60 | K32: 1 | L32: 30 | M32: 30 | N32: QZBW - Anforderungen an Erzeugergruppen, Stand 01.01.2023 | O32: S. 7, Abschnitt 3.3.3 | P32: Die Mitarbeiter/das Personal und die Mitglieder der Erzeugergruppe werden regelmäßig geschult. Die Durchführung der Schulungen ist dokumentiert.
A33: QZ-0056 | B33: QZBW | C33: Genossenschaft / zentrale Einrichtung / Zeichennutzer | D33: Administrative Tätigkeiten im QMS der Erzeugergruppe | E33: Interne Prüfungen innerhalb der Gruppe | F33: Interne Audits terminieren und Auditzeitplan pflegen | G33: Fristgerechter und dokumentierter Zeitplan der internen Audits und Kontrollen | H33: jährlich | I33: 1 | J33: 30 | K33: 0.5 | L33: 30 | M33: 15 | N33: QZBW - Anforderungen an Erzeugergruppen, Stand 01.01.2023 | O33: S. 8, Abschnitte 4.1.5 bis 4.1.7 | P33: Interne Audits/Kontrollen können in Teilaudits erfolgen. In diesem Fall muss ein Zeitplan vorliegen.
A34: QZ-0057 | B34: QZBW | C34: Genossenschaft / zentrale Einrichtung / Zeichennutzer | D34: Administrative Tätigkeiten im QMS der Erzeugergruppe | E34: Interne Prüfungen innerhalb der Gruppe | F34: Mitgliedsfreigabe im Vier-Augen-Prinzip prüfen und dokumentieren | G34: Dokumentierte Freigabe jedes Mitglieds im Vier-Augen-Prinzip | H34: jährlich je Mitglied | I34: 1 | J34: 15 | K34: 0.25 | L34: 30 | M34: 7.5 | N34: QZBW - Anforderungen an Erzeugergruppen, Stand 01.01.2023 | O34: S. 8, Abschnitt 4.1.8 | P34: Diese Freigabe ist dokumentiert.
A35: QZ-0058 | B35: QZBW | C35: Genossenschaft / zentrale Einrichtung / Zeichennutzer | D35: Administrative Tätigkeiten im QMS der Erzeugergruppe | E35: Rückverfolgbarkeits- und Plausibilitätsprüfung | F35: Rückverfolgbarkeitssystem anhand eines Warenbeispiels testen und Ergebnis dokumentieren | G35: Mindestens jährlich getestetes und dokumentiertes Rückverfolgbarkeitssystem | H35: jährlich | I35: 1 | J35: 60 | K35: 1 | L35: 30 | M35: 30 | N35: QZBW - Anforderungen an Erzeugergruppen, Stand 01.01.2023 | O35: S. 10, Abschnitt 6.1.2 | P35: Das System muss mindestens jährlich getestet werden. Der Test ist zu dokumentieren.
A36: QZ-0059 | B36: QZBW | C36: Genossenschaft / zentrale Einrichtung / Zeichennutzer | D36: Administrative Tätigkeiten als Zeichennutzer | E36: Datenaufzeichnung und -pflege | F36: Warenflüsse zwischen QZBW- und Nicht-QZBW-Ware trennen und nachvollziehbar dokumentieren | G36: Nachvollziehbare Trennung der Warenflüsse zwischen QZBW- und Nicht-QZBW-Ware in der Weinbereitung | H36: jährlich (Modellannahme für fortlaufende Pflicht) | I36: 1 | J36: 120 | K36: 2 | L36: 25 | M36: 50 | N36: QZBW – Zusatzanforderungen Wein, Stand 2025 | O36: S. 7, Abschnitt III.6 | P36: Wein, Sekt und Perlwein für die Vermarktung unter dem Qualitätszeichen ist eindeutig und nachvollziehbar zu kennzeichnen. Ware, die nicht unter dem Qualitätszeichen Baden-Württemberg vermarktet wird, ist im gesamten Betriebsablauf von der Programmware nachvollziehbar getrennt zu führen.
A37: QZ-0060 | B37: QZBW | C37: Traubenerzeuger / landwirtschaftlicher Betrieb | D37: Traubenerzeuger; Bezugsform: Gruppe | E37: Archivierung von Nachweisen | F37: Vorhandene Betriebsnachweise für das QMS zusammenstellen und der Erzeugergruppe übermitteln | G37: Vollständig zusammengestelltes und an die Erzeugergruppe übermitteltes QMS-Nachweispaket | H37: jährlich | I37: 1 | J37: 30 | K37: 0.5 | L37: 50 | M37: 25 | N37: QZBW – Zusatzanforderungen Wein, Stand 2025; Teilnahmevereinbarung Gruppenzertifizierung, Stand 2023 | O37: ZA Wein 2025, S. 6, Abschnitt Dokumentation; Teilnahmevereinbarung GZ 2023, S. 1, Ziff. I.4 | P37: Vor Anlieferung der Ernte […] muss die Dokumentation (Betriebsheft) bei der jeweiligen genossenschaftlichen oder privaten Kellerei […] zur Prüfung vorgelegt werden.
A38: QZ-0061 | B38: QZBW | C38: Traubenerzeuger / landwirtschaftlicher Betrieb | D38: Traubenerzeuger; Bezugsform: Gruppe | E38: Festlegung und Nachverfolgung von Korrekturmaßnahmen | F38: Umsetzung von Korrekturmaßnahmen dokumentieren und der Erzeugergruppe melden | G38: Dokumentierter Umsetzungsnachweis zu festgelegten Korrekturmaßnahmen und Mitteilung an die Erzeugergruppe | H38: bei Bedarf | I38: 1 | J38: 15 | K38: 0.25 | L38: 50 | M38: 12.5 | N38: QZBW – Teilnahmevereinbarung Gruppenzertifizierung (pflanzliche Bereiche), Stand 2023 | O38: S. 2, Ziff. I.4–5 | P38: Bei […] im Rahmen der internen Kontrolle festgestellten Mängeln, geeignete Abhilfe- und Korrekturmaßnahmen einzuleiten und diese zu dokumentieren.
A39: QZ-0062 | B39: QZBW | C39: Genossenschaft / zentrale Einrichtung / Zeichennutzer | D39: Administrative Tätigkeiten im QMS der Erzeugergruppe | E39: Verträge | F39: Kontrollvertrag beziehungsweise Kontrollauftrag prüfen, unterzeichnen und ablegen | G39: Dokumentierte Beauftragung einer zugelassenen Zertifizierungsstelle für die externe Gruppenkontrolle | H39: einmalig | I39: 1 | J39: 30 | K39: 0.5 | L39: 50 | M39: 25 | N39: QZBW – Teilnahmevereinbarung Gruppenzertifizierung (pflanzliche Bereiche), Stand 2023 | O39: S. 1, Ziff. I.4 | P39: Die regelmäßige Inspektion, die Überwachung und ggf. die Zertifizierung erfolgen durch eine […] zugelassene Zertifizierungsstelle im Auftrag des gruppenführenden Unternehmens.
A40: QZ-0063 | B40: QZBW | C40: Genossenschaft / zentrale Einrichtung / Zeichennutzer | D40: Administrative Tätigkeiten im QMS der Erzeugergruppe | E40: QMS-Dokumentation und -lenkung | F40: QMS-Kontrollunterlagen zusammenstellen und der Zertifizierungsstelle bereitstellen | G40: Vollständiges, prüffähiges QMS-Kontrollpaket für die externe Zertifizierungsstelle | H40: jährlich | I40: 1 | J40: 60 | K40: 1 | L40: 30 | M40: 30 | N40: QZBW – Anforderungen an Erzeugergruppen, Stand 01.01.2023 | O40: S. 8, Abschnitt 4.1.3; S. 10–11, Abschnitte 7.1.1–7.1.2 | P40: Die Berichte (ausgefüllte Checklisten) interner Audits/Kontrollen sind vollständig und aussagekräftig. Aufzeichnungen der Nachverfolgung von Korrekturmaßnahmen müssen vorliegen.
A41: QZ-0064 | B41: QZBW | C41: Kontroll-/Zertifizierungsstelle | D41: Externe Kontrolle; Bezugsform: Gruppe | E41: Stichprobenkontrollen | F41: Externen QMS-Kontrolltermin abstimmen und erforderliche Kontrollunterlagen anfordern | G41: Abgestimmter Termin und angefordertes Kontrollpaket für die externe QMS-Prüfung | H41: jährlich; gruppenfix, anteilig je Mitglied (n=150) | I41: =1/Annahmen!$C$77 -> 0.0066666667 | J41: 30 | K41: =I41*J41/60 -> 0.0033333333 | L41: 30 | M41: =K41*L41 -> 0.1 | N41: QZBW – Anforderungen an Erzeugergruppen, Stand 01.01.2023 | O41: S. 8, Abschnitt 4.1.5 | P41: Die internen Audits/Kontrollen müssen vor der externen (neutralen) Kontrolle durch die Zertifizierungsstelle abgeschlossen sein.
A42: QZ-0065 | B42: QZBW | C42: Kontroll-/Zertifizierungsstelle | D42: Externe Kontrolle; Bezugsform: Gruppe | E42: Ausfüllen von Checklisten und Formulare | F42: Zertifizierungsentscheidung dokumentieren und Gruppenzertifikat beziehungsweise Zertifikatsdaten übermitteln | G42: Dokumentierte Zertifizierungsentscheidung und übermitteltes Gruppenzertifikat beziehungsweise Zertifikatsdaten | H42: jährlich; gruppenfix, anteilig je Mitglied (n=150) | I42: =1/Annahmen!$C$77 -> 0.0066666667 | J42: 30 | K42: =I42*J42/60 -> 0.0033333333 | L42: 30 | M42: =K42*L42 -> 0.1 | N42: QZBW – Programmbestimmungen, Stand 01.01.2025; Teilnahmevereinbarung Gruppenzertifizierung, Stand 2023 | O42: Programmbestimmungen QZBW 2025, S. 9, Abschnitt 3.4 | P42: Die Erzeugergruppe ist als juristische Einheit der Zertifikatinhaber und fungiert als Zeichennutzer.
A43: QZ-0066 | B43: QZBW | C43: Genossenschaft / zentrale Einrichtung / Zeichennutzer | D43: Administrative Tätigkeiten im QMS der Erzeugergruppe | E43: Archivierung von Nachweisen | F43: Gruppenzertifikat prüfen, intern zuordnen und im QMS ablegen | G43: Geprüftes und im QMS abgelegtes Gruppenzertifikat | H43: jährlich | I43: 1 | J43: 15 | K43: 0.25 | L43: 30 | M43: 7.5 | N43: QZBW – Programmbestimmungen, Stand 01.01.2025 | O43: S. 9, Abschnitt 3.4 | P43: Die Erzeugergruppe ist als juristische Einheit der Zertifikatinhaber und fungiert als Zeichennutzer.
A44: QZ-0067 | B44: QZBW | C44: Externer Lizenznehmer | D44: Lizenznahme der Erzeugergruppe / Zeichennutzerin | E44: Verträge | F44: Zeichennutzungsvertrag der Erzeugergruppe prüfen und gegenzeichnen sowie Programmanmeldung weiterleiten | G44: Gegengezeichneter Zeichennutzungsvertrag und programmgemäß registrierte Erzeugergruppe | H44: einmalig | I44: 1 | J44: 60 | K44: 1 | L44: 30 | M44: 30 | N44: QZBW – Teilnahmevereinbarung Gruppenzertifizierung (pflanzliche Bereiche), Stand 2023; Programmbestimmungen QZBW 2025 | O44: Teilnahmevereinbarung GZ 2023, S. 2, Ziff. II.2; Programmbestimmungen 2025, Abschnitt 3.4 | P44: Es stellt seinerseits die ordentliche Teilnahme am Qualitätszeichen Baden-Württemberg durch den Abschluss eines Zeichennutzungsvertrages mit einem Lizenznehmer sicher.
A45: QZ-0068 | B45: QZBW | C45: Kontroll-/Zertifizierungsstelle | D45: Externe Kontrolle; Bezugsform: Zeichennutzer | E45: Kontrollvorbereitung | F45: Jährliche Zeichennutzerkontrolle terminieren und programmspezifische Unterlagen anfordern | G45: Abgestimmter Termin und vollständiges Kontrollpaket der Genossenschaft als Zeichennutzerin | H45: jährlich; gruppenfix, anteilig je Mitglied (n=150) | I45: =1/Annahmen!$C$77 -> 0.0066666667 | J45: 15 | K45: =I45*J45/60 -> 0.0016666667 | L45: 30 | M45: =K45*L45 -> 0.05 | N45: QZBW – Programmbestimmungen, Stand 01.01.2026 | O45: S. 24, Abschnitt 6.9; S. 39, Abschnitt 12.3; Zeitansatz siehe ANN-046 | P45: Winzergenossenschaft, Kellerei: 100 %.
A46: QZ-0069 | B46: QZBW | C46: Kontroll-/Zertifizierungsstelle | D46: Externe Kontrolle; Bezugsform: Zeichennutzer | E46: Dokumentenprüfung und Kontrolldokumentation | F46: Eigenkontrollsystem, Produkt- und Qualitätsnachweise, Waren- und Herkunftsdokumentation, Rückverfolgbarkeit und Kennzeichnung prüfen und Kontrollcheckliste vervollständigen | G46: Dokumentierte jährliche Zeichennutzerkontrolle mit bewerteten Prüfpunkten und nachvollziehbarem Ergebnis | H46: jährlich; gruppenfix, anteilig je Mitglied (n=150) | I46: =1/Annahmen!$C$77 -> 0.0066666667 | J46: 60 | K46: =I46*J46/60 -> 0.0066666667 | L46: 30 | M46: =K46*L46 -> 0.2 | N46: QZBW – Programmbestimmungen, Stand 01.01.2026 | O46: S. 18, Abschnitt 6.2.1; S. 39, Abschnitt 12.3; Zeitansatz siehe ANN-047 | P46: Kontrolle/Überprüfung des Eigenkontrollsystems und der Dokumentationen.
A47: QZ-0070 | B47: QZBW | C47: Kontroll-/Zertifizierungsstelle | D47: Externe Kontrolle; Bezugsform: Mitgliederstichprobe | E47: Stichprobenplanung | F47: Risikobasierte Mitgliederstichprobe auswählen und jährlichen Kontrollplan dokumentieren | G47: Nachvollziehbar ausgewählte Stichprobe von 13 Mitgliedern und dokumentierter Kontrollplan | H47: jährlich; gruppenfix, anteilig je Mitglied (n=150) | I47: =1/Annahmen!$C$77 -> 0.0066666667 | J47: 30 | K47: =I47*J47/60 -> 0.0033333333 | L47: 30 | M47: =K47*L47 -> 0.1 | N47: QZBW – Programmbestimmungen, Stand 01.01.2026 | O47: S. 19–20, Abschnitt 6.3; Zeitansatz siehe ANN-043 | P47: Der Mindestumfang der Stichprobe ist die Quadratwurzel der Zahl der Mitglieder.
A48: QZ-0071 | B48: QZBW | C48: Kontroll-/Zertifizierungsstelle | D48: Externe Kontrolle; Bezugsform: Mitgliederstichprobe | E48: Administrative Kontrollvorbereitung | F48: Termin und Unterlagen je ausgewähltem Mitglied koordinieren und Kontrollakte vorbereiten | G48: Vorbereitete Kontrollakten für 13 externe Mitgliederkontrollen | H48: jährlich; 13 Stichproben je Gruppe, anteilig je Mitglied (n=150) | I48: =Annahmen!$C$78/Annahmen!$C$77 -> 0.086666667 | J48: 15 | K48: =I48*J48/60 -> 0.021666667 | L48: 30 | M48: =K48*L48 -> 0.65 | N48: QZBW – Programmbestimmungen, Stand 01.01.2026 | O48: S. 19–20, Abschnitt 6.3; Zeitansatz siehe ANN-044 | P48: Die Auswahl soll frühere Kontrollergebnisse und mögliche Beschwerden berücksichtigen.
A49: QZ-0072 | B49: QZBW | C49: Kontroll-/Zertifizierungsstelle | D49: Externe Kontrolle; Bezugsform: Mitgliederstichprobe | E49: Administrative Kontrollnachbereitung | F49: Kontrollcheckliste je Stichprobenmitglied abschließen, Ergebnis und gegebenenfalls Abweichungen dokumentieren und Kontrollakte schließen | G49: Vollständige administrative Abschlussdokumentation für 13 externe Mitgliederkontrollen | H49: jährlich; 13 Stichproben je Gruppe, anteilig je Mitglied (n=150) | I49: =Annahmen!$C$78/Annahmen!$C$77 -> 0.086666667 | J49: 15 | K49: =I49*J49/60 -> 0.021666667 | L49: 30 | M49: =K49*L49 -> 0.65 | N49: QZBW – Programmbestimmungen, Stand 01.01.2026 | O49: S. 40, Abschnitt 12.5; Zeitansatz siehe ANN-045 | P49: Die auditierten Betriebe sind unverzüglich über alle Prüfergebnisse zu unterrichten.
A50: QZ-0073 | B50: QZBW | C50: Externer Lizenznehmer | D50: Laufende teilnehmerbezogene Lizenznehmerverwaltung | E50: Programm- und Vertragsüberwachung | F50: Programminhalte und vertragliche Verpflichtungen der angeschlossenen Teilnehmer laufend überwachen | G50: Nachvollziehbar überwachter Teilnehmerstatus und dokumentierte Einhaltung der programmspezifischen und vertraglichen Pflichten | H50: jährlich; teilnehmerbezogen | I50: =1 -> 1 | J50: =Annahmen!$C$87 -> 10 | K50: =I50*J50/60 -> 0.16666667 | L50: 30 | M50: =K50*L50 -> 5 | N50: QZBW – Programmbestimmungen, Stand 01.01.2026 | O50: S. 8, Abschnitt 3.2; Zeitansatz siehe ANN-050 | P50: Sie gewährleisten die ordnungsgemäße Umsetzung und Überwachung der Programminhalte bei den ihnen vertraglich angeschlossenen Erzeugern und Zeichennutzern.
A51: QZ-0074 | B51: QZBW | C51: Externer Lizenznehmer | D51: Laufende teilnehmerbezogene Lizenznehmerverwaltung | E51: Kontrollorganisation und -überwachung | F51: Vorgesehene Kontrollen veranlassen und deren Durchführung administrativ überwachen | G51: Beauftragte und statusseitig nachverfolgte Kontrollen bei angeschlossenen Erzeugern und Zeichennutzern | H51: jährlich; teilnehmerbezogen | I51: =1 -> 1 | J51: =Annahmen!$C$88 -> 15 | K51: =I51*J51/60 -> 0.25 | L51: 30 | M51: =K51*L51 -> 7.5 | N51: QZBW – Programmbestimmungen, Stand 01.01.2026 | O51: S. 22, Abschnitte 6.7–6.8; Zeitansatz siehe ANN-051 | P51: Hierbei werden insbesondere die Lizenznehmer regelmäßig dahingehend überprüft, ob sie ihren vertraglichen Pflichten zur Veranlassung und Überwachung von Kontrollen […] nachkommen.
A52: QZ-0075 | B52: QZBW | C52: Externer Lizenznehmer | D52: Laufende teilnehmerbezogene Lizenznehmerverwaltung | E52: Prüfergebnis- und Maßnahmenmanagement | F52: Prüfergebnisse zuordnen, Teilnehmerstatus aktualisieren und gewöhnliche Korrekturhinweise nachverfolgen | G52: Vollständig zugeordnete Prüfberichte und nachvollziehbar nachgehaltene Standardabweichungen beziehungsweise Korrekturhinweise | H52: jährlich; teilnehmerbezogen | I52: =1 -> 1 | J52: =Annahmen!$C$89 -> 15 | K52: =I52*J52/60 -> 0.25 | L52: 30 | M52: =K52*L52 -> 7.5 | N52: QZBW – Programmbestimmungen, Stand 01.01.2026 | O52: S. 40, Abschnitt 12.5; Zeitansatz siehe ANN-052 | P52: Zertifizierungsstellen sind verpflichtet, […] den verantwortlichen Lizenznehmer fortlaufend unverzüglich über alle Prüfergebnisse zu unterrichten.
A53: QZ-0076 | B53: QZBW | C53: Externer Lizenznehmer | D53: Laufende teilnehmerbezogene Lizenznehmerverwaltung | E53: Teilnehmer- und Stammdatenmanagement | F53: Neuanmeldungen und Stammdatenänderungen verwalten und unverzüglich an die MBW melden | G53: Aktuelle Teilnehmer- und Stammdaten sowie zeitnah an die MBW übermittelte Neu- und Änderungsmeldungen | H53: jährlich; teilnehmerbezogen | I53: =1 -> 1 | J53: =Annahmen!$C$90 -> 15 | K53: =I53*J53/60 -> 0.25 | L53: 30 | M53: =K53*L53 -> 7.5 | N53: QZBW – Programmbestimmungen, Stand 01.01.2026 | O53: S. 39, Abschnitt 12.4; Zeitansatz siehe ANN-053 | P53: Bei Neuanmeldungen oder Änderungen der Stammdaten von Erzeugern oder Zeichennutzern muss der Lizenznehmer die MBW unverzüglich informieren.
A54: QZ-0077 | B54: QZBW | C54: Externer Lizenznehmer | D54: Laufende teilnehmerbezogene Lizenznehmerverwaltung | E54: Jährliche Teilnehmermeldung | F54: Jahresmeldung der angeschlossenen Erzeuger und Zeichennutzer erstellen, plausibilisieren und an die MBW übermitteln | G54: Jährliche zusammenfassende, nach Produktbereichen getrennte Meldung der angeschlossenen Erzeuger und Zeichennutzer an die MBW | H54: jährlich; teilnehmerbezogen | I54: =1 -> 1 | J54: =Annahmen!$C$91 -> 5 | K54: =I54*J54/60 -> 0.083333333 | L54: 30 | M54: =K54*L54 -> 2.5 | N54: QZBW – Programmbestimmungen, Stand 01.01.2026 | O54: S. 39, Abschnitt 12.4; Zeitansatz siehe ANN-054 | P54: Lizenznehmer sind verpflichtet, jährlich zum 31. Dezember eine zusammenfassende Meldung über die angeschlossenen Erzeuger und Zeichennutzer bei der MBW […] abzugeben.
A55: QZ-0078 | B55: QZBW | C55: Externer Lizenznehmer | D55: Anlassbezogene Lizenznehmermaßnahmen außerhalb des Standardjahres | E55: Sanktionierung und Ausschluss | F55: Schwere Verstöße bewerten und erforderliche Sanktionierung beziehungsweise Ausschluss veranlassen und dokumentieren | G55: Dokumentierte, verhältnismäßige Sanktions- oder Ausschlussentscheidung einschließlich erforderlicher Abstimmungen | H55: bei Bedarf; im Basisszenario nicht angesetzt | L55: 30 | N55: QZBW – Programmbestimmungen, Stand 01.01.2026 | O55: S. 8, 22 und 40, Abschnitte 3.2, 6.7 und 12.5; Abgrenzung siehe ANN-055 | P55: Die Lizenznehmer sind darüber hinaus für die Sanktionierung und den Ausschluss von Erzeugern und Zeichennutzern bei schwerwiegenden Verfehlungen verantwortlich.

Sheet Anford_BioZBW_zert_spez
A1: ID | B1: Programm | C1: Akteur | D1: Rolle | E1: Prozesskategorie | F1: Administrative Tätigkeit (Objekt + Verb) | G1: Fachliche Anforderung / erforderlicher Nachweis | H1: Häufigkeit | I1: Fallzahl / Bezugsgröße | J1: Zeitaufwand je Vorgang (Min.) | K1: Gesamter Zeitaufwand (Std.) | L1: Stundensatz (EUR/Std.) | M1: Arbeitszeitkosten (EUR) | N1: Quelldokument | O1: Genaue Fundstelle | P1: Wörtliches Zitat
A2: BIO-0001 | B2: BioZBW | C2: Traubenerzeuger / landwirtschaftlicher Betrieb | D2: Traubenerzeuger; Bezugsform: Gruppe | E2: Verträge | F2: Teilnahmeerklärung gegenüber der Genossenschaft als Zeichennutzerin und Unternehmergruppe prüfen, unterzeichnen und übermitteln | G2: Unterzeichnete beziehungsweise vertraglich integrierte Teilnahmeerklärung des Traubenerzeugers gegenüber der Genossenschaft als Zeichennutzerin und Unternehmergruppe | H2: einmalig | I2: 1 | J2: 15 | K2: 0.25 | L2: 50 | M2: 12.5 | N2: BioZBW – Programmbestimmungen, Stand 01.01.2026; Verordnung (EU) 2018/848; Delegierte Verordnung (EU) 2021/715 | O2: S. 22–23, Abschnitte 9.1–9.2; VO (EU) 2018/848, Art. 36 | P2: Landwirtschaftliche Erzeugerbetriebe (Erzeuger) müssen über den Zeichennutzer eine Teilnahmeerklärung zum Biozeichen Baden-Württemberg abgeben. […] Bei bestehenden vertraglichen Beziehungen […] ist es möglich, die Inhalte der Teilnahmeerklärung […] als Zusatz oder Bestandteil dieser vertraglichen Regelungen abzuschließen.
A3: BIO-0002 | B3: BioZBW | C3: Traubenerzeuger / landwirtschaftlicher Betrieb | D3: Traubenerzeuger; Bezugsform: Gruppe | E3: Ausfüllen von Checklisten und Formulare | F3: Datenschutzhinweise zur Teilnahmevereinbarung lesen und unterzeichnen | G3: Dokumentierte Kenntnisnahme der Datenschutzhinweise zur Teilnahmevereinbarung | H3: einmalig | I3: 1 | J3: 15 | K3: 0.25 | L3: 50 | M3: 12.5 | N3: BioZBW – Teilnahmeerklärung Erzeuger, Stand 07.12.2017 | O3: Teilnahmeerklärung Erzeuger BioZBW, S. 2, Datenschutzhinweis | P3: Die in der Teilnahmeerklärung angegebenen personenbezogenen Daten […] sind für die Durchführung und Überwachung sowie die Dokumentation im Rahmen des Bio-Zeichens Baden-Württemberg erforderlich.
A4: BIO-0013 | B4: BioZBW | C4: Genossenschaft / zentrale Einrichtung / Zeichennutzer | D4: Administrative Tätigkeiten im QMS der Erzeugergruppe | E4: Verträge | F4: Teilnahmevereinbarung mit dem Gruppenmitglied ausfüllen, unterzeichnen und ablegen | G4: Unterzeichnete Teilnahmevereinbarung mit dem Gruppenmitglied | H4: einmalig | I4: 1 | J4: 15 | K4: 0.25 | L4: 50 | M4: 12.5 | N4: Verordnung (EU) 2018/848; Durchführungsverordnung (EU) 2021/279 | O4: Art. 5 Buchst. b; https://eur-lex.europa.eu/eli/reg/2018/848/oj?locale=de; https://eur-lex.europa.eu/legal-content/DE/ALL/?uri=CELEX%3A32021R0279 | P4: Unterzeichnete Mitgliedsvereinbarungen
A5: BIO-0014 | B5: BioZBW | C5: Genossenschaft / zentrale Einrichtung / Zeichennutzer | D5: Administrative Tätigkeiten als Zeichennutzer | E5: Verträge | F5: Zeichennutzungsvertrag lesen, unterzeichnen und ablegen | G5: Unterzeichneter Zeichennutzungsvertrag | H5: einmalig | I5: 1 | J5: 30 | K5: 0.5 | L5: 50 | M5: 25 | N5: BioZBW – Programmbestimmungen, Stand 01.01.2025 | O5: Programmbestimmungen BioZBW 2025, S. 8, Abschnitt 3.4 | P5: Zeichennutzer sind Verarbeitungs- und Vermarktungsbetriebe […] Dazu schließen sie mit einem Lizenznehmer einen entsprechenden Zeichennutzungsvertrag ab.
A6: BIO-0015 | B6: BioZBW | C6: Genossenschaft / zentrale Einrichtung / Zeichennutzer | D6: Administrative Tätigkeiten als Zeichennutzer | E6: Ausfüllen von Checklisten und Formulare | F6: Datenschutzhinweise zum Zeichennutzungsvertrag lesen und unterzeichnen | G6: Dokumentierte Kenntnisnahme der Datenschutzhinweise zum Zeichennutzungsvertrag | H6: einmalig | I6: 1 | J6: 7.5 | K6: 0.125 | L6: 50 | M6: 6.25 | N6: BioZBW – Datenschutzhinweise zum Zeichennutzungsvertrag, 2024 | O6: Datenschutzhinweise Zeichennutzungsvertrag BioZBW 2024, S. 1, Abschnitt „Zwecke und Rechtsgrundlagen der Verarbeitung“ | P6: Ihre personenbezogenen Daten werden verarbeitet, um den Zeichennutzungsvertrag abschließen und erfüllen zu können.
A7: BIO-0016 | B7: BioZBW | C7: Genossenschaft / zentrale Einrichtung / Zeichennutzer | D7: Administrative Tätigkeiten im QMS der Erzeugergruppe | E7: Ausfüllen von Checklisten und Formulare | F7: Mitglieder- und Meldedatei aktualisieren und jährlich an den Lizenznehmer übermitteln | G7: Aktuelles Mitgliederverzeichnis sowie jährliche Auskunft über die vorliegenden Teilnahmeerklärungen | H7: jährlich sowie bei Änderungen | I7: 1 | J7: 240 | K7: 4 | L7: 30 | M7: 120 | N7: Verordnung (EU) 2018/848; Durchführungsverordnung (EU) 2021/279; BioZBW – Programmbestimmungen, Stand 01.01.2026 | O7: BioZBW-Programmbestimmungen 2026, S. 27, Abschnitt 11.3; VO (EU) 2021/279, Art. 5 Buchst. a | P7: Zeichennutzer […] sind verpflichtet, ihrem Lizenznehmer regelmäßig jährlich zum Stand 31. Oktober […] Auskunft über die bei ihnen vorliegenden Teilnahmeerklärungen von Erzeugern zu geben.
A8: BIO-0017 | B8: BioZBW | C8: Genossenschaft / zentrale Einrichtung / Zeichennutzer | D8: Administrative Tätigkeiten als Zeichennutzer | E8: Eigenkontrolle als Zeichennutzer | F8: Eigenkontrollcheckliste des Zeichennutzers ausfüllen, aktualisieren und ablegen | G8: Durchgängiges Eigenkontrollsystem des Zeichennutzers mit vollständig bearbeiteter Eigenkontrollcheckliste | H8: jährlich (Modellannahme) | I8: 1 | J8: 60 | K8: 1 | L8: 30 | M8: 30 | N8: BioZBW – Programmbestimmungen, Stand 01.01.2026; BioZBW – Eigenkontrolle Zeichennutzer, Version 2024; BioZBW – Zusatzanforderungen für pflanzliche Produkte, Stand 2024 | O8: BioZBW-Programmbestimmungen 2026, S. 14, Abschnitt 6.1; Eigenkontrolle Zeichennutzer 2024; ZA pflanzliche Produkte 2024, S. 8, Abschnitt III.3 | P8: Jeder Zeichennutzer und gegebenenfalls von diesem eingebundene Dienstleister haben ein durchgängiges Eigenkontrollsystem zu führen und mit den vorgegebenen Checklisten nachzuweisen.
A9: BIO-0018 | B9: BioZBW | C9: Genossenschaft / zentrale Einrichtung / Zeichennutzer | D9: Administrative Tätigkeiten im QMS der Erzeugergruppe | E9: Interne Prüfungen innerhalb der Gruppe | F9: Eigenkontrollcheckliste und betriebliche Nachweise des Gruppenmitglieds prüfen, Prüfergebnis dokumentieren und Mitglied freigeben | G9: Geprüfte Eigenkontrollcheckliste und betriebliche Nachweise mit dokumentiertem Prüfergebnis und Freigabestatus | H9: einmalig | I9: 1 | J9: 120 | K9: 2 | L9: 30 | M9: 60 | N9: Verordnung (EU) 2018/848; Durchführungsverordnung (EU) 2021/279 | O9: Art. 36 Abs. 1 Buchst. g; Art. 5 Buchst. c; https://eur-lex.europa.eu/eli/reg/2018/848/oj?locale=de; https://eur-lex.europa.eu/legal-content/DE/ALL/?uri=CELEX%3A32021R0279 | P9: Dokumentierte interne Kontrollen und Kontrollberichte
A10: BIO-0019 | B10: BioZBW | C10: Genossenschaft / zentrale Einrichtung / Zeichennutzer | D10: Administrative Tätigkeiten im QMS der Erzeugergruppe | E10: Interne Prüfungen innerhalb der Gruppe | F10: Maßnahmenpläne prüfen und Prüfergebnis dokumentieren | G10: Geprüfte Maßnahmenpläne | H10: einmalig | I10: 1 | J10: 30 | K10: 0.5 | L10: 30 | M10: 15 | N10: Verordnung (EU) 2018/848; Durchführungsverordnung (EU) 2021/279 | O10: Art. 5 Buchst. f; https://eur-lex.europa.eu/eli/reg/2018/848/oj?locale=de; https://eur-lex.europa.eu/legal-content/DE/ALL/?uri=CELEX%3A32021R0279 | P10: Maßnahmen bei Nichtkonformität und Nachverfolgung
A11: BIO-0020 | B11: BioZBW | C11: Genossenschaft / zentrale Einrichtung / Zeichennutzer | D11: Administrative Tätigkeiten im QMS der Erzeugergruppe | E11: Interne Prüfungen innerhalb der Gruppe | F11: Pflanzenschutzaufzeichnungen prüfen und Prüfergebnis dokumentieren | G11: Geprüfte Pflanzenschutzaufzeichnungen | H11: einmalig | I11: 1 | J11: 60 | K11: 1 | L11: 30 | M11: 30 | N11: Durchführungsverordnung (EU) 2021/279 | O11: Art. 5 Buchst. g; https://eur-lex.europa.eu/legal-content/DE/ALL/?uri=CELEX%3A32021R0279 | P11: Rückverfolgbarkeitsaufzeichnungen zu Betriebsmitteln, Erzeugung, Lagerung und Lieferung
A12: BIO-0021 | B12: BioZBW | C12: Genossenschaft / zentrale Einrichtung / Zeichennutzer | D12: Administrative Tätigkeiten im QMS der Erzeugergruppe | E12: Interne Prüfungen innerhalb der Gruppe | F12: Düngemittelaufzeichnungen prüfen und Prüfergebnis dokumentieren | G12: Geprüfte Düngemittelaufzeichnungen | H12: einmalig | I12: 1 | J12: 60 | K12: 1 | L12: 30 | M12: 30 | N12: Durchführungsverordnung (EU) 2021/279 | O12: Art. 5 Buchst. g; https://eur-lex.europa.eu/legal-content/DE/ALL/?uri=CELEX%3A32021R0279 | P12: Rückverfolgbarkeitsaufzeichnungen zu Betriebsmitteln, Erzeugung, Lagerung und Lieferung
A13: BIO-0022 | B13: BioZBW | C13: Genossenschaft / zentrale Einrichtung / Zeichennutzer | D13: Administrative Tätigkeiten im QMS der Erzeugergruppe | E13: Rückverfolgbarkeits- und Plausibilitätsprüfung | F13: Ernteaufzeichnungen prüfen und Prüfergebnis dokumentieren | G13: Geprüfte Ernteaufzeichnungen | H13: einmalig | I13: 1 | J13: 30 | K13: 0.5 | L13: 30 | M13: 15 | N13: Durchführungsverordnung (EU) 2021/279 | O13: Art. 5 Buchst. g; https://eur-lex.europa.eu/legal-content/DE/ALL/?uri=CELEX%3A32021R0279 | P13: Rückverfolgbarkeitsaufzeichnungen zu Betriebsmitteln, Erzeugung, Lagerung und Lieferung
... A25: BIO-0042 | B25: BioZBW | C25: Genossenschaft / zentrale Einrichtung / Zeichennutzer | D25: Administrative Tätigkeiten im QMS der Erzeugergruppe | E25: QMS-Dokumentation und -lenkung | F25: QMS-Verfahren, Unterlagen und Aufzeichnungen erstellen, aktualisieren und bereitstellen | G25: Aktuelle und vollständig verfügbare QMS-Verfahren, Unterlagen und Aufzeichnungen der Unternehmergruppe | H25: fortlaufend | I25: 1 | J25: 240 | K25: 4 | L25: 30 | M25: 120 | N25: Verordnung (EU) 2018/848; Delegierte Verordnung (EU) 2021/715; Durchführungsverordnung (EU) 2021/279 | O25: VO (EU) 2018/848, Art. 36; VO (EU) 2021/715, Art. 1 Nr. 1 Buchst. b und c; VO (EU) 2021/279, Art. 5 | P25: Entwicklung der IKS-Verfahren und Ausarbeitung der entsprechenden Unterlagen und Aufzeichnungen, Aktualisierung und Verfügbar machen dieser für die IKS-Inspektoren und gegebenenfalls die Mitglieder der Gruppe.
A26: BIO-0043 | B26: BioZBW | C26: Kontroll-/Zertifizierungsstelle | D26: Externe Kontrolle; Bezugsform: Gruppe | E26: Stichprobenkontrollen | F26: QMS anhand der Unterlagen verifizieren und Ergebnis dokumentieren | G26: Verifiziertes QMS | H26: jährlich; gruppenfix, anteilig je Mitglied (n=150) | I26: =1/Annahmen!$C$77 -> 0.0066666667 | J26: 240 | K26: =I26*J26/60 -> 0.026666667 | L26: 30 | M26: =K26*L26 -> 0.8 | N26: Verordnung (EU) 2018/848; Durchführungsverordnung (EU) 2021/279 | O26: Art. 36; Art. 7; https://eur-lex.europa.eu/eli/reg/2018/848/oj?locale=de; https://eur-lex.europa.eu/legal-content/DE/ALL/?uri=CELEX%3A32021R0279 | P26: Verifizierung des internen Kontrollsystems
A27: BIO-0044 | B27: BioZBW | C27: Kontroll-/Zertifizierungsstelle | D27: Externe Kontrolle; Bezugsform: Gruppe | E27: Ausfüllen von Checklisten und Formulare | F27: Prüfergebnisse dokumentieren und Quartalsmeldung an die MBW übermitteln | G27: Dokumentierte Prüfergebnisse sowie fristgerechte Quartalsmeldung der Zertifizierungsstelle | H27: vierteljährlich; 240 Min. als Gesamtmodellwert je Jahr; gruppenfix, anteilig je Mitglied (n=150) | I27: =1/Annahmen!$C$77 -> 0.0066666667 | J27: 240 | K27: =I27*J27/60 -> 0.026666667 | L27: 30 | M27: =K27*L27 -> 0.8 | N27: BioZBW – Programmbestimmungen, Stand 01.01.2026; Durchführungsverordnung (EU) 2021/279 | O27: BioZBW-Programmbestimmungen 2026, S. 28, Abschnitt 11.5; VO (EU) 2021/279, Art. 7 | P27: Über die Zertifizierungstätigkeit ist regelmäßig zu einem Quartalsende ein zusammenfassender Bericht zu erstellen. […] Die Berichte müssen jeweils im darauffolgenden Quartal […] bei der MBW abgegeben werden.
A28: BIO-0047 | B28: BioZBW | C28: Genossenschaft / zentrale Einrichtung / Zeichennutzer | D28: Administrative Tätigkeiten im QMS der Erzeugergruppe | E28: Mitglieder- und Zulassungsmanagement | F28: Mitgliederliste mit Kontrollstatus und Versionsstand aktualisieren | G28: Aktuelle Mitgliederliste mit Status, Kontrollangaben und Versionsstand | H28: bei jeder Änderung | I28: 1 | J28: 15 | K28: 0.25 | L28: 30 | M28: 7.5 | N28: Durchführungsverordnung (EU) 2021/279 | O28: Art. 5 Buchst. a und letzter Absatz | P28: Die in Absatz 1 Buchstabe a genannte Liste der Mitglieder wird vom IKS-Verwalter aktualisiert, sobald sich eines der [...] aufgeführten Elemente ändert.
A29: BIO-0048 | B29: BioZBW | C29: Genossenschaft / zentrale Einrichtung / Zeichennutzer | D29: Administrative Tätigkeiten im QMS der Erzeugergruppe | E29: Qualifikation und Schulung | F29: interne QMS-Kontrolleure ernennen sowie Interessenkonflikte und Qualifikation dokumentieren | G29: Dokumentierte Ernennung, Unabhängigkeit und Qualifikation der interne QMS-Kontrolleure | H29: bei Ernennung und jährlich | I29: 1 | J29: 30 | K29: 0.5 | L29: 30 | M29: 15 | N29: Delegierte Verordnung (EU) 2021/715; Durchführungsverordnung (EU) 2021/279 | O29: VO (EU) 2021/715, Art. 1 Nr. 1 Buchst. c Ziff. vii und ix; VO (EU) 2021/279, Art. 5 Buchst. d und j | P29: jährliche Überprüfung der Erklärungen zu Interessenkonflikten der IKS-Inspektoren
A30: BIO-0049 | B30: BioZBW | C30: Genossenschaft / zentrale Einrichtung / Zeichennutzer | D30: Administrative Tätigkeiten im QMS der Erzeugergruppe | E30: Qualifikation und Schulung | F30: interne QMS-Kontrolleure und Mitglieder schulen und Schulungsnachweise pflegen | G30: Jährliche Schulungen der interne QMS-Kontrolleure und dokumentierte Schulungen der Gruppenmitglieder | H30: jährlich | I30: 1 | J30: 60 | K30: 1 | L30: 30 | M30: 30 | N30: Delegierte Verordnung (EU) 2021/715; Durchführungsverordnung (EU) 2021/279 | O30: VO (EU) 2021/715, Art. 1 Nr. 1 Buchst. b Ziff. iv und v; VO (EU) 2021/279, Art. 5 Buchst. d und e | P30: Schulungen der IKS-Inspektoren, die mindestens einmal jährlich stattfinden [...] Schulungen der Mitglieder der Gruppe zu den IKS-Verfahren
A31: BIO-0050 | B31: BioZBW | C31: Genossenschaft / zentrale Einrichtung / Zeichennutzer | D31: Administrative Tätigkeiten im QMS der Erzeugergruppe | E31: Interne Prüfungen innerhalb der Gruppe | F31: Interne Inspektionen terminieren und Inspektionsplan pflegen | G31: Vom QMS-verantwortliche Person geplante und fristgerecht durchgeführte interne Inspektionen | H31: jährlich | I31: 1 | J31: 30 | K31: 0.5 | L31: 30 | M31: 15 | N31: Delegierte Verordnung (EU) 2021/715 | O31: Art. 1 Nr. 1 Buchst. c Ziff. viii | P31: Anberaumung interner Inspektionen und Sicherstellung ihrer angemessenen Durchführung gemäß dem [...] Plan des IKS-Verwalters
A32: BIO-0051 | B32: BioZBW | C32: Genossenschaft / zentrale Einrichtung / Zeichennutzer | D32: Administrative Tätigkeiten im QMS der Erzeugergruppe | E32: Mitglieder- und Zulassungsmanagement | F32: Neue Mitglieder, Produktionseinheiten oder Tätigkeiten prüfen und Zulassung dokumentieren | G32: Dokumentierte Zulassung neuer Mitglieder, Produktionseinheiten und Tätigkeiten | H32: bei Aufnahme oder Änderung | I32: 1 | J32: 30 | K32: 0.5 | L32: 30 | M32: 15 | N32: Delegierte Verordnung (EU) 2021/715 | O32: Art. 1 Nr. 1 Buchst. b Ziff. iii und Buchst. c Ziff. x | P32: Zulassung neuer Mitglieder oder neuer Produktionseinheiten oder neuer Tätigkeiten bestehender Mitglieder
A33: BIO-0052 | B33: BioZBW | C33: Genossenschaft / zentrale Einrichtung / Zeichennutzer | D33: Administrative Tätigkeiten im QMS der Erzeugergruppe | E33: Kontroll-, Abweichungs- und Beschwerdedokumentation | F33: Erhebliche Verstöße, Mitgliedssperren und Vermarktungsverbote an die Kontrollstelle melden | G33: Unverzügliche Meldung erheblicher oder kritischer Verstöße, Sperren und Vermarktungsverbote | H33: bei Bedarf | I33: 1 | J33: 30 | K33: 0.5 | L33: 30 | M33: 15 | N33: Durchführungsverordnung (EU) 2021/279 | O33: Art. 6 | P33: Der IKS-Verwalter teilt der zuständigen Behörde oder gegebenenfalls der Kontrollbehörde oder Kontrollstelle unverzüglich Folgendes mit
A34: BIO-0053 | B34: BioZBW | C34: Traubenerzeuger / landwirtschaftlicher Betrieb | D34: Traubenerzeuger; Bezugsform: Gruppe | E34: Archivierung von Nachweisen | F34: Vorhandene Betriebsnachweise für das QMS zusammenstellen und der Unternehmergruppe übermitteln | G34: Vollständig zusammengestelltes und an die Unternehmergruppe übermitteltes QMS-Nachweispaket | H34: jährlich | I34: 1 | J34: 30 | K34: 0.5 | L34: 50 | M34: 25 | N34: Verordnung (EU) 2018/848; Durchführungsverordnung (EU) 2021/279 | O34: VO (EU) 2018/848, Art. 36; VO (EU) 2021/279, Art. 5 | P34: Der IKS-Verwalter […] führt über jedes Mitglied […] Aufzeichnungen und bewahrt diese auf […] und stellt die erforderlichen Unterlagen für die amtlichen Kontrollen bereit.
A35: BIO-0054 | B35: BioZBW | C35: Traubenerzeuger / landwirtschaftlicher Betrieb | D35: Traubenerzeuger; Bezugsform: Gruppe | E35: Festlegung und Nachverfolgung von Korrekturmaßnahmen | F35: Umsetzung von Korrekturmaßnahmen dokumentieren und der Unternehmergruppe melden | G35: Dokumentierter Umsetzungsnachweis zu festgelegten Korrekturmaßnahmen und Mitteilung an die Unternehmergruppe | H35: bei Bedarf | I35: 1 | J35: 15 | K35: 0.25 | L35: 50 | M35: 12.5 | N35: Durchführungsverordnung (EU) 2021/279 | O35: Art. 5 Buchst. f | P35: Maßnahmen bei Nichtkonformität […] einschließlich des Zeitplans für ihre Durchführung und der Überwachung ihres Abschlusses.
A36: BIO-0055 | B36: BioZBW | C36: Genossenschaft / zentrale Einrichtung / Zeichennutzer | D36: Administrative Tätigkeiten im QMS der Erzeugergruppe | E36: Verträge | F36: Kontrollvertrag beziehungsweise Kontrollauftrag prüfen, unterzeichnen und ablegen | G36: Dokumentierte Beauftragung der Kontrollstelle für die externe Kontrolle der Unternehmergruppe | H36: einmalig | I36: 1 | J36: 30 | K36: 0.5 | L36: 50 | M36: 25 | N36: Verordnung (EU) 2018/848; Durchführungsverordnung (EU) 2021/279 | O36: VO (EU) 2018/848, Art. 36; VO (EU) 2021/279, Art. 7 | P36: Die Gruppe […] unterliegt einem Kontrollsystem für die amtlichen Kontrollen und anderen amtlichen Tätigkeiten.
A37: BIO-0056 | B37: BioZBW | C37: Genossenschaft / zentrale Einrichtung / Zeichennutzer | D37: Administrative Tätigkeiten im QMS der Erzeugergruppe | E37: QMS-Dokumentation und -lenkung | F37: QMS-Kontrollunterlagen zusammenstellen und der Kontrollstelle bereitstellen | G37: Vollständiges, prüffähiges QMS-Kontrollpaket für die externe Kontrollstelle | H37: jährlich | I37: 1 | J37: 60 | K37: 1 | L37: 30 | M37: 30 | N37: Durchführungsverordnung (EU) 2021/279 | O37: Art. 5 und 7 | P37: Der IKS-Verwalter stellt […] die Dokumente und Aufzeichnungen der Gruppe […] zur Verfügung.
A38: BIO-0057 | B38: BioZBW | C38: Kontroll-/Zertifizierungsstelle | D38: Externe Kontrolle; Bezugsform: Gruppe | E38: Stichprobenkontrollen | F38: Externen QMS-Kontrolltermin abstimmen und erforderliche Kontrollunterlagen anfordern | G38: Abgestimmter Termin und angefordertes Kontrollpaket für die externe QMS-Prüfung | H38: jährlich; gruppenfix, anteilig je Mitglied (n=150) | I38: =1/Annahmen!$C$77 -> 0.0066666667 | J38: 30 | K38: =I38*J38/60 -> 0.0033333333 | L38: 30 | M38: =K38*L38 -> 0.1 | N38: Durchführungsverordnung (EU) 2021/279 | O38: Art. 7 | P38: Die zuständige Behörde oder gegebenenfalls die Kontrollbehörde oder Kontrollstelle überprüft jährlich die Einrichtung und Funktionsweise des IKS.
A39: BIO-0058 | B39: BioZBW | C39: Kontroll-/Zertifizierungsstelle | D39: Externe Kontrolle; Bezugsform: Gruppe | E39: Ausfüllen von Checklisten und Formulare | F39: Zertifizierungsentscheidung dokumentieren und Gruppenzertifikat beziehungsweise Zertifikatsdaten übermitteln | G39: Dokumentierte Zertifizierungsentscheidung und übermittelte Zertifikatsdaten für die Unternehmergruppe | H39: jährlich; gruppenfix, anteilig je Mitglied (n=150) | I39: =1/Annahmen!$C$77 -> 0.0066666667 | J39: 30 | K39: =I39*J39/60 -> 0.0033333333 | L39: 30 | M39: =K39*L39 -> 0.1 | N39: Verordnung (EU) 2018/848 | O39: Art. 36 Abs. 2 in Verbindung mit Art. 35 | P39: Das in Artikel 35 genannte Zertifikat wird für die gesamte Gruppe ausgestellt.
A40: BIO-0059 | B40: BioZBW | C40: Genossenschaft / zentrale Einrichtung / Zeichennutzer | D40: Administrative Tätigkeiten im QMS der Erzeugergruppe | E40: Archivierung von Nachweisen | F40: Gruppenzertifikat prüfen, intern zuordnen und im QMS ablegen | G40: Geprüftes und im QMS abgelegtes Gruppenzertifikat | H40: jährlich | I40: 1 | J40: 15 | K40: 0.25 | L40: 30 | M40: 7.5 | N40: Verordnung (EU) 2018/848 | O40: Art. 36 Abs. 2 in Verbindung mit Art. 35 | P40: Das in Artikel 35 genannte Zertifikat wird für die gesamte Gruppe ausgestellt.
A41: BIO-0060 | B41: BioZBW | C41: Externer Lizenznehmer | D41: Lizenznahme der Erzeugergruppe / Zeichennutzerin | E41: Verträge | F41: Zeichennutzungsvertrag der Genossenschaft prüfen und gegenzeichnen sowie Programmanmeldung weiterleiten | G41: Gegengezeichneter Zeichennutzungsvertrag und programmgemäß registrierte Genossenschaft | H41: einmalig | I41: 1 | J41: 60 | K41: 1 | L41: 30 | M41: 30 | N41: BioZBW – Programmbestimmungen, Stand 01.01.2026 | O41: S. 22, Abschnitt 9.2 | P41: Die Teilnahme als Zeichennutzer ist nur auf der Grundlage eines Zeichennutzungsvertrages mit einem Lizenznehmer möglich.
A42: BIO-0061 | B42: BioZBW | C42: Genossenschaft / zentrale Einrichtung / Zeichennutzer | D42: Administrative Tätigkeiten als Zeichennutzer | E42: Datenaufzeichnung und -pflege | F42: BioZBW-Produktaufstellung aktualisieren und für Kontrollen bereitstellen | G42: Stets aktuelle Aufstellung der mit BioZBW gekennzeichneten und vermarkteten Produkte | H42: jährlich sowie bei Änderungen | I42: 1 | J42: 30 | K42: 0.5 | L42: 30 | M42: 15 | N42: BioZBW – Programmbestimmungen, Stand 01.01.2026 | O42: S. 27, Abschnitt 11.3 | P42: Zeichennutzer sind verpflichtet, eine stets aktuelle Aufstellung der Produkte vorzuhalten, die mit dem Biozeichen Baden-Württemberg gekennzeichnet und vermarktet werden.
A43: BIO-0062 | B43: BioZBW | C43: Genossenschaft / zentrale Einrichtung / Zeichennutzer | D43: Administrative Tätigkeiten als Zeichennutzer | E43: Archivierung von Nachweisen | F43: Qualitätsprüfung administrativ anmelden sowie Ergebnisnachweis zuordnen und bereithalten | G43: Aktueller Qualitätsprüfungsnachweis für BioZBW-Verarbeitungsprodukte | H43: gemäß Zertifikatslaufzeit; im Modell jährlich | I43: 1 | J43: 30 | K43: 0.5 | L43: 30 | M43: 15 | N43: BioZBW – Programmbestimmungen, Stand 01.01.2026; BioZBW – Zusatzanforderungen für pflanzliche Produkte, Stand 2024 | O43: Programmbestimmungen 2026, S. 15–16, Abschnitte 6.4–6.4.1; ZA pflanzliche Produkte 2024, S. 8–9, Abschnitt III.5 | P43: Verarbeitungsprodukte, für die eine Zeichennutzung erfolgt, müssen regelmäßig zu Qualitätsprüfungen angestellt werden. […] Der Qualitätsnachweis erfolgt durch regelmäßige Teilnahme an den Prüfungen der DLG oder an vergleichbaren Qualitätsprüfungen.
A44: BIO-0063 | B44: BioZBW | C44: Externer Lizenznehmer | D44: Laufende teilnehmerbezogene Lizenznehmerverwaltung | E44: Jährliche Teilnehmermeldung | F44: Jahresmeldung der angeschlossenen Erzeuger und Zeichennutzer erstellen, plausibilisieren und an die MBW übermitteln | G44: Jährliche zusammenfassende, nach Produktbereichen getrennte Meldung der angeschlossenen Erzeuger und Zeichennutzer an die MBW | H44: jährlich; teilnehmerbezogen | I44: =1 -> 1 | J44: =Annahmen!$C$91 -> 5 | K44: =I44*J44/60 -> 0.083333333 | L44: 30 | M44: =K44*L44 -> 2.5 | N44: BioZBW – Programmbestimmungen, Stand 01.01.2026 | O44: S. 27–28, Abschnitt 11.4; Zeitansatz siehe ANN-054 | P44: Lizenznehmer sind verpflichtet, jährlich zum 31. Dezember eine zusammenfassende Meldung über die angeschlossenen Erzeuger und Zeichennutzer bei der MBW […] abzugeben.
A45: BIO-0064 | B45: BioZBW | C45: Traubenerzeuger / landwirtschaftlicher Betrieb | D45: Traubenerzeuger; Bezugsform: Gruppe | E45: Ausfüllen von Checklisten und Formulare | F45: Eigenkontrollcheckliste des landwirtschaftlichen Betriebs ausfüllen und ablegen | G45: Vollständig ausgefüllte BioZBW-Eigenkontrollcheckliste des landwirtschaftlichen Betriebs | H45: jährlich (fachlich gesetzte Modellannahme) | I45: 1 | J45: 30 | K45: 0.5 | L45: 50 | M45: 25 | N45: Fachlich gesetzte Modellannahme der Studienleitung; nicht als eigenständige Pflicht in den ausgewerteten BioZBW-Dokumenten belegt | O45: Modellannahme vom 05.08.2026 | P45: Kein wörtliches Quellenzitat; die Pflicht zur Eigenkontrollcheckliste des Traubenerzeugers wurde für die Kostenmodellierung fachlich gesetzt.
A46: BIO-0065 | B46: BioZBW | C46: Kontroll-/Zertifizierungsstelle | D46: Externe Kontrolle; Bezugsform: Zeichennutzer | E46: Kontrollvorbereitung | F46: Jährliche Zeichennutzerkontrolle terminieren und programmspezifische Unterlagen anfordern | G46: Abgestimmter Termin und vollständiges Kontrollpaket der Genossenschaft als Zeichennutzerin | H46: jährlich; gruppenfix, anteilig je Mitglied (n=150) | I46: =1/Annahmen!$C$77 -> 0.0066666667 | J46: 15 | K46: =I46*J46/60 -> 0.0016666667 | L46: 30 | M46: =K46*L46 -> 0.05 | N46: BioZBW – Programmbestimmungen, Stand 01.01.2026 | O46: S. 17, Abschnitt 6.8; S. 27, Abschnitt 11.3; Zeitansatz siehe ANN-046 | P46: Erfassung, Handel, Verarbeitung (Zeichennutzer): 100 %.
A47: BIO-0066 | B47: BioZBW | C47: Kontroll-/Zertifizierungsstelle | D47: Externe Kontrolle; Bezugsform: Zeichennutzer | E47: Dokumentenprüfung und Kontrolldokumentation | F47: Eigenkontrollsystem, Produkt- und Qualitätsnachweise, Waren- und Herkunftsdokumentation, Rückverfolgbarkeit und Kennzeichnung prüfen und Kontrollcheckliste vervollständigen | G47: Dokumentierte jährliche Zeichennutzerkontrolle mit bewerteten Prüfpunkten und nachvollziehbarem Ergebnis | H47: jährlich; gruppenfix, anteilig je Mitglied (n=150) | I47: =1/Annahmen!$C$77 -> 0.0066666667 | J47: 60 | K47: =I47*J47/60 -> 0.0066666667 | L47: 30 | M47: =K47*L47 -> 0.2 | N47: BioZBW – Programmbestimmungen, Stand 01.01.2026; BioZBW-Kombicheckliste 2025 | O47: Programmbestimmungen S. 14–15, Abschnitt 6.2.1; Kombicheckliste S. 2–6; Zeitansatz siehe ANN-047 | P47: Kontrolle/Überprüfung des Eigenkontrollsystems bzw. der Dokumentationen.
A48: BIO-0067 | B48: BioZBW | C48: Kontroll-/Zertifizierungsstelle | D48: Externe Kontrolle; Bezugsform: Mitgliederstichprobe | E48: Stichprobenplanung | F48: Risikobasierte Mitgliederstichprobe auswählen und jährlichen Kontrollplan dokumentieren | G48: Nachvollziehbar ausgewählte Stichprobe von 15 Mitgliedern und dokumentierter Kontrollplan | H48: jährlich; gruppenfix, anteilig je Mitglied (n=150) | I48: =1/Annahmen!$C$77 -> 0.0066666667 | J48: 30 | K48: =I48*J48/60 -> 0.0033333333 | L48: 30 | M48: =K48*L48 -> 0.1 | N48: BioZBW – Programmbestimmungen, Stand 01.01.2026 | O48: S. 17, Abschnitt 6.8; Zeitansatz siehe ANN-043 | P48: Landwirtschaftliche Erzeuger pflanzlicher Produkte: mindestens 10 % jährlich.
A49: BIO-0068 | B49: BioZBW | C49: Kontroll-/Zertifizierungsstelle | D49: Externe Kontrolle; Bezugsform: Mitgliederstichprobe | E49: Administrative Kontrollvorbereitung | F49: Termin und Unterlagen je ausgewähltem Mitglied koordinieren und Kontrollakte vorbereiten | G49: Vorbereitete Kontrollakten für 15 programmspezifische Mitgliederkontrollen | H49: jährlich; 15 Stichproben je Gruppe, anteilig je Mitglied (n=150) | I49: =Annahmen!$C$79/Annahmen!$C$77 -> 0.1 | J49: 15 | K49: =I49*J49/60 -> 0.025 | L49: 30 | M49: =K49*L49 -> 0.75 | N49: BioZBW – Programmbestimmungen, Stand 01.01.2026 | O49: S. 17, Abschnitt 6.8; Zeitansatz siehe ANN-044 | P49: Landwirtschaftliche Erzeuger pflanzlicher Produkte: mindestens 10 % jährlich.
A50: BIO-0069 | B50: BioZBW | C50: Kontroll-/Zertifizierungsstelle | D50: Externe Kontrolle; Bezugsform: Mitgliederstichprobe | E50: Administrative Kontrollnachbereitung | F50: Kontrollcheckliste je Stichprobenmitglied abschließen, Ergebnis und gegebenenfalls Abweichungen dokumentieren und Kontrollakte schließen | G50: Vollständige administrative Abschlussdokumentation für 15 programmspezifische Mitgliederkontrollen | H50: jährlich; 15 Stichproben je Gruppe, anteilig je Mitglied (n=150) | I50: =Annahmen!$C$79/Annahmen!$C$77 -> 0.1 | J50: 15 | K50: =I50*J50/60 -> 0.025 | L50: 30 | M50: =K50*L50 -> 0.75 | N50: BioZBW – Programmbestimmungen, Stand 01.01.2026 | O50: S. 17 und 28, Abschnitte 6.8 und 11.5; Zeitansatz siehe ANN-045 | P50: Landwirtschaftliche Erzeuger pflanzlicher Produkte: mindestens 10 % jährlich.
A51: BIO-0070 | B51: BioZBW | C51: Externer Lizenznehmer | D51: Laufende teilnehmerbezogene Lizenznehmerverwaltung | E51: Programm- und Vertragsüberwachung | F51: Programminhalte und vertragliche Verpflichtungen der angeschlossenen Teilnehmer laufend überwachen | G51: Nachvollziehbar überwachter Teilnehmerstatus und dokumentierte Einhaltung der programmspezifischen und vertraglichen Pflichten | H51: jährlich; teilnehmerbezogen | I51: =1 -> 1 | J51: =Annahmen!$C$87 -> 10 | K51: =I51*J51/60 -> 0.16666667 | L51: 30 | M51: =K51*L51 -> 5 | N51: BioZBW – Programmbestimmungen, Stand 01.01.2026 | O51: S. 7–8, Abschnitt 3.2; Zeitansatz siehe ANN-050 | P51: Sie gewährleisten die ordnungsgemäße Umsetzung und Überwachung der Programminhalte bei den ihnen vertraglich angeschlossenen Erzeugern und Zeichennutzern.
A52: BIO-0071 | B52: BioZBW | C52: Externer Lizenznehmer | D52: Laufende teilnehmerbezogene Lizenznehmerverwaltung | E52: Kontrollorganisation und -überwachung | F52: Vorgesehene Kontrollen veranlassen und deren Durchführung administrativ überwachen | G52: Beauftragte und statusseitig nachverfolgte Kontrollen bei angeschlossenen Erzeugern und Zeichennutzern | H52: jährlich; teilnehmerbezogen | I52: =1 -> 1 | J52: =Annahmen!$C$88 -> 15 | K52: =I52*J52/60 -> 0.25 | L52: 30 | M52: =K52*L52 -> 7.5 | N52: BioZBW – Programmbestimmungen, Stand 01.01.2026 | O52: S. 17–18, Abschnitte 6.7 und 7.1; Zeitansatz siehe ANN-051 | P52: Hierbei werden insbesondere die Lizenznehmer regelmäßig dahingehend überprüft, ob sie ihren vertraglichen Pflichten zur Veranlassung und Überwachung von Kontrollen […] nachkommen.
A53: BIO-0072 | B53: BioZBW | C53: Externer Lizenznehmer | D53: Laufende teilnehmerbezogene Lizenznehmerverwaltung | E53: Prüfergebnis- und Maßnahmenmanagement | F53: Prüfergebnisse zuordnen, Teilnehmerstatus aktualisieren und gewöhnliche Korrekturhinweise nachverfolgen | G53: Vollständig zugeordnete Prüfberichte und nachvollziehbar nachgehaltene Standardabweichungen beziehungsweise Korrekturhinweise | H53: jährlich; teilnehmerbezogen | I53: =1 -> 1 | J53: =Annahmen!$C$89 -> 15 | K53: =I53*J53/60 -> 0.25 | L53: 30 | M53: =K53*L53 -> 7.5 | N53: BioZBW – Programmbestimmungen, Stand 01.01.2026 | O53: S. 28, Abschnitt 11.5; Zeitansatz siehe ANN-052 | P53: Zertifizierungsstellen sind verpflichtet, […] den verantwortlichen Lizenznehmer fortlaufend unverzüglich über alle Prüfergebnisse zu unterrichten.
A54: BIO-0073 | B54: BioZBW | C54: Externer Lizenznehmer | D54: Laufende teilnehmerbezogene Lizenznehmerverwaltung | E54: Teilnehmer- und Stammdatenmanagement | F54: Neuanmeldungen und Stammdatenänderungen verwalten und unverzüglich an die MBW melden | G54: Aktuelle Teilnehmer- und Stammdaten sowie zeitnah an die MBW übermittelte Neu- und Änderungsmeldungen | H54: jährlich; teilnehmerbezogen | I54: =1 -> 1 | J54: =Annahmen!$C$90 -> 15 | K54: =I54*J54/60 -> 0.25 | L54: 30 | M54: =K54*L54 -> 7.5 | N54: BioZBW – Programmbestimmungen, Stand 01.01.2026 | O54: S. 27–28, Abschnitt 11.4; Zeitansatz siehe ANN-053 | P54: Bei Neuanmeldungen oder Änderungen der Stammdaten von Erzeugern oder Zeichennutzern muss der Lizenznehmer die MBW unverzüglich informieren.
A55: BIO-0074 | B55: BioZBW | C55: Externer Lizenznehmer | D55: Anlassbezogene Lizenznehmermaßnahmen außerhalb des Standardjahres | E55: Sanktionierung und Ausschluss | F55: Schwere Verstöße bewerten und erforderliche Sanktionierung beziehungsweise Ausschluss veranlassen und dokumentieren | G55: Dokumentierte, verhältnismäßige Sanktions- oder Ausschlussentscheidung einschließlich erforderlicher Abstimmungen | H55: bei Bedarf; im Basisszenario nicht angesetzt | L55: 30 | N55: BioZBW – Programmbestimmungen, Stand 01.01.2026 | O55: S. 20–21 und 28, Abschnitte 8 und 11.5; Abgrenzung siehe ANN-055 | P55: Bei vorsätzlichem oder nach schriftlicher Ermahnung fortgesetztem Verstoß […] ist der Lizenznehmer verpflichtet, […] Maßnahmen für einen vorübergehenden oder dauerhaften Ausschluss […] zu treffen.

Sheet Kostenrechnung
A1: Kostenrechnung – enge zertifizierungsspezifische Szenarien
A2: Aktuell sind ausschließlich QZBW und BioZBW ohne fachrechtliche/betriebliche Basisadministration. Alle Ergebnisse greifen formelbasiert auf die beiden Anforderungsblätter zu.
A4: Kennzahl | B4: QZBW (EUR) | C4: BioZBW (EUR) | D4: Differenz QZBW – BioZBW (EUR)
A5: Gesamtkosten eng | B5: =SUM(Anford_QZBW_zert_spez!$M$2:$M$55) -> 1099.7 | C5: =SUM(Anford_BioZBW_zert_spez!$M$2:$M$55) -> 1049.9 | D5: =B5-C5 -> 49.8
A6: Gesamtzeit eng (Std.) | B6: =SUM(Anford_QZBW_zert_spez!$K$2:$K$55) -> 34.24 | C6: =SUM(Anford_BioZBW_zert_spez!$K$2:$K$55) -> 33.246667 | D6: =B6-C6 -> 0.99333333
A7: Anzahl enthaltener Tätigkeiten | B7: =COUNT(Anford_QZBW_zert_spez!$M$2:$M$55) -> 53 | C7: =COUNT(Anford_BioZBW_zert_spez!$M$2:$M$55) -> 53 | D7: =B7-C7 -> 0
A9: Abstimmung | B9: Aktuelle Arbeitsversion (EUR) | C9: Interne V3 vor Abgrenzung (EUR) | D9: Methodische Veränderung (EUR) | E9: Status
A10: QZBW eng | B10: =B5 -> 1099.7 | C10: 1693.75 | D10: =B10-C10 -> -594.05 | E10: INFO – methodisch bereinigt
A11: BioZBW eng | B11: =C5 -> 1049.9 | C11: 1358.75 | D11: =B11-C11 -> -308.85 | E11: INFO – methodisch bereinigt
A12: Differenz QZBW – BioZBW | B12: =B10-B11 -> 49.8 | C12: 335 | D12: =B12-C12 -> -285.2 | E12: INFO – methodisch bereinigt
A15: Akteursgruppe | B15: QZBW Kosten (EUR) | C15: BioZBW Kosten (EUR) | D15: Differenz (EUR) | E15: QZBW Zeit (Std.) | F15: BioZBW Zeit (Std.) | H15: Rollenaufteilung Genossenschaft
A16: Traubenerzeuger / landwirtschaftlicher Betrieb | B16: =SUMIFS(Anford_QZBW_zert_spez!$M$2:$M$55,Anford_QZBW_zert_spez!$C$2:$C$55,$A16) -> 137.5 | C16: =SUMIFS(Anford_BioZBW_zert_spez!$M$2:$M$55,Anford_BioZBW_zert_spez!$C$2:$C$55,$A16) -> 87.5 | D16: =B16-C16 -> 50 | E16: =SUMIFS(Anford_QZBW_zert_spez!$K$2:$K$55,Anford_QZBW_zert_spez!$C$2:$C$55,$A16) -> 2.75 | F16: =SUMIFS(Anford_BioZBW_zert_spez!$K$2:$K$55,Anford_BioZBW_zert_spez!$C$2:$C$55,$A16) -> 1.75 | H16: Rolle der Genossenschaft | I16: QZBW (EUR) | J16: BioZBW (EUR) | K16: Differenz (EUR)
A17: Genossenschaft / zentrale Einrichtung / Zeichennutzer | B17: =SUMIFS(Anford_QZBW_zert_spez!$M$2:$M$55,Anford_QZBW_zert_spez!$C$2:$C$55,$A17) -> 898.75 | C17: =SUMIFS(Anford_BioZBW_zert_spez!$M$2:$M$55,Anford_BioZBW_zert_spez!$C$2:$C$55,$A17) -> 898.75 | D17: =B17-C17 -> 0 | E17: =SUMIFS(Anford_QZBW_zert_spez!$K$2:$K$55,Anford_QZBW_zert_spez!$C$2:$C$55,$A17) -> 29.375 | F17: =SUMIFS(Anford_BioZBW_zert_spez!$K$2:$K$55,Anford_BioZBW_zert_spez!$C$2:$C$55,$A17) -> 29.375 | H17: Administrative Tätigkeiten im QMS der Erzeugergruppe | I17: =SUMIFS(Anford_QZBW_zert_spez!$M$2:$M$49,Anford_QZBW_zert_spez!$D$2:$D$49,$H17) -> 772.5 | J17: =SUMIFS(Anford_BioZBW_zert_spez!$M$2:$M$50,Anford_BioZBW_zert_spez!$D$2:$D$50,$H17) -> 757.5 | K17: =I17-J17 -> 15
A18: Separate Zeichennutzer / Verarbeitungsstufe außerhalb der Genossenschaft | B18: =SUMIFS(Anford_QZBW_zert_spez!$M$2:$M$55,Anford_QZBW_zert_spez!$C$2:$C$55,$A18) -> 0 | C18: =SUMIFS(Anford_BioZBW_zert_spez!$M$2:$M$55,Anford_BioZBW_zert_spez!$C$2:$C$55,$A18) -> 0 | D18: =B18-C18 -> 0 | E18: =SUMIFS(Anford_QZBW_zert_spez!$K$2:$K$55,Anford_QZBW_zert_spez!$C$2:$C$55,$A18) -> 0 | F18: =SUMIFS(Anford_BioZBW_zert_spez!$K$2:$K$55,Anford_BioZBW_zert_spez!$C$2:$C$55,$A18) -> 0 | H18: Administrative Tätigkeiten als Zeichennutzer | I18: =SUMIFS(Anford_QZBW_zert_spez!$M$2:$M$49,Anford_QZBW_zert_spez!$D$2:$D$49,$H18) -> 126.25 | J18: =SUMIFS(Anford_BioZBW_zert_spez!$M$2:$M$50,Anford_BioZBW_zert_spez!$D$2:$D$50,$H18) -> 141.25 | K18: =I18-J18 -> -15
A19: Kontroll-/Zertifizierungsstelle | B19: =SUMIFS(Anford_QZBW_zert_spez!$M$2:$M$55,Anford_QZBW_zert_spez!$C$2:$C$55,$A19) -> 3.45 | C19: =SUMIFS(Anford_BioZBW_zert_spez!$M$2:$M$55,Anford_BioZBW_zert_spez!$C$2:$C$55,$A19) -> 3.65 | D19: =B19-C19 -> -0.2 | E19: =SUMIFS(Anford_QZBW_zert_spez!$K$2:$K$55,Anford_QZBW_zert_spez!$C$2:$C$55,$A19) -> 0.115 | F19: =SUMIFS(Anford_BioZBW_zert_spez!$K$2:$K$55,Anford_BioZBW_zert_spez!$C$2:$C$55,$A19) -> 0.12166667 | H19: Summe Genossenschaft | I19: =SUM(I17:I18) -> 898.75 | J19: =SUM(J17:J18) -> 898.75 | K19: =I19-J19 -> 0
A20: Externer Lizenznehmer | B20: =SUMIFS(Anford_QZBW_zert_spez!$M$2:$M$55,Anford_QZBW_zert_spez!$C$2:$C$55,$A20) -> 60 | C20: =SUMIFS(Anford_BioZBW_zert_spez!$M$2:$M$55,Anford_BioZBW_zert_spez!$C$2:$C$55,$A20) -> 60 | D20: =B20-C20 -> 0 | E20: =SUMIFS(Anford_QZBW_zert_spez!$K$2:$K$55,Anford_QZBW_zert_spez!$C$2:$C$55,$A20) -> 2 | F20: =SUMIFS(Anford_BioZBW_zert_spez!$K$2:$K$55,Anford_BioZBW_zert_spez!$C$2:$C$55,$A20) -> 2
A21: Laufende teilnehmerbezogene Lizenznehmerverwaltung | B21: =SUMIFS(Anford_QZBW_zert_spez!$M$2:$M$55,Anford_QZBW_zert_spez!$C$2:$C$55,$A$20,Anford_QZBW_zert_spez!$D$2:$D$55,$A21) -> 30 | C21: =SUMIFS(Anford_BioZBW_zert_spez!$M$2:$M$55,Anford_BioZBW_zert_spez!$C$2:$C$55,$A$20,Anford_BioZBW_zert_spez!$D$2:$D$55,$A21) -> 30 | D21: =B21-C21 -> 0 | E21: =SUMIFS(Anford_QZBW_zert_spez!$K$2:$K$55,Anford_QZBW_zert_spez!$C$2:$C$55,$A$20,Anford_QZBW_zert_spez!$D$2:$D$55,$A21) -> 1 | F21: =SUMIFS(Anford_BioZBW_zert_spez!$K$2:$K$55,Anford_BioZBW_zert_spez!$C$2:$C$55,$A$20,Anford_BioZBW_zert_spez!$D$2:$D$55,$A21) -> 1
A22: Lizenznahme der Erzeugergruppe / Zeichennutzerin | B22: =SUMIFS(Anford_QZBW_zert_spez!$M$2:$M$55,Anford_QZBW_zert_spez!$C$2:$C$55,$A$20,Anford_QZBW_zert_spez!$D$2:$D$55,$A22) -> 30 | C22: =SUMIFS(Anford_BioZBW_zert_spez!$M$2:$M$55,Anford_BioZBW_zert_spez!$C$2:$C$55,$A$20,Anford_BioZBW_zert_spez!$D$2:$D$55,$A22) -> 30 | D22: =B22-C22 -> 0 | E22: =SUMIFS(Anford_QZBW_zert_spez!$K$2:$K$55,Anford_QZBW_zert_spez!$C$2:$C$55,$A$20,Anford_QZBW_zert_spez!$D$2:$D$55,$A22) -> 1 | F22: =SUMIFS(Anford_BioZBW_zert_spez!$K$2:$K$55,Anford_BioZBW_zert_spez!$C$2:$C$55,$A$20,Anford_BioZBW_zert_spez!$D$2:$D$55,$A22) -> 1
A23: Prozesskategorie | B23: QZBW Kosten (EUR) | C23: BioZBW Kosten (EUR) | D23: Differenz (EUR) | H23: Ergänzte Prozesskategorien aus den Prüfschritten 2 und 3
A24: Archivierung von Nachweisen | B24: =SUMIFS(Anford_QZBW_zert_spez!$M$2:$M$55,Anford_QZBW_zert_spez!$E$2:$E$55,$A24) -> 47.5 | C24: =SUMIFS(Anford_BioZBW_zert_spez!$M$2:$M$55,Anford_BioZBW_zert_spez!$E$2:$E$55,$A24) -> 47.5 | D24: =B24-C24 -> 0 | H24: Prozesskategorie | I24: QZBW (EUR) | J24: BioZBW (EUR) | K24: Differenz (EUR)
A25: Eigenkontrolle als Zeichennutzer | B25: =SUMIFS(Anford_QZBW_zert_spez!$M$2:$M$55,Anford_QZBW_zert_spez!$E$2:$E$55,$A25) -> 30 | C25: =SUMIFS(Anford_BioZBW_zert_spez!$M$2:$M$55,Anford_BioZBW_zert_spez!$E$2:$E$55,$A25) -> 30 | D25: =B25-C25 -> 0 | H25: Kontrollvorbereitung | I25: =SUMIFS(Anford_QZBW_zert_spez!$M$2:$M$55,Anford_QZBW_zert_spez!$E$2:$E$55,$H25) -> 0.05 | J25: =SUMIFS(Anford_BioZBW_zert_spez!$M$2:$M$55,Anford_BioZBW_zert_spez!$E$2:$E$55,$H25) -> 0.05 | K25: =I25-J25 -> 0
A26: Ausfüllen von Checklisten und Formulare | B26: =SUMIFS(Anford_QZBW_zert_spez!$M$2:$M$55,Anford_QZBW_zert_spez!$E$2:$E$55,$A26) -> 214.65 | C26: =SUMIFS(Anford_BioZBW_zert_spez!$M$2:$M$55,Anford_BioZBW_zert_spez!$E$2:$E$55,$A26) -> 164.65 | D26: =B26-C26 -> 50 | H26: Dokumentenprüfung und Kontrolldokumentation | I26: =SUMIFS(Anford_QZBW_zert_spez!$M$2:$M$55,Anford_QZBW_zert_spez!$E$2:$E$55,$H26) -> 0.2 | J26: =SUMIFS(Anford_BioZBW_zert_spez!$M$2:$M$55,Anford_BioZBW_zert_spez!$E$2:$E$55,$H26) -> 0.2 | K26: =I26-J26 -> 0
A27: Datenaufzeichnung und -pflege | B27: =SUMIFS(Anford_QZBW_zert_spez!$M$2:$M$55,Anford_QZBW_zert_spez!$E$2:$E$55,$A27) -> 50 | C27: =SUMIFS(Anford_BioZBW_zert_spez!$M$2:$M$55,Anford_BioZBW_zert_spez!$E$2:$E$55,$A27) -> 65 | D27: =B27-C27 -> -15 | H27: Stichprobenplanung | I27: =SUMIFS(Anford_QZBW_zert_spez!$M$2:$M$55,Anford_QZBW_zert_spez!$E$2:$E$55,$H27) -> 0.1 | J27: =SUMIFS(Anford_BioZBW_zert_spez!$M$2:$M$55,Anford_BioZBW_zert_spez!$E$2:$E$55,$H27) -> 0.1 | K27: =I27-J27 -> 0
A28: Kontroll-, Abweichungs- und Beschwerdedokumentation | B28: =SUMIFS(Anford_QZBW_zert_spez!$M$2:$M$55,Anford_QZBW_zert_spez!$E$2:$E$55,$A28) -> 75 | C28: =SUMIFS(Anford_BioZBW_zert_spez!$M$2:$M$55,Anford_BioZBW_zert_spez!$E$2:$E$55,$A28) -> 90 | D28: =B28-C28 -> -15 | H28: Administrative Kontrollvorbereitung | I28: =SUMIFS(Anford_QZBW_zert_spez!$M$2:$M$55,Anford_QZBW_zert_spez!$E$2:$E$55,$H28) -> 0.65 | J28: =SUMIFS(Anford_BioZBW_zert_spez!$M$2:$M$55,Anford_BioZBW_zert_spez!$E$2:$E$55,$H28) -> 0.75 | K28: =I28-J28 -> -0.1
A29: Festlegung und Nachverfolgung von Korrekturmaßnahmen | B29: =SUMIFS(Anford_QZBW_zert_spez!$M$2:$M$55,Anford_QZBW_zert_spez!$E$2:$E$55,$A29) -> 42.5 | C29: =SUMIFS(Anford_BioZBW_zert_spez!$M$2:$M$55,Anford_BioZBW_zert_spez!$E$2:$E$55,$A29) -> 42.5 | D29: =B29-C29 -> 0 | H29: Administrative Kontrollnachbereitung | I29: =SUMIFS(Anford_QZBW_zert_spez!$M$2:$M$55,Anford_QZBW_zert_spez!$E$2:$E$55,$H29) -> 0.65 | J29: =SUMIFS(Anford_BioZBW_zert_spez!$M$2:$M$55,Anford_BioZBW_zert_spez!$E$2:$E$55,$H29) -> 0.75 | K29: =I29-J29 -> -0.1
A30: Interne Prüfungen innerhalb der Gruppe | B30: =SUMIFS(Anford_QZBW_zert_spez!$M$2:$M$55,Anford_QZBW_zert_spez!$E$2:$E$55,$A30) -> 157.5 | C30: =SUMIFS(Anford_BioZBW_zert_spez!$M$2:$M$55,Anford_BioZBW_zert_spez!$E$2:$E$55,$A30) -> 150 | D30: =B30-C30 -> 7.5 | H30: Programm- und Vertragsüberwachung | I30: =SUMIFS(Anford_QZBW_zert_spez!$M$2:$M$55,Anford_QZBW_zert_spez!$E$2:$E$55,$H30) -> 5 | J30: =SUMIFS(Anford_BioZBW_zert_spez!$M$2:$M$55,Anford_BioZBW_zert_spez!$E$2:$E$55,$H30) -> 5 | K30: =I30-J30 -> 0
A31: QMS-Dokumentation und -lenkung | B31: =SUMIFS(Anford_QZBW_zert_spez!$M$2:$M$55,Anford_QZBW_zert_spez!$E$2:$E$55,$A31) -> 150 | C31: =SUMIFS(Anford_BioZBW_zert_spez!$M$2:$M$55,Anford_BioZBW_zert_spez!$E$2:$E$55,$A31) -> 150 | D31: =B31-C31 -> 0 | H31: Kontrollorganisation und -überwachung | I31: =SUMIFS(Anford_QZBW_zert_spez!$M$2:$M$55,Anford_QZBW_zert_spez!$E$2:$E$55,$H31) -> 7.5 | J31: =SUMIFS(Anford_BioZBW_zert_spez!$M$2:$M$55,Anford_BioZBW_zert_spez!$E$2:$E$55,$H31) -> 7.5 | K31: =I31-J31 -> 0
A32: Rückverfolgbarkeits- und Plausibilitätsprüfung | B32: =SUMIFS(Anford_QZBW_zert_spez!$M$2:$M$55,Anford_QZBW_zert_spez!$E$2:$E$55,$A32) -> 135 | C32: =SUMIFS(Anford_BioZBW_zert_spez!$M$2:$M$55,Anford_BioZBW_zert_spez!$E$2:$E$55,$A32) -> 105 | D32: =B32-C32 -> 30 | H32: Prüfergebnis- und Maßnahmenmanagement | I32: =SUMIFS(Anford_QZBW_zert_spez!$M$2:$M$55,Anford_QZBW_zert_spez!$E$2:$E$55,$H32) -> 7.5 | J32: =SUMIFS(Anford_BioZBW_zert_spez!$M$2:$M$55,Anford_BioZBW_zert_spez!$E$2:$E$55,$H32) -> 7.5 | K32: =I32-J32 -> 0
A33: Stichprobenkontrollen | B33: =SUMIFS(Anford_QZBW_zert_spez!$M$2:$M$55,Anford_QZBW_zert_spez!$E$2:$E$55,$A33) -> 0.9 | C33: =SUMIFS(Anford_BioZBW_zert_spez!$M$2:$M$55,Anford_BioZBW_zert_spez!$E$2:$E$55,$A33) -> 0.9 | D33: =B33-C33 -> 0 | H33: Teilnehmer- und Stammdatenmanagement | I33: =SUMIFS(Anford_QZBW_zert_spez!$M$2:$M$55,Anford_QZBW_zert_spez!$E$2:$E$55,$H33) -> 7.5 | J33: =SUMIFS(Anford_BioZBW_zert_spez!$M$2:$M$55,Anford_BioZBW_zert_spez!$E$2:$E$55,$H33) -> 7.5 | K33: =I33-J33 -> 0
A34: Verträge | B34: =SUMIFS(Anford_QZBW_zert_spez!$M$2:$M$55,Anford_QZBW_zert_spez!$E$2:$E$55,$A34) -> 105 | C34: =SUMIFS(Anford_BioZBW_zert_spez!$M$2:$M$55,Anford_BioZBW_zert_spez!$E$2:$E$55,$A34) -> 105 | D34: =B34-C34 -> 0 | H34: Jährliche Teilnehmermeldung | I34: =SUMIFS(Anford_QZBW_zert_spez!$M$2:$M$55,Anford_QZBW_zert_spez!$E$2:$E$55,$H34) -> 2.5 | J34: =SUMIFS(Anford_BioZBW_zert_spez!$M$2:$M$55,Anford_BioZBW_zert_spez!$E$2:$E$55,$H34) -> 2.5 | K34: =I34-J34 -> 0
A35: Mitglieder- und Zulassungsmanagement | B35: =SUMIFS(Anford_QZBW_zert_spez!$M$2:$M$55,Anford_QZBW_zert_spez!$E$2:$E$55,$A35) -> 15 | C35: =SUMIFS(Anford_BioZBW_zert_spez!$M$2:$M$55,Anford_BioZBW_zert_spez!$E$2:$E$55,$A35) -> 22.5 | D35: =B35-C35 -> -7.5 | H35: Summe ergänzte Prozesskategorien | I35: =SUM(I25:I34) -> 31.65 | J35: =SUM(J25:J34) -> 31.85 | K35: =I35-J35 -> -0.2
A36: Qualifikation und Schulung | B36: =SUMIFS(Anford_QZBW_zert_spez!$M$2:$M$55,Anford_QZBW_zert_spez!$E$2:$E$55,$A36) -> 45 | C36: =SUMIFS(Anford_BioZBW_zert_spez!$M$2:$M$55,Anford_BioZBW_zert_spez!$E$2:$E$55,$A36) -> 45 | D36: =B36-C36 -> 0 | H36: Gesamt aller Prozesskategorien | I36: =SUM(B24:B36)+I35 -> 1099.7 | J36: =SUM(C24:C36)+J35 -> 1049.9 | K36: =I36-J36 -> 49.8
A37: Personaltyp | B37: Stundensatz (EUR/Std.) | C37: QZBW Summe Fallzahlen | D37: BioZBW Summe Fallzahlen | E37: Datenstatus
A38: Betriebsleiter*in / Geschäftsführer*in | B38: =Annahmen!C7 -> 50 | C38: =SUMIFS(Anford_QZBW_zert_spez!$I$2:$I$55,Anford_QZBW_zert_spez!$L$2:$L$55,$B38) -> 10 | D38: =SUMIFS(Anford_BioZBW_zert_spez!$I$2:$I$55,Anford_BioZBW_zert_spez!$L$2:$L$55,$B38) -> 9 | E38: Modellwert aus Ausgangsdatei; empirischer Status nicht belegt
A39: Verwaltungskraft | B39: =Annahmen!C8 -> 30 | C39: =SUMIFS(Anford_QZBW_zert_spez!$I$2:$I$55,Anford_QZBW_zert_spez!$L$2:$L$55,$B39) -> 33.22 | D39: =SUMIFS(Anford_BioZBW_zert_spez!$I$2:$I$55,Anford_BioZBW_zert_spez!$L$2:$L$55,$B39) -> 34.246667 | E39: Modellwert aus Ausgangsdatei; empirischer Status nicht belegt
A40: Facharbeiter*in | B40: =Annahmen!C9 -> 25 | C40: =SUMIFS(Anford_QZBW_zert_spez!$I$2:$I$55,Anford_QZBW_zert_spez!$L$2:$L$55,$B40) -> 1 | D40: =SUMIFS(Anford_BioZBW_zert_spez!$I$2:$I$55,Anford_BioZBW_zert_spez!$L$2:$L$55,$B40) -> 1 | E40: Modellwert aus Ausgangsdatei; empirischer Status nicht belegt
A43: Methodische Hinweise
A44: Die enge Rechnung summiert ausschließlich Zeilen mit „In enger Kostenrechnung enthalten = Ja“. Betrachtet wird die gesamte Weinwertschöpfungskette vom Traubenerzeuger bis zur Kontrollstelle.
A45: Monetarisiert werden nur zusätzliche zertifizierungsspezifische administrative Tätigkeiten: Informationen erfassen, übertragen, prüfen, verarbeiten, ablegen oder kommunizieren.
A46: Die Erstellung fachrechtlich ohnehin erforderlicher Dünge-, Pflanzenschutz-, Ernte- oder Verkaufsaufzeichnungen ist ausgeschlossen. Die zusätzliche gruppenbezogene Prüfung dieser vorhandenen Nachweise bleibt enthalten.
A47: Physische Standort-, Prozess- und Vor-Ort-Prüfungen sind ausgeschlossen. Ob die Anforderungen ausgeführt wurden, wird administrativ bereits über Eigenkontrollchecklisten, Nachweisprüfung und Kontrollprotokolle beziehungsweise physisch bei der Vor-Ort-Kontrolle geprüft; eine zusätzliche Monetarisierung würde Doppelzählungen begünstigen.
A48: Für BioZBW ist eine rechtskonforme, bereits EU-ökologisch zertifizierte Weinwertschöpfungskette Baseline. Direkte EU-Gruppenanforderungen und beschlossene funktionale Übertragungen aus QZBW sind im Anforderungsblatt getrennt gekennzeichnet.
A49: HACCP ist bei der Weinbereitung/Verarbeitung fachlich relevant, wird aber nicht als separater QZBW- oder BioZBW-Zusatzkostenblock berechnet, weil ein HACCP-basiertes Verfahren bereits nach allgemeinem Lebensmittelhygienerecht erforderlich ist.
A50: Kontrollstellenkosten sind modellierte interne Arbeitszeit. Sie sind nicht mit Kontrollgebühren, Rechnungen oder Förderzahlungen gleichzusetzen.
A51: Die SankeyMATIC-Codes enthalten ausschließlich QZBW und BioZBW – jeweils nur zertifizierungsspezifisch – und werden mit vorgeschaltetem Gesamtflow aus den enthaltenen Zeilen dieser Arbeitsmappe neu erzeugt.
A52: Die Tätigkeiten der Genossenschaft werden getrennt nach „Administrative Tätigkeiten im QMS der Erzeugergruppe“ und „Administrative Tätigkeiten als Zeichennutzer“ ausgewiesen. Normativ belegte, aber nur über analoge Zeitansätze monetarisierte QMS-Pflichten sind in den Annahmen ausdrücklich als noch empirisch zu validieren gekennzeichnet.
A53: Die Tätigkeiten der Genossenschaft werden getrennt nach „Administrative Tätigkeiten im QMS der Erzeugergruppe“ und „Administrative Tätigkeiten als Zeichennutzer“ ausgewiesen. Weitere QMS-Pflichten ohne belastbaren Zeitansatz bleiben in den Anforderungsblättern sichtbar, werden aber nicht monetarisiert.
A54: Die frühere QZBW-Position Rückstandsuntersuchungen (240 EUR) ist ausgeschlossen: Für Wein, Sekt und Perlwein ist in der produktspezifischen Kontrollfrequenztabelle kein Rückstandsuntersuchungsplan ausgewiesen.
... A57: Die laufende Lizenznehmerverwaltung wird für QZBW und BioZBW symmetrisch mit insgesamt 60 Minuten beziehungsweise 30,00 EUR je Mitglied und Jahr angesetzt. Die einmalige Vertragsprüfung bleibt separat; seltene Sanktionierungs- und Ausschlussfälle sind dokumentiert, aber im Standardjahr nicht monetarisiert.

Sheet Quellen
A1: Quellenregister
A2: Dokumente und Rechtsgrundlagen der Arbeitsversion. Dokumenttitel und offizielle Online-Fundstellen dienen der wissenschaftlichen Nachvollziehbarkeit.
A3: Quellen-ID | B3: Programm | C3: Dokumenttitel | D3: Version / Stand | E3: Dateiname | F3: Offizielle Fundstelle / Bezugsquelle | G3: Behandelte Akteursrollen | H3: Verwendung in der Kostenrechnung | I3: Bemerkungen
A4: SRC-001 | B4: Beide | C4: Kostenanalyse – interne Ausgangsarbeitsmappe | D4: V2e, 2026-07-19 | E4: Kostenschätzungen-data-V2e_korrigiert_2026-07-19.xlsx | F4: In dieser Arbeitsmappe dokumentiert; kein externer Dateiverweis | G4: Alle Akteursrollen | H4: Primäre Quelle für Zeitansätze, Fallzahlen und Stundensätze | I4: Datei bleibt unverändert; interne Herkunftsangabe wird vor einer späteren Publikationsfassung neutralisiert.
A5: SRC-002 | B5: QZBW | C5: Zusatzanforderungen Wein | D5: 2025 | E5: QZBW - ZA Wein 2025.pdf | F5: https://mbw.imageplant.de/ | G5: Traubenerzeuger; Zeichennutzer; Weinbereitung | H5: QZBW-Anforderungen, Qualitätsnachweis und HACCP-Einordnung | I5: Qualitätsnachweis S. 3 und 7; HACCP S. 7.
A6: SRC-003 | B6: BioZBW | C6: Zusatzanforderungen für pflanzliche Produkte | D6: 2024 | E6: ZA BioZBW Pflanzlich 2024.pdf | F6: https://mbw.imageplant.de/ | G6: Erzeuger; Zeichennutzer; Verarbeitung | H6: BioZBW-Anforderungen und HACCP-Einordnung | I6: Analytische Anforderungen sind produktbezogen auf Säfte/Essige; keine getrennte Grundlage für Wein-Zucker/Säure/Alkohol/Sensorik/Nmin.
A7: SRC-004 | B7: QZBW; methodisches Übertragungsvorbild | C7: Anforderungen an Erzeugergruppen | D7: 2023 | E7: Anforderungen Erzeugergruppen Stand 2023_2.pdf | F7: https://mbw.imageplant.de/ | G7: Erzeugergruppe; QMS; interne Audits und Kontrollen | H7: QZBW-Gruppenzertifizierung und dokumentiertes Übertragungsvorbild für nicht unmittelbar belegte BioZBW-Detailpositionen | I7: Keine normative BioZBW-Quelle; eine Verwendung als Übertragungsvorbild wird ausschließlich unter Zahlenherkunft/Übertragungsstatus ausgewiesen.
A8: SRC-005 | B8: BioZBW | C8: Verordnung (EU) 2018/848 | D8: konsolidierter Rechtsbezug | E8: Ökoverordnung 2018_848.pdf | F8: https://eur-lex.europa.eu/eli/reg/2018/848/oj?locale=de | G8: Unternehmergruppe; QMS | H8: Rechtsgrundlage Gruppenzertifizierung | I8: Art. 36; https://eur-lex.europa.eu/eli/reg/2018/848/oj?locale=de
A9: SRC-006 | B9: BioZBW | C9: Durchführungsverordnung (EU) 2021/279 | D9: 2021 | E9: Ökoverordnung 2021_279.pdf | F9: https://eur-lex.europa.eu/legal-content/DE/ALL/?uri=CELEX%3A32021R0279 | G9: Mitglieder; QMS; Kontrollstelle | H9: Dokumente, Aufzeichnungen, Nichtkonformität und externe Verifizierung | I9: Art. 4 bis 7; https://eur-lex.europa.eu/legal-content/DE/ALL/?uri=CELEX%3A32021R0279
A10: SRC-007 | B10: Beide | C10: Verordnung (EG) Nr. 852/2004 über Lebensmittelhygiene | D10: konsolidiert 2021-03-24 | E10: EUR-Lex | F10: https://eur-lex.europa.eu/legal-content/DE/ALL/?uri=CELEX%3A02004R0852-20210324 | G10: Zeichennutzer; Weinbereitung/Verarbeitung | H10: Fachrechtliche HACCP-Baseline | I10: Art. 5 gilt für Verarbeitung nach der Primärproduktion; Primärproduktion ist ausgenommen.
A11: SRC-008 | B11: Fachrechtliche Baseline | C11: Weinverordnung | D11: geltende Fassung | E11: Gesetze im Internet | F11: https://www.gesetze-im-internet.de/weinv_1995/BJNR063010995.html | G11: Weinbereitung/Verarbeitung; Antragsteller Qualitätsweinprüfung | H11: Analytischer und sensorischer Untersuchungsbefund der amtlichen Qualitätsweinprüfung | I11: §§ 22 und 23 sowie Anlage 10; https://www.gesetze-im-internet.de/weinv_1995/anlage_10.html
A12: SRC-009 | B12: Fachrechtliche Baseline | C12: Düngeverordnung | D12: geltende Fassung | E12: Gesetze im Internet | F12: https://www.gesetze-im-internet.de/d_v_2017/__4.html | G12: Traubenerzeuger | H12: Ermittlung des verfügbaren Stickstoffs und Düngebedarfsermittlung | I12: § 4 Abs. 4; Nmin-Bodenprobe ist eine mögliche, nicht generell die einzige Ermittlungsmethode.
A13: SRC-010 | B13: QZBW | C13: SankeyMATIC-Code 1 | D13: v2 | E13: Sankey_Code_02_QZBW_nur_zertifizierungsspezifisch_v2.txt | F13: Im Blatt „SankeyMATIC-Codes“ dieser Arbeitsmappe enthalten | G13: Visualisierung | H13: Aus den enthaltenen Zeilen der Arbeitsversion neu generiert | I13: Zertifizierungsspezifisches QZBW-Szenario; Code und vorgeschalteter Gesamtflow werden aus den enthaltenen QZBW-Zeilen dieser Arbeitsmappe neu erzeugt.
A14: SRC-011 | B14: BioZBW | C14: SankeyMATIC-Code 2 | D14: v2 | E14: Sankey_Code_04_BioZBW_nur_zertifizierungsspezifisch_v2.txt | F14: Im Blatt „SankeyMATIC-Codes“ dieser Arbeitsmappe enthalten | G14: Visualisierung | H14: Aus den enthaltenen Zeilen der Arbeitsversion neu generiert | I14: Zertifizierungsspezifisches BioZBW-Szenario; Code und vorgeschalteter Gesamtflow werden aus den enthaltenen BioZBW-Zeilen dieser Arbeitsmappe neu erzeugt.
... A33: SRC-030 | B33: QZBW | C33: Teilnahmevereinbarung Gruppenzertifizierung – pflanzliche Bereiche | D33: Stand 2023 | E33: Teilnahmevereinbarung QZBW Gruppenzertifizierung Pflanze 2023.pdf | F33: https://mbw.imageplant.de/ | G33: Erzeuger; Erzeugergruppe; externer Lizenznehmer; Zertifizierungsstelle | H33: Direkte vertragliche Einbindung des Gruppenmitglieds, Korrekturmeldungen, Kontrollauftrag und externe Lizenznehmerbeziehung | I33: Zentrale Quelle für die in V8 korrigierte Rollen- und Datenflusszuordnung.

Sheet Annahmen
A1: ID
A2: Untersuchungsgegenstand ist die gesamte Weinwertschöpfungskette. Monetarisiert werden ausschließlich eindeutig zertifizierungsbedingte, überwiegend am Schreibtisch ausgeführte Tätigkeiten der Erfassung, Übertragung, Prüfung, Verarbeitung, Ablage oder Kommunikation von Informationen. Physische Standort- und Vor-Ort-Kontrollen sowie fachrechtliche Baseline-Aufwände werden nicht eingerechnet.
A5: Zentrale Rechenannahmen
A6: Annahmen-ID | B6: Parameter | C6: Wert | D6: Einheit | E6: Betroffenes Programm | F6: Betroffener Akteur | G6: Begründung | H6: Quelle / Herleitung | I6: Unsicherheit | J6: Status
A7: ANN-001 | B7: Stundensatz Betriebsleitung/Geschäftsführung | C7: 50 | D7: EUR/Stunde | E7: Beide | F7: Traubenerzeuger / Leitung | G7: Aus der internen Ausgangsarbeitsmappe übernommen | H7: Kostenpositionen_korr | I7: Empirischer Status nicht belegt | J7: Verwendet
A8: ANN-002 | B8: Stundensatz Verwaltungskraft | C8: 30 | D8: EUR/Stunde | E8: Beide | F8: Genossenschaft / Zeichennutzer / Kontrollstelle | G8: Aus der internen Ausgangsarbeitsmappe übernommen | H8: Kostenpositionen_korr | I8: Empirischer Status nicht belegt | J8: Verwendet
A9: ANN-003 | B9: Stundensatz Facharbeiter*in | C9: 25 | D9: EUR/Stunde | E9: Beide | F9: Mehrere | G9: Aus der internen Ausgangsarbeitsmappe übernommen | H9: Kostenpositionen_korr | I9: Empirischer Status nicht belegt | J9: Verwendet
A10: ANN-004 | B10: Berechnung Gesamtzeit | C10: Fallzahl × Minuten je Vorgang ÷ 60 | D10: Stunden | E10: Beide | F10: Alle | G10: Transparente Formel je Tätigkeit | H10: Methodische Festlegung dieser Version | I10: Niedrig | J10: Verwendet
A11: ANN-005 | B11: Systemgrenze | C11: Gesamte Weinwertschöpfungskette | D11: Scope | E11: Beide | F11: Traubenerzeuger bis Kontrollstelle | G11: Betrachtet werden Traubenerzeuger, Erzeugergemeinschaft, Zeichennutzer, Weinbereitung/Verarbeitung und Kontrollstelle | H11: Abstimmung 2026-07-23 | I11: Niedrig | J11: Verwendet
A12: ANN-006 | B12: Administrative Tätigkeit | C12: Erfassen, übertragen, prüfen, verarbeiten, ablegen oder kommunizieren von Informationen | D12: Definition | E12: Beide | F12: Alle | G12: Fokus auf Schreibtischtätigkeiten, die durch Digitalisierung oder kooperative Datennutzung erleichtert werden können | H12: Abstimmung 2026-07-23 | I12: Niedrig | J12: Verwendet
A13: ANN-007 | B13: QZBW-Baseline | C13: Rechtskonforme Weinwertschöpfungskette ohne QZBW | D13: Baseline | E13: QZBW | F13: Alle | G13: Nur zusätzlicher QZBW-Aufwand zählt | H13: Aufgabenstellung und Abstimmung | I13: Niedrig | J13: Verwendet
A14: ANN-008 | B14: BioZBW-Baseline | C14: Rechtskonforme, bereits EU-ökologisch zertifizierte Weinwertschöpfungskette | D14: Baseline | E14: BioZBW | F14: Alle | G14: Normale EU-Öko-Zertifizierung wird nicht erneut als BioZBW-Zusatzaufwand berechnet | H14: Aufgabenstellung und Abstimmung | I14: Niedrig | J14: Verwendet
A15: ANN-009 | B15: Prüfung vorhandener Betriebsaufzeichnungen | C15: Nur zusätzliche Prüfung einbezogen | D15: Abgrenzung | E15: Beide | F15: Gruppeninterne Prüfungen | G15: Erstellung der zugrunde liegenden Dünge-, Pflanzenschutz-, Ernte- oder Verkaufsaufzeichnungen bleibt Baseline | H15: Abstimmung 2026-07-23 | I15: Niedrig | J15: Verwendet
A16: ANN-010 | B16: Physische Standort- und Vor-Ort-Kontrollen | C16: Aus enger Rechnung ausgeschlossen | D16: Abgrenzung | E16: Beide | F16: Zeichennutzer / Kontrollstelle | G16: Keine reine Schreibtischtätigkeit; administrative Nachweisprüfung ist bereits separat erfasst | H16: Abstimmung 2026-07-23 | I16: Niedrig | J16: Verwendet
A17: ANN-011 | B17: HACCP | C17: Anforderung ja, separater Zusatzkostenblock nein | D17: Baseline | E17: Beide | F17: Weinbereitung/Verarbeitung | G17: HACCP ist bereits nach allgemeinem Lebensmittelhygienerecht erforderlich; QZBW/BioZBW kontrollieren den vorhandenen Nachweis | H17: Art. 5 VO (EG) 852/2004; https://eur-lex.europa.eu/legal-content/DE/ALL/?uri=CELEX%3A02004R0852-20210324 | I17: Niedrig | J17: Verwendet
A18: ANN-012 | B18: BioZBW-Gruppenzertifizierung | C18: Direkte EU-Grundlage und programmspezifische Extrapolation getrennt kennzeichnen | D18: Quellenlogik | E18: BioZBW | F18: Unternehmergruppe / QMS | G18: Mitgliedsvereinbarung, Mitgliederliste, interne Kontrollen, Maßnahmen und Rückverfolgbarkeit sind weitgehend direkt belegt; Formate und Zeichennutzungsunterlagen teilweise extrapoliert | H18: Art. 36 VO 2018/848; Art. 5 bis 7 VO 2021/279 | I18: Mittel | J18: Verwendet
A19: ANN-013 | B19: Betriebliche Eigenprüfung | C19: 1 | D19: pro Jahr | E19: BioZBW | F19: Zeichennutzer / Betrieb | G19: Gemäß Aufgabenstellung jährlich | H19: Aufgabenstellung 2026-07-23 | I19: Zeitansatz bleibt Modellwert | J19: Verwendet
A20: ANN-014 | B20: Kontrollstellenaufwand versus Kontrollgebühren | C20: Getrennte Kostenperspektiven | D20: Abgrenzung | E20: Beide | F20: Kontroll-/Zertifizierungsstelle | G20: Modelliert wird Arbeitszeit der Kontrollstelle; keine belegten Gebühren, Rechnungen oder Förderzahlungen | H20: Interne Ausgangsarbeitsmappe | I20: Gebührenhöhe nicht belegt | J20: Verwendet
A21: ANN-015 | B21: Fallzahlen | C21: Werte je Kostenposition aus Ausgangsmodell | D21: Vorgänge/Bezugsgröße | E21: Beide | F21: Alle | G21: Unverändert übernommen; keine neuen empirischen Werte | H21: Kostenpositionen_korr, Spalte M | I21: Bezugszeitraum teilweise unklar | J21: Verwendet
A22: ANN-016 | B22: Zeitansätze | C22: Modellwerte aus Ausgangsmodell | D22: Minuten je Vorgang | E22: Beide | F22: Alle | G22: Abweichende Kommentarschätzungen bleiben als Unsicherheitsbereiche sichtbar; kein neuer Mittelwert | H22: Kostenpositionen_korr, Spalte N und Kommentare | I22: Mittel | J22: Verwendet
A23: ANN-017 | B23: Numerische Neuschätzungen | C23: Ja – ausschließlich transparent gekennzeichnete analoge Modellannahmen für neu identifizierte administrative Tätigkeiten | D23: Qualitätssicherung | E23: Beide | F23: Alle | G23: Nach der Harmonisierung mit der Datenflussanalyse werden normative, bislang unbepreiste Tätigkeiten mit zentralen Modellwerten ergänzt. Sie sind nicht empirisch erhoben und müssen validiert werden. | H23: Harmonisierung AP Kostenanalyse/Datenflussanalyse 2026-08-02 | I23: Hoch | J23: Verwendet
A24: ANN-018 | B24: Spätere Publikationsfassung | C24: Interne Entwicklungsbezeichnungen entfernen | D24: Redaktioneller Folgeschritt | E24: Beide | F24: Alle | G24: Interner Prüfpfad bleibt archiviert; Ergebnistabellen des Abschlussberichts werden neutral formuliert und Änderungen zum Zwischenbericht methodisch erläutert | H24: Abstimmung 2026-07-23 | I24: Nicht Bestandteil dieser Arbeitsversion | J24: Vorgemerkt
A25: ANN-019 | B25: Formulierungslogik der Anforderungsblätter | C25: Soll-Zustand – Objekt plus Verb – Quellenbeleg in derselben Zeile | D25: Darstellungsregel | E25: Beide | F25: Alle | G25: Fachliche Anforderung, auszuführende administrative Tätigkeit und Quellenbeleg werden ohne Doppelung getrennt dargestellt | H25: Abstimmung 2026-07-24 | I25: Niedrig | J25: Verwendet
A26: ANN-020 | B26: Programmspezifische Quellenlogik | C26: Normative Quelle strikt von Zahlenherkunft trennen | D26: Darstellungsregel | E26: Beide | F26: Alle | G26: QZBW-Blatt nennt keine BioZBW-Unterlage als Anforderungsquelle und umgekehrt; Übertragungen erscheinen nur unter Zahlenherkunft/Übertragungsstatus | H26: Abstimmung 2026-07-24 | I26: Niedrig | J26: Verwendet
A27: ANN-021 | B27: Weinanalytik und Sensorik | C27: Fachrechtlicher Untersuchungsbefund statt einzelner QZBW-Zusatzkosten | D27: Baseline | E27: QZBW | F27: Weinbereitung/Verarbeitung | G27: Alkohol, vergärbarer Zucker, Gesamtsäure und Sensorik sind Bestandteile der amtlichen Qualitätsweinprüfung; nur der QZBW-Qualitätsnachweis wird separat ausgewiesen | H27: Weinverordnung §§ 22 und 23 sowie Anlage 10; https://www.gesetze-im-internet.de/weinv_1995/anlage_10.html | I27: Niedrig | J27: Verwendet
A28: ANN-022 | B28: Nmin | C28: Keine eigenständige QZBW-Analyseposition | D28: Baseline | E28: Beide | F28: Traubenerzeuger | G28: Erforderlich ist die Ermittlung und Dokumentation des verfügbaren Stickstoffs/Düngebedarfs; eine eigene Nmin-Laboranalyse ist nur eine mögliche Methode | H28: § 4 Abs. 4 Düngeverordnung; https://www.gesetze-im-internet.de/d_v_2017/__4.html | I28: Niedrig | J28: Verwendet
A29: ANN-023 | B29: SankeyMATIC-Szenarien | C29: Nur QZBW und BioZBW – jeweils zertifizierungsspezifisch | D29: Visualisierung | E29: Beide | F29: Alle | G29: Beide Codes beginnen mit einem Gesamtflow und verzweigen anschließend nach Akteur, Prozesskategorie und Tätigkeit | H29: Abstimmung 2026-07-24 | I29: Niedrig | J29: Verwendet
A30: ANN-024 | B30: Rollen- und Systembegriffsabgrenzung | C30: Erzeugergruppe/Unternehmergruppe bleibt Zeichennutzer beziehungsweise Zertifikatsinhaber und wird nicht zum Lizenznehmer; QZBW verwendet QMS, EU-Bio verwendet QMS. Die monetarisierten Teilprozesse werden überschneidungsfrei ausgewiesen. | D30: Abgrenzung | E30: Beide | F30: Erzeugergemeinschaft / Zeichennutzer / Lizenznehmer | G30: Die Gruppe übernimmt gegenüber ihren Mitgliedern interne Bündelungs-, Kontroll- und Dokumentationsfunktionen, bleibt aber selbst durch Zeichennutzungsvertrag an einen separaten Lizenznehmer angebunden. | H30: QZBW-Programmbestimmungen 2025, Abschnitte 3.2 bis 3.5, 6.3 und 10.2; Anforderungen an Erzeugergruppen 2023, Abschnitte 1.2 bis 7; VO (EU) 2018/848 Art. 36; VO (EU) 2021/715; VO (EU) 2021/279 Art. 5 bis 7 | I30: Niedrig | J30: Verwendet
A31: Ausschlussregister – interne Arbeitsfassung
A32: Der Ausschluss bedeutet nicht, dass die Anforderungen unwichtig sind. Er zeigt, dass sie außerhalb der engen Kostenrechnung digital unterstützbarer administrativer Tätigkeiten liegen, bereits zur fachrechtlichen Baseline gehören oder nicht belastbar quantifiziert werden konnten.
A33: Ausschluss-ID | B33: Programm | C33: Ursprungszeile | D33: Ursprüngliche Position | E33: Ursprünglicher Betrag | F33: Ursprüngliche Quelle / Regelgrundlage | G33: Plausible ursprüngliche Aufnahmelogik | H33: Aktueller Prüfungsbefund / Ausschlussgrund | I33: Aktuelle Behandlung
A34: EX-001 | B34: QZBW | C34: Kostenpositionen_korr!36:36 | D34: Weinkellerei prüfen | E34: 30.00 EUR | F34: QZBW-Programmbestimmungen 2026; BioZBW-Programmbestimmungen 2026; Ursprungsmodell | G34: Plausible Rekonstruktion: Die Anforderungen an Erzeugergruppen verlangen interne Audits aller zentralen Standorte, an denen Gruppenerzeugnisse aufbereitet, gelagert oder abgepackt werden. | H34: Ausgeschlossen: physische Standort- beziehungsweise Prozessprüfung; keine reine administrative Schreibtischtätigkeit. | I34: Anforderung bleibt im Anforderungsblatt sichtbar; Betrag fließt nicht in Kostenrechnung oder aktuellen Sankey-Code ein.
A35: EX-002 | B35: QZBW | C35: Kostenpositionen_korr!37:37 | D35: Abfüllbereich prüfen | E35: 30.00 EUR | F35: QZBW-Programmbestimmungen 2026; BioZBW-Programmbestimmungen 2026; Ursprungsmodell | G35: Plausible Rekonstruktion: Die Anforderungen an Erzeugergruppen verlangen interne Audits aller zentralen Standorte, an denen Gruppenerzeugnisse aufbereitet, gelagert oder abgepackt werden. | H35: Ausgeschlossen: physische Standort- beziehungsweise Prozessprüfung; keine reine administrative Schreibtischtätigkeit. | I35: Anforderung bleibt im Anforderungsblatt sichtbar; Betrag fließt nicht in Kostenrechnung oder aktuellen Sankey-Code ein.
A36: EX-003 | B36: QZBW | C36: Kostenpositionen_korr!38:38 | D36: Etikettierung prüfen | E36: 15.00 EUR | F36: QZBW-Programmbestimmungen 2026; BioZBW-Programmbestimmungen 2026; Ursprungsmodell | G36: Plausible Rekonstruktion: Die Anforderungen an Erzeugergruppen verlangen interne Audits aller zentralen Standorte, an denen Gruppenerzeugnisse aufbereitet, gelagert oder abgepackt werden. | H36: Ausgeschlossen: physische Standort- beziehungsweise Prozessprüfung; keine reine administrative Schreibtischtätigkeit. | I36: Anforderung bleibt im Anforderungsblatt sichtbar; Betrag fließt nicht in Kostenrechnung oder aktuellen Sankey-Code ein.
A37: EX-004 | B37: QZBW | C37: Kostenpositionen_korr!39:39 | D37: Rohstofflager prüfen | E37: 60.00 EUR | F37: QZBW-Programmbestimmungen 2026; BioZBW-Programmbestimmungen 2026; Ursprungsmodell | G37: Plausible Rekonstruktion: Die Anforderungen an Erzeugergruppen verlangen interne Audits aller zentralen Standorte, an denen Gruppenerzeugnisse aufbereitet, gelagert oder abgepackt werden. | H37: Ausgeschlossen: physische Standort- beziehungsweise Prozessprüfung; keine reine administrative Schreibtischtätigkeit. | I37: Anforderung bleibt im Anforderungsblatt sichtbar; Betrag fließt nicht in Kostenrechnung oder aktuellen Sankey-Code ein.
A38: EX-005 | B38: QZBW | C38: Kostenpositionen_korr!40:40 | D38: Maschinen prüfen | E38: 15.00 EUR | F38: QZBW-Programmbestimmungen 2026; BioZBW-Programmbestimmungen 2026; Ursprungsmodell | G38: Plausible Rekonstruktion: Die Anforderungen an Erzeugergruppen verlangen interne Audits aller zentralen Standorte, an denen Gruppenerzeugnisse aufbereitet, gelagert oder abgepackt werden. | H38: Ausgeschlossen: physische Standort- beziehungsweise Prozessprüfung; keine reine administrative Schreibtischtätigkeit. | I38: Anforderung bleibt im Anforderungsblatt sichtbar; Betrag fließt nicht in Kostenrechnung oder aktuellen Sankey-Code ein.
A39: EX-006 | B39: QZBW | C39: Kostenpositionen_korr!41:41 | D39: Flaschenlager prüfen | E39: 30.00 EUR | F39: QZBW-Programmbestimmungen 2026; BioZBW-Programmbestimmungen 2026; Ursprungsmodell | G39: Plausible Rekonstruktion: Die Anforderungen an Erzeugergruppen verlangen interne Audits aller zentralen Standorte, an denen Gruppenerzeugnisse aufbereitet, gelagert oder abgepackt werden. | H39: Ausgeschlossen: physische Standort- beziehungsweise Prozessprüfung; keine reine administrative Schreibtischtätigkeit. | I39: Anforderung bleibt im Anforderungsblatt sichtbar; Betrag fließt nicht in Kostenrechnung oder aktuellen Sankey-Code ein.
A40: EX-007 | B40: BioZBW | C40: Kostenpositionen_korr!36:36 | D40: Weinkellerei prüfen | E40: 30.00 EUR | F40: QZBW-Programmbestimmungen 2026; BioZBW-Programmbestimmungen 2026; Ursprungsmodell | G40: Plausible Rekonstruktion: Die Anforderungen an Erzeugergruppen verlangen interne Audits aller zentralen Standorte, an denen Gruppenerzeugnisse aufbereitet, gelagert oder abgepackt werden. | H40: Ausgeschlossen: physische Standort- beziehungsweise Prozessprüfung; keine reine administrative Schreibtischtätigkeit. | I40: Anforderung bleibt im Anforderungsblatt sichtbar; Betrag fließt nicht in Kostenrechnung oder aktuellen Sankey-Code ein.
A41: EX-008 | B41: BioZBW | C41: Kostenpositionen_korr!37:37 | D41: Abfüllbereich prüfen | E41: 30.00 EUR | F41: QZBW-Programmbestimmungen 2026; BioZBW-Programmbestimmungen 2026; Ursprungsmodell | G41: Plausible Rekonstruktion: Die Anforderungen an Erzeugergruppen verlangen interne Audits aller zentralen Standorte, an denen Gruppenerzeugnisse aufbereitet, gelagert oder abgepackt werden. | H41: Ausgeschlossen: physische Standort- beziehungsweise Prozessprüfung; keine reine administrative Schreibtischtätigkeit. | I41: Anforderung bleibt im Anforderungsblatt sichtbar; Betrag fließt nicht in Kostenrechnung oder aktuellen Sankey-Code ein.
A42: EX-009 | B42: BioZBW | C42: Kostenpositionen_korr!38:38 | D42: Etikettierung prüfen | E42: 15.00 EUR | F42: QZBW-Programmbestimmungen 2026; BioZBW-Programmbestimmungen 2026; Ursprungsmodell | G42: Plausible Rekonstruktion: Die Anforderungen an Erzeugergruppen verlangen interne Audits aller zentralen Standorte, an denen Gruppenerzeugnisse aufbereitet, gelagert oder abgepackt werden. | H42: Ausgeschlossen: physische Standort- beziehungsweise Prozessprüfung; keine reine administrative Schreibtischtätigkeit. | I42: Anforderung bleibt im Anforderungsblatt sichtbar; Betrag fließt nicht in Kostenrechnung oder aktuellen Sankey-Code ein.
A43: EX-010 | B43: BioZBW | C43: Kostenpositionen_korr!39:39 | D43: Rohstofflager prüfen | E43: 60.00 EUR | F43: QZBW-Programmbestimmungen 2026; BioZBW-Programmbestimmungen 2026; Ursprungsmodell | G43: Plausible Rekonstruktion: Die Anforderungen an Erzeugergruppen verlangen interne Audits aller zentralen Standorte, an denen Gruppenerzeugnisse aufbereitet, gelagert oder abgepackt werden. | H43: Ausgeschlossen: physische Standort- beziehungsweise Prozessprüfung; keine reine administrative Schreibtischtätigkeit. | I43: Anforderung bleibt im Anforderungsblatt sichtbar; Betrag fließt nicht in Kostenrechnung oder aktuellen Sankey-Code ein.
A44: EX-011 | B44: BioZBW | C44: Kostenpositionen_korr!40:40 | D44: Maschinen prüfen | E44: 15.00 EUR | F44: QZBW-Programmbestimmungen 2026; BioZBW-Programmbestimmungen 2026; Ursprungsmodell | G44: Plausible Rekonstruktion: Die Anforderungen an Erzeugergruppen verlangen interne Audits aller zentralen Standorte, an denen Gruppenerzeugnisse aufbereitet, gelagert oder abgepackt werden. | H44: Ausgeschlossen: physische Standort- beziehungsweise Prozessprüfung; keine reine administrative Schreibtischtätigkeit. | I44: Anforderung bleibt im Anforderungsblatt sichtbar; Betrag fließt nicht in Kostenrechnung oder aktuellen Sankey-Code ein.
... A61: EX-028 | B61: QZBW | C61: Kostenpositionen_korr!45:45 | D61: Rückstandsuntersuchungen organisieren und Ergebnisse dokumentieren | E61: 240.00 EUR | F61: QZBW-Programmbestimmungen 2025, Abschnitte 6.6 und 6.9 | G61: Plausible Rekonstruktion: Die allgemeine Lizenznehmerverantwortung für Prüfpläne wurde als gruppenbezogener Wein-Aufwand interpretiert. | H61: Ausgeschlossen: Die produktspezifische Kontrollfrequenztabelle weist für Wein, Sekt und Perlwein keine Rückstandsuntersuchung aus; zudem wäre primär der Lizenznehmer verantwortlich und eine direkte Beauftragung des Zeichennutzers nur in Absprache möglich. | I61: Im Vollblatt als ausgeschlossene frühere Modellposition sichtbar; kein Betrag in Kostenrechnung, reduziertem Sankey-Datensatz oder Sankey-Code.
A62: ANN-025 | B62: Warenflusstrennung QZBW/BioZBW | C62: 1 | D62: Vorgang/Jahr | E62: Beide | F62: Genossenschaft als Zeichennutzer | G62: Beide Programme verlangen eine nachvollziehbare Trennung von Programmware und Nichtprogrammware. Für die fortlaufende Pflicht wird ein jährlicher Modellvorgang angesetzt. | H62: QZBW ZA Wein 2025, S. 7, Abschnitt III.6; BioZBW ZA pflanzliche Produkte 2024, S. 9, Abschnitt III.6 | I62: Mittlere Unsicherheit: Zeitansatz analog aus dem bestehenden BioZBW-Modell, nicht empirisch erhoben | J62: Verwendet
A63: ANN-026 | B63: Bereitstellung vorhandener Betriebsnachweise für das QMS | C63: 30 | D63: Minuten je Mitglied/Jahr | E63: Beide | F63: Traubenerzeuger | G63: Zusammenstellen, Vollständigkeit prüfen und an die Gruppe übermitteln; Erstellung der Basisnachweise ausgeschlossen | H63: Analogie zu Formular-/Nachweisübermittlung in V7 | I63: Hoch – nicht empirisch erhoben | J63: Verwendet
A64: ANN-027 | B64: Meldung der Umsetzung von Korrekturmaßnahmen | C64: 15 | D64: Minuten je Ereignis | E64: Beide | F64: Traubenerzeuger | G64: Nur Dokumentation und Rückmeldung, keine physische Umsetzung | H64: Analogie zu kurzen Formular-/Kommunikationsvorgängen in V7 | I64: Hoch – Fallhäufigkeit und Zeit nicht empirisch erhoben | J64: Verwendet
A65: ANN-028 | B65: QMS-Steuerungsaufgaben | C65: 15 | D65: bis 60 Minuten je Vorgang | E65: Beide | F65: Erzeugergruppe | G65: Je nach Tätigkeit: Statuspflege 15 Min.; Zulassung/Qualifikation/Planung 30 Min.; Schulungsdokumentation oder Rückverfolgbarkeitstest 60 Min. | H65: Analogie zu vorhandenen Verwaltungs- und Prüftätigkeiten in V7 | I65: Hoch – nicht empirisch erhoben | J65: Verwendet
A66: ANN-029 | B66: Externe Kontrollvorbereitung und Zertifikatsadministration | C66: 30 | D66: Minuten je Vorgang | E66: Beide | F66: Kontrollstelle | G66: Termin-/Unterlagenkoordination und Zertifikatsentscheidung getrennt von Vor-Ort-Kontrolle und Kontrollstellenmeldung | H66: Analogie zu vorhandenen Kontrollstellen-Verwaltungstätigkeiten in V7 | I66: Hoch – Abgrenzung empirisch zu prüfen | J66: Verwendet
A67: ANN-030 | B67: QMS-Kontrollpaket der Erzeugergruppe | C67: 60 | D67: Minuten je Jahr | E67: Beide | F67: Erzeugergruppe | G67: Zusammenstellen und Übermitteln vorhandener QMS-Unterlagen; laufende Dokumentenpflege separat | H67: Analogie zu Dokumentenbündelung und Übermittlung in V7 | I67: Hoch – nicht empirisch erhoben | J67: Verwendet
A68: ANN-031 | B68: Externer Lizenznehmer | C68: 60 | D68: Minuten je Gruppenaufnahme | E68: Beide | F68: Externer Lizenznehmer | G68: Prüfung/Gegenzeichnung des Zeichennutzungsvertrags und Weiterleitung der Programmanmeldung | H68: Rollenprüfung; Analogie zu Vertrags- und Meldevorgängen | I68: Hoch – Tätigkeitsumfang und Stundensatz empirisch zu prüfen | J68: Verwendet
A69: ANN-032 | B69: BioZBW-Eigenkontrolle Erzeuger | C69: Keine separate Position | D69: Abgrenzung | E69: BioZBW | F69: Traubenerzeuger | G69: Keine programmspezifische Erzeuger-Eigenkontrollcheckliste gefunden; EU-Recht verlangt interne Kontrolle durch das QMS der Gruppe | H69: BioZBW ZA Pflanzliche Produkte 2025; BioZBW Eigenkontrolle Zeichennutzer 2024; VO (EU) 2018/848 und 2021/279 | I69: Mittel | J69: Verwendet
A70: ANN-033 | B70: BioZBW-Warenflusstrennung beim Erzeuger | C70: Aus enger Rechnung ausgeschlossen | D70: Baseline/Rollenabgrenzung | E70: BioZBW | F70: Traubenerzeuger | G70: EU-Öko-Baseline und bisherige Quelle richtet sich an Zeichennutzer; BioZBW-Zeichennutzerpflicht bleibt enthalten | H70: BioZBW ZA Pflanzliche Produkte 2025, Abschnitt III.6; BioZBW Eigenkontrolle Zeichennutzer 2024 | I70: Niedrig | J70: Verwendet
A71: ANN-034 | B71: Unterschiedliche Zielsysteme der APs | C71: Datenflussanalyse bildet alle relevanten Nachweise und Datenflüsse ab; Kostenanalyse nur zusätzlichen Zertifizierungsaufwand | D71: Methodische Abgrenzung | E71: Beide | F71: Alle | G71: Doppelte Darstellung eines Nachweises in Fachrechts- und QMS-Prozess ist in der Datenflussanalyse zulässig; in der Kostenrechnung keine doppelte Monetarisierung | H71: Harmonisierung 2026-08-02 | I71: Niedrig | J71: Verwendet
A72: ANN-035 | B72: BioZBW-Produktaufstellung | C72: 30 | D72: Minuten je Jahr | E72: BioZBW | F72: Zeichennutzer | G72: Aktualisieren, plausibilisieren und für Kontrollen bereitstellen | H72: Analogie zu Listenpflege und kurzer Nachweisadministration | I72: Hoch – nicht empirisch erhoben | J72: Verwendet
A73: ANN-036 | B73: BioZBW-Qualitätsprüfungsnachweis | C73: 30 | D73: Minuten je Prüfzyklus; im Modell jährlich | E73: BioZBW | F73: Zeichennutzer | G73: Nur Anmeldung, Zuordnung und Bereithaltung des Nachweises; Prüfung, Probe und Labor ausgeschlossen | H73: Analogie zur QZBW-Qualitätsnachweisposition | I73: Hoch – Prüforganisation und tatsächliche Frequenz empirisch zu prüfen | J73: Verwendet
A74: ANN-037 | B74: Jahresmeldung des BioZBW-Lizenznehmers | C74: 60 | D74: Minuten je Jahr | E74: BioZBW | F74: Externer Lizenznehmer | G74: Zusammenstellung, Prüfung, Trennung nach Produktbereichen und Übermittlung an MBW | H74: Analogie zu Vertrags- und Meldeadministration | I74: Hoch – nicht empirisch erhoben | J74: Verwendet
A75: ANN-038 | B75: Lohnverarbeitung | C75: Nicht im Basisszenario | D75: Bedingte Anforderung | E75: BioZBW | F75: Zeichennutzer | G75: Vereinbarung und Kontrollstelleninformation nur bei ausgelagerten Verarbeitungsschritten | H75: BioZBW-Programmbestimmungen 2026, S. 23–24, Abschnitt 9.3 | I75: Niedrig hinsichtlich Norm; Auslöser fallspezifisch | J75: Nicht monetarisiert
A76: ANN-039 | B76: BioZBW-Informationspflichten auf Anfrage/bei Änderung | C76: Nicht im Standardjahr | D76: Ereignisabhängige Anforderung | E76: BioZBW | F76: Erzeuger/Zeichennutzer | G76: Produktionsauskunft und Stammdatenänderung nur bei Anfrage oder tatsächlicher Änderung | H76: BioZBW-Programmbestimmungen 2026, S. 27, Abschnitt 11.3 | I76: Niedrig hinsichtlich Norm; Häufigkeit offen | J76: Nicht monetarisiert
A77: ANN-040 | B77: Referenzgruppengröße für gruppenfixe Kontrollstellenkosten | C77: 150 | D77: aktive Mitglieder je Gruppe | E77: QZBW und BioZBW | F77: Kontroll-/Zertifizierungsstelle | G77: Gruppenfixe Kontrollstellentätigkeiten werden anteilig einem Mitglied zugerechnet (1/150). | H77: Festgelegtes Referenzszenario der Kostenanalyse, 21.08.2026 | I77: Referenzannahme; Abhängigkeit von der Gruppengröße in diesem Schritt noch nicht als Sensitivität modelliert | J77: Verwendet
A78: ANN-041 | B78: QZBW-Stichprobenumfang der externen Mitgliederkontrolle | C78: =ROUNDUP(SQRT($C$77),0) -> 13 | D78: Mitgliederkontrollen je Gruppe und Jahr | E78: QZBW | F78: Kontroll-/Zertifizierungsstelle | G78: Standardfall: aufgerundete Quadratwurzel der 150 Gruppenmitglieder. | H78: QZBW-Programmbestimmungen 2026, S. 19–20, Abschnitt 6.3 | I78: Stichprobe kann risikobasiert auf 15 erhöht oder bei wirksamem QMS auf 10 reduziert werden; hier Standardfall. | J78: Verwendet
A79: ANN-042 | B79: BioZBW-Stichprobenumfang für die Kontrolle programmspezifischer Zusatzanforderungen | C79: =ROUNDUP($C$77*10%,0) -> 15 | D79: Mitgliederkontrollen je Gruppe und Jahr | E79: BioZBW | F79: Kontroll-/Zertifizierungsstelle | G79: Mindestens 10 % der landwirtschaftlichen Erzeuger pflanzlicher Produkte; bei n=150 ergeben sich 15 Kontrollen. | H79: BioZBW-Programmbestimmungen 2026, S. 17, Abschnitt 6.8 | I79: Die EU-Öko-Grundkontrolle und deren 5-%-Nachinspektionsregel werden nicht als BIOZBW-spezifischer Zusatzaufwand monetarisiert. | J79: Verwendet
A80: ANN-043 | B80: Risikobasierte Auswahl und Dokumentation des jährlichen Mitglieder-Kontrollplans | C80: 30 | D80: Minuten je Gruppe und Jahr | E80: QZBW und BioZBW | F80: Kontroll-/Zertifizierungsstelle | G80: Mitgliederstichprobe anhand der vorgeschriebenen Quote auswählen, Risikokriterien dokumentieren und Kontrollplan festhalten. | H80: Analoge Ex-ante-Schätzung auf Basis der Auswahlvorgaben in QZBW 2026, Abschnitt 6.3, und BioZBW 2026, Abschnitt 6.8 | I80: Hoch – Zeitansatz nicht empirisch erhoben; bei stark automatisierter Auswahl geringer möglich. | J80: Verwendet
A81: ANN-044 | B81: Administrative Vorbereitung je extern kontrolliertem Gruppenmitglied | C81: 15 | D81: Minuten je Stichprobenmitglied | E81: QZBW und BioZBW | F81: Kontroll-/Zertifizierungsstelle | G81: Termin und Unterlagen je ausgewähltem Mitglied koordinieren sowie Kontrollakte vorbereiten; keine Reise- oder Vor-Ort-Zeit. | H81: Analogie zu bestehenden Termin- und Unterlagenkoordinationspositionen; QZBW 2026, Abschnitt 6.3; BioZBW 2026, Abschnitt 6.8 | I81: Hoch – Ex-ante-Annahme; abhängig von Datenqualität, Systemzugang und Rückfragen. | J81: Verwendet
A82: ANN-045 | B82: Administrative Nachbereitung je extern kontrolliertem Gruppenmitglied | C82: 15 | D82: Minuten je Stichprobenmitglied | E82: QZBW und BioZBW | F82: Kontroll-/Zertifizierungsstelle | G82: Kontrollcheckliste abschließen, Ergebnis und gegebenenfalls Abweichungen dokumentieren und Kontrollakte schließen; keine Vor-Ort-Prüfzeit. | H82: QZBW-Programmbestimmungen 2026, Abschnitt 12.5; BioZBW-Programmbestimmungen 2026, Abschnitt 11.5; analoge Ex-ante-Schätzung | I82: Hoch – Ex-ante-Annahme; aufwendige Abweichungsfälle sind nicht pauschal enthalten. | J82: Verwendet
A83: ANN-046 | B83: Administrative Vorbereitung der jährlichen Zeichennutzerkontrolle | C83: 15 | D83: Minuten je Zeichennutzerkontrolle und Jahr | E83: QZBW und BioZBW | F83: Kontroll-/Zertifizierungsstelle | G83: Kontrolltermin abstimmen und das programmspezifische Dokumentenpaket beim Zeichennutzer anfordern; eine Genossenschaft ist ein Zeichennutzer. | H83: QZBW-Programmbestimmungen 2026, S. 24; BioZBW-Programmbestimmungen 2026, S. 17 | I83: Hoch – Ex-ante-Annahme; tatsächlicher Aufwand hängt von Standardisierung und Vorbefüllung ab. | J83: Verwendet
A84: ANN-047 | B84: Dokumentenprüfung und administrative Checklistenbearbeitung bei der Zeichennutzerkontrolle | C84: 60 | D84: Minuten je Zeichennutzerkontrolle und Jahr | E84: QZBW und BioZBW | F84: Kontroll-/Zertifizierungsstelle | G84: Eigenkontrolle, Produkt- und Qualitätsnachweise, Waren- und Herkunftsdokumentation, Rückverfolgbarkeit und Kennzeichnung dokumentenbasiert prüfen und in der Checkliste dokumentieren. | H84: QZBW-Programmbestimmungen 2026, Abschnitte 6.2.1, 6.9 und 12.3; BioZBW-Programmbestimmungen 2026, Abschnitte 6.2.1, 6.8 und 11.3; BioZBW-Kombicheckliste 2025 | I84: Hoch – Ex-ante-Annahme; die Programmbestimmungen belegen die Pflicht, nicht den Zeitansatz. | J84: Verwendet
A85: ANN-048 | B85: Abgrenzung externer Kontrollen | C85: Nicht monetarisiert | D85: Abgrenzung | E85: QZBW und BioZBW | F85: Kontroll-/Zertifizierungsstelle | G85: Physische Vor-Ort-, Standort- und Prozessprüfung, Reisezeit, Probenahme sowie anlassbezogene Nachkontrollen, Sanktionen und Ausschlussfälle bleiben außerhalb der Jahressumme. | H85: Methodische Abgrenzung der engen zertifizierungsspezifischen administrativen Rechnung | I85: Die Jahressumme bildet deshalb nicht die vollständigen Kontrollkosten ab. | J85: Nicht monetarisiert
A86: ANN-049 | B86: Gebündelter laufender Lizenznehmeraufwand je Mitglied und Jahr | C86: =SUM(C87:C91) -> 60 | D86: Minuten je Mitglied und Jahr | E86: QZBW und BioZBW | F86: Externer Lizenznehmer | G86: Kontrollsumme der fünf laufenden Routinebausteine. Eine Stunde je Mitglied und Jahr entspricht bei 30 EUR je Stunde 30 EUR je Mitglied und Jahr. | H86: QZBW-Programmbestimmungen 2026, Abschnitte 3.2, 6.7, 6.8, 12.4 und 12.5; BioZBW-Programmbestimmungen 2026, Abschnitte 3.2, 6.7, 11.4 und 11.5; https://www.gemeinschaftsmarketing-bw.de/qualitaetszeichen-bw/was-ist-das-qualitaetszeichen/; https://www.gemeinschaftsmarketing-bw.de/bio-zeichen-bw/was-ist-das-bio-zeichen-2/ | I86: Hoch – Die Programmbestimmungen belegen die Aufgaben, nicht den Zeitansatz; die Aufteilung ist eine transparente Ex-ante-Annahme. | J86: Verwendet
A87: ANN-050 | B87: Programminhalte und vertragliche Verpflichtungen laufend überwachen | C87: 10 | D87: Minuten je Mitglied und Jahr | E87: QZBW und BioZBW | F87: Externer Lizenznehmer | G87: Teilnehmerstatus und Einhaltung der programmspezifischen sowie vertraglichen Pflichten im Standardjahr administrativ überwachen. | H87: QZBW-Programmbestimmungen 2026, S. 8, Abschnitt 3.2; BioZBW-Programmbestimmungen 2026, S. 7–8, Abschnitt 3.2; https://www.gemeinschaftsmarketing-bw.de/qualitaetszeichen-bw/was-ist-das-qualitaetszeichen/; https://www.gemeinschaftsmarketing-bw.de/bio-zeichen-bw/was-ist-das-bio-zeichen-2/ | I87: Hoch – Ex-ante-Annahme; abhängig von Standardisierung und Zahl der Statusänderungen. | J87: Verwendet
A88: ANN-051 | B88: Kontrollen veranlassen und Durchführung überwachen | C88: 15 | D88: Minuten je Mitglied und Jahr | E88: QZBW und BioZBW | F88: Externer Lizenznehmer | G88: Kontrollbeauftragung, Termin- beziehungsweise Statusüberwachung und Vollständigkeitskontrolle der vorgesehenen Kontrollen administrativ begleiten. | H88: QZBW-Programmbestimmungen 2026, S. 22, Abschnitte 6.7–6.8; BioZBW-Programmbestimmungen 2026, S. 17–18, Abschnitte 6.7 und 7.1; https://www.gemeinschaftsmarketing-bw.de/qualitaetszeichen-bw/was-ist-das-qualitaetszeichen/; https://www.gemeinschaftsmarketing-bw.de/bio-zeichen-bw/was-ist-das-bio-zeichen-2/ | I88: Hoch – Ex-ante-Annahme; keine Prüf- oder Vor-Ort-Zeit der Zertifizierungsstelle enthalten. | J88: Verwendet
A89: ANN-052 | B89: Prüfergebnisse verarbeiten und Standardabweichungen nachverfolgen | C89: 15 | D89: Minuten je Mitglied und Jahr | E89: QZBW und BioZBW | F89: Externer Lizenznehmer | G89: Prüfberichte beziehungsweise Auditprotokolle zuordnen, Status aktualisieren und die Bearbeitung gewöhnlicher Korrekturhinweise nachhalten. | H89: QZBW-Programmbestimmungen 2026, S. 40, Abschnitt 12.5; BioZBW-Programmbestimmungen 2026, S. 28, Abschnitt 11.5; https://www.gemeinschaftsmarketing-bw.de/qualitaetszeichen-bw/was-ist-das-qualitaetszeichen/; https://www.gemeinschaftsmarketing-bw.de/bio-zeichen-bw/was-ist-das-bio-zeichen-2/ | I89: Hoch – Ex-ante-Annahme; schwere Verstöße und formelle Sanktionen sind nicht enthalten. | J89: Verwendet
A90: ANN-053 | B90: Neuanmeldungen und Stammdatenänderungen verwalten und an die MBW melden | C90: 15 | D90: Minuten je Mitglied und Jahr | E90: QZBW und BioZBW | F90: Externer Lizenznehmer | G90: Teilnehmer- und Stammdaten im Jahresverlauf pflegen und tatsächliche Neuanmeldungen beziehungsweise Änderungen unverzüglich an die MBW weiterleiten. | H90: QZBW-Programmbestimmungen 2026, S. 39, Abschnitt 12.4; BioZBW-Programmbestimmungen 2026, S. 27–28, Abschnitt 11.4; https://www.gemeinschaftsmarketing-bw.de/qualitaetszeichen-bw/was-ist-das-qualitaetszeichen/; https://www.gemeinschaftsmarketing-bw.de/bio-zeichen-bw/was-ist-das-bio-zeichen-2/ | I90: Hoch – Pauschalierter Jahresdurchschnitt; reale Fallzahl schwankt. | J90: Verwendet
A91: ANN-054 | B91: Jährliche zusammenfassende Teilnehmermeldung an die MBW erstellen | C91: 5 | D91: Minuten je Mitglied und Jahr | E91: QZBW und BioZBW | F91: Externer Lizenznehmer | G91: Angeschlossene Erzeuger und Zeichennutzer getrennt nach Produktbereichen konsolidieren, plausibilisieren und zum 31. Dezember melden. | H91: QZBW-Programmbestimmungen 2026, S. 39, Abschnitt 12.4; BioZBW-Programmbestimmungen 2026, S. 27–28, Abschnitt 11.4; https://www.gemeinschaftsmarketing-bw.de/qualitaetszeichen-bw/was-ist-das-qualitaetszeichen/; https://www.gemeinschaftsmarketing-bw.de/bio-zeichen-bw/was-ist-das-bio-zeichen-2/ | I91: Hoch – Ex-ante-Annahme für den anteiligen Aufwand innerhalb einer gebündelten Sammelmeldung. | J91: Verwendet
A92: ANN-055 | B92: Anlassbezogene Sanktionierung und Ausschlussverfahren des Lizenznehmers | C92: Nicht im Standardjahr | D92: Ereignisabhängige Anforderung | E92: QZBW und BioZBW | F92: Externer Lizenznehmer | G92: Bei schweren oder fortgesetzten Verstößen Abmahnung, Vertragsstrafe, Vermarktungsausschluss oder Kündigung prüfen, abstimmen, aussprechen und dokumentieren. | H92: QZBW-Programmbestimmungen 2026, S. 8, 22 und 40, Abschnitte 3.2, 6.7 und 12.5; BioZBW-Programmbestimmungen 2026, S. 20–21 und 28, Abschnitte 8 und 11.5; https://www.gemeinschaftsmarketing-bw.de/qualitaetszeichen-bw/was-ist-das-qualitaetszeichen/; https://www.gemeinschaftsmarketing-bw.de/bio-zeichen-bw/was-ist-das-bio-zeichen-2/ | I92: Die Pflicht ist belegt, Eintrittshäufigkeit und Zeitaufwand sind für ein Standardjahr nicht belastbar pauschalierbar. | J92: Nicht monetarisiert

Sheet Protokoll
A1: ID | B1: ID | C1: ID | D1: ID | E1: ID | F1: ID | G1: ID | H1: ID | I1: ID | J1: ID
A2: Dieses Blatt dokumentiert die interne Qualitätssicherung. Vor einer späteren Publikationsfassung werden interne Entwicklungsbezeichnungen entfernt und Änderungen gegenüber dem Zwischenbericht neutral erläutert.
A4: Datum | B4: Änderung / Prüfung | C4: Ausgangsproblem | D4: Vorgenommene Lösung | E4: Betroffene Blätter / Positionen | F4: Noch offene Frage | G4: Beleg-IDs
A5: 46222 | B5: Vier getrennte Szenarien eingeführt | C5: Die alte Summe vermischte QZBW- und BioZBW-spezifische Positionen. | D5: Vier eigenständige, reproduzierbare Summen und Sankey-Quellen. | E5: Altdatei; fachlich relevante Zielblätter
A6: 46222 | B6: Düngemittel 1.200 EUR / Pflanzenschutz 600 EUR bestätigt | C6: Die Excel-Werte waren richtig; in der alten Sankey-Grafik waren die Bezeichnungen vertauscht. | D6: Neue Diagramme verwenden die korrekte Zuordnung. | E6: Altdatei; fachlich relevante Zielblätter
A7: 46222 | B7: Fachrechtliche Basisdokumentation vom Zertifizierungszusatz getrennt | C7: Düngung, Pflanzenschutz sowie weitere Basisaufzeichnungen fallen nicht ausschließlich durch die Zertifizierung an. | D7: Nur im breiten Szenario vollständig enthalten. | E7: Altdatei; fachlich relevante Zielblätter
A8: 46222 | B8: HACCP beim Traubenerzeuger ausgeschlossen | C8: Falsche Akteursebene und mögliche Doppelzählung. | D8: 50 EUR bis zur Neuabgrenzung nicht summiert. | E8: Altdatei; fachlich relevante Zielblätter
A9: 46222 | B9: Gemischte Analyseposition ausgeschlossen | C9: Zucker/Säure/Alkohol/Sensorik/Nmin lassen sich nicht als eine Position einem Akteur und Programm zuordnen. | D9: 500 EUR bis zur Aufteilung nicht summiert. | E9: Altdatei; fachlich relevante Zielblätter
A10: 46222 | B10: Kontrollstellenaufwand sprachlich von Kontrollgebühren getrennt | C10: 465 EUR waren modellierte Arbeitszeit, keine belegte Rechnung oder Gebühr. | D10: Bericht muss dies explizit ausweisen; Gebühren separat behandeln. | E10: Altdatei; fachlich relevante Zielblätter
A11: 46222 | B11: Kontrollstichproben berichtigt | C11: 10 % gilt im BioZBW-Zusatzkontrollkontext; QZBW-Gruppenprüfung folgt Wurzelstichprobe. | D11: Methodik- und Ergebnistext werden korrigiert. | E11: Altdatei; fachlich relevante Zielblätter
A12: 46222 | B12: Förderlogik berichtigt | C12: Förderung reduziert erstattungsfähige Ausgaben, ist selbst aber keine Kostenposition. | D12: Keine pauschale Aussage „sieben Jahre keine Kontrollkosten“ mehr. | E12: Altdatei; fachlich relevante Zielblätter
A13: 46226 | B13: Blatt Quellen_Annahmen getrennt | C13: Quellen, Rechenannahmen und Prüfentscheidungen erfüllen unterschiedliche Funktionen. | D13: Drei eigenständige Blätter Quellen, Annahmen und Prüfprotokoll erstellt. | E13: Quellen; Annahmen; Prüfprotokoll | F13: Keine.
A14: 46226 | B14: Systemgrenze auf gesamte Weinwertschöpfungskette präzisiert | C14: Die Rolle der Weinbereitung/Verarbeitung musste ausdrücklich sichtbar werden. | D14: Traubenerzeuger, Erzeugergemeinschaft, Zeichennutzer, Weinbereitung/Verarbeitung und Kontrollstelle werden betrachtet; gezählt wird weiterhin nur inkrementeller Zertifizierungsaufwand. | E14: Annahmen; beide Anforderungsblätter; Kostenrechnung | F14: Keine.
A15: 46226 | B15: Administrative Tätigkeiten enger definiert | C15: Forschungsziel ist die Erleichterung administrativer Arbeit durch Digitalisierung und kooperative Datennutzung. | D15: Nur Erfassen, Übertragen, Prüfen, Verarbeiten, Ablegen oder Kommunizieren von Informationen wird monetarisiert. | E15: Annahmen; Kostenrechnung | F15: Keine.
A16: 46226 | B16: Physische Prüfungen zentraler Einrichtungen ausgeschlossen | C16: Sechs Standort- und Prozessprüfungen waren keine reinen Schreibtischtätigkeiten. | D16: Weinkellerei, Abfüllung, Etikettierung, Rohstofflager, Maschinen und Flaschenlager aus beiden engen Rechnungen entfernt; Anforderungen bleiben nachvollziehbar. | E16: Beide Anforderungsblätter; Annahmen; SankeyMATIC-Codes | F16: Keine.
A17: 46226 | B17: Vor-Ort-Kontrollchecklisten ausgeschlossen | C17: Kontrollchecklisten bildeten die Durchführung physischer Inspektionen ab. | D17: Dokumentenbasierte Systemverifizierung und Kontrollstellenmeldung bleiben enthalten; Betriebs-, Zeichennutzer- und Kombichecklisten werden nicht monetarisiert. | E17: Beide Anforderungsblätter; Kostenrechnung; SankeyMATIC-Codes | F17: Keine.
A18: 46226 | B18: BioZBW-Gruppenpakete geprüft | C18: Funktionale Übertragungen aus QZBW waren inhaltlich zu entscheiden. | D18: Verträge/Meldedatei/Eigenkontrollcheckliste, zwölf dokumentenbezogene interne Prüftätigkeiten sowie Beschwerden/Protokoll/QMS bestätigt; direkte EU-Basis und Extrapolation gekennzeichnet. | E18: Anforderungen_BioZBW; Quellen; Prüfprotokoll | F18: Empirische Zeitansätze bleiben Modellwerte.
A19: 46226 | B19: HACCP fachlich eingeordnet | C19: QZBW und BioZBW verlangen bei Weinbereitung/Verarbeitung ein dokumentiertes HACCP-Konzept. | D19: Anforderung beim richtigen Akteur ausgewiesen, aber nicht monetarisiert, weil HACCP bereits nach Art. 5 VO (EG) 852/2004 Baseline ist. | E19: Beide Anforderungsblätter; Annahmen | F19: Keine.
A20: 46226 | B20: Gemischte Analyseposition quellenbasiert bereinigt | C20: 500 EUR bündelten Zucker, Säure, Alkohol, Sensorik und Nmin ohne trennbare Akteure oder Kosten. | D20: Vorläufig ohne Kostenallokation aufgeteilt; abschließende fachrechtliche Bündelung am 2026-07-24 dokumentiert. | E20: Anforderungen_QZBW; Annahmen | F20: Durch spätere Entscheidung erledigt.
A21: 46226 | B21: Zahlenherkunft ergänzt | C21: Direkt übernommene Werte, Analogübertragungen und methodische Entscheidungen waren schwer unterscheidbar. | D21: Spalten Zahlenherkunft und Übertragungsstatus ergänzt; keine neue numerische Schätzung vorgenommen. | E21: Beide Anforderungsblätter; Annahmen | F21: Keine.
A22: 46226 | B22: Zeitkonflikte methodisch behandelt | C22: Mehrere Modellwerte weichen von Kommentarschätzungen ab. | D22: Modellwerte bleiben Basiswerte; Kommentarschätzungen werden als Unsicherheitsbereiche dokumentiert, ohne neue Mittelwerte. | E22: Beide Anforderungsblätter; Annahmen | F22: Empirische Validierung bleibt sinnvoll.
A23: 46226 | B23: SankeyMATIC beibehalten | C23: Excel-Add-ins stehen mit der Universitätslizenz nicht zur Verfügung. | D23: Aktuelle enge Codes werden aus den enthaltenen Zeilen der Arbeitsmappe neu erzeugt. | E23: SankeyMATIC-Codes | F23: Szenarioauswahl wurde am 2026-07-24 abschließend festgelegt.
A24: 46226 | B24: Spätere Publikationsbereinigung vorgemerkt | C24: Interne Entwicklungs- und Herkunftsbezeichnungen sollen im Abschlussbericht nicht präsent sein. | D24: Interne Arbeitsversion bleibt archiviert; spätere Publikationsfassung wird neutralisiert und erklärt Abweichungen zum Zwischenbericht methodisch. | E24: Annahmen; Prüfprotokoll | F24: Erst vor Finalisierung des Abschlussberichts durchführen.
... A31: 46229 | B31: Fehlende wörtliche Quellenbelege ergänzt | C31: In 56 Zeilen stand lediglich ein Platzhalter ohne wörtlichen Quellenbeleg. | D31: Die zugehörigen Programmrichtlinien, Verträge, Eigenkontroll- und Neutral-Kontrollchecklisten wurden im Volltext durchsucht; wörtliche Belege und genaue Fundstellen wurden zeilenbezogen ergänzt. Wo eine Quelle nur eine übergeordnete Pflicht belegt, wird die begrenzte Belegreichweite ausdrücklich genannt. | E31: Anforderungen_QZBW; Anforderungen_BioZBW; Quellen; Prüfprotokoll | F31: Keine verbleibenden Platzhalter dieser Formulierung.
A32: 2026-07-27 | B32: Reduzierte Anforderungsblätter ergänzt | C32: Die Vollblätter enthalten zusätzlich Baseline-, Prüf- und Herleitungsspalten sowie nicht zertifizierungsspezifische Anforderungen. | D32: Je Programm wurde eine kompakte, mit dem Vollblatt verknüpfte Ansicht erstellt. Enthalten sind nur Zeilen mit „Zertifizierungsspezifischer Zusatzaufwand = Ja“ sowie die Spalten A:G, K:P und V:X. | E32: Anford_QZBW_zert_spez; Anford_BioZBW_zert_spez | F32: Keine.
A33: 2026-07-27 | B33: Gerätespezifische Pfadverweise vollständig entfernt | C33: Gerätespezifische Speicherpfade wären nach der Online-Veröffentlichung ungültig und legten persönliche Ablagestrukturen offen. | D33: Fundstellen auf Dokumenttitel, Seiten-/Artikelangaben und offizielle URLs reduziert; Quellenregister auf offizielle Bezugsquellen umgestellt; interne Sankey-Codes als in der Arbeitsmappe enthalten gekennzeichnet. | E33: Anforderungen_QZBW; Anforderungen_BioZBW; Quellen; SankeyMATIC-Codes; beide reduzierten Anforderungsblätter | F33: Keine.
A34: 2026-07-28 | B34: Fundstellen in reduzierten Anforderungsblättern vereinheitlicht | C34: Die Spalte „Genaue Fundstelle“ wiederholte teilweise das Quelldokument und enthielt URLs oder interpretierende Hinweise statt reiner Navigationsangaben. | D34: Fundstellen auf Seite und Kapitel-/Abschnittsnummer beziehungsweise Artikelangaben reduziert; Endreihenfolge im BioZBW-Blatt auf Quelldokument, Fundstelle, Zitat vereinheitlicht. | E34: Anford_QZBW_zert_spez; Anford_BioZBW_zert_spez | F34: Keine.
A35: 2026-07-28 | B35: Kostenrechnung auf reduzierte Anforderungsblätter umgestellt | C35: Nach der Spaltenumordnung enthielten Formeln der Kostenrechnung ungültige #BEZUG!-Verweise auf frühere Spaltenstrukturen. | D35: Formeln mit direkten, begrenzten Bezügen auf die beiden reduzierten Anforderungsblätter neu aufgebaut; QZ-0052 gemäß bestehender Abgrenzung nicht in der engen Kostenrechnung berücksichtigt und die verschobenen Zahlenwerte dieser Zeile geleert. | E35: Kostenrechnung; Anford_QZBW_zert_spez; Anford_BioZBW_zert_spez | F35: Keine.
A36: 2026-07-28 | B36: SankeyMATIC-Darstellung für breite Ausgabe optimiert | C36: Die nahezu quadratische Diagrammfläche führte bei den zahlreichen Endknoten zu überlappenden und teilweise abgeschnittenen Beschriftungen. | D36: Beide Codes auf 3000 × 1800 Pixel mit größeren seitlichen Rändern umgestellt; Knotenbreite auf 18 erhöht; Grundschrift auf 9 Pixel verkleinert; Namen und Werte auf identische Größe sowie gleichbleibende Skalierung gesetzt. | E36: SankeyMATIC-Codes, Diagramme 1 und 2 | F36: Keine.
A37: 2026-07-28 | B37: Ersten SankeyMATIC-Ausgangsknoten in „Gesamt“ umbenannt | C37: Der erste Ausgangsknoten trug die lange Bezeichnung „Gesamter zertifizierungsspezifischer Aufwand“. | D37: Den ersten Ausgangsknoten in beiden SankeyMATIC-Codes einheitlich in „Gesamt“ umbenannt; alle Flusswerte und nachgelagerten Knoten unverändert belassen. | E37: SankeyMATIC-Codes, Diagramme 1 und 2 | F37: Keine.
A38: 2026-07-31 | B38: Rollenmodell Erzeugergruppe, Zeichennutzer und Lizenznehmer geklärt | C38: Die Erzeugergruppe erfüllt gegenüber Mitgliedern teilweise lizenznehmerähnliche Bündelungsfunktionen; unklar war, ob sie rechtlich/funktional zum Lizenznehmer wird. | D38: Die Gruppe bleibt Zeichennutzer und Zertifikatsinhaber; QZBW verwendet hierfür den Oberbegriff QMS, das EU-Bio-Recht den Oberbegriff IKS. Ein separater Lizenznehmer bleibt für den Zeichennutzungsvertrag, die Programmüberwachung und lizenznehmerspezifische Aufgaben erforderlich. | E38: Beide Anforderungsblätter; Annahmen; Quellen | F38: Keine. | G38: BEL-001 bis BEL-005
A39: 2026-07-31 | B39: QMS-Kostenblock fachlich abgegrenzt und umbenannt | C39: Die Bezeichnung Maintenance and implementation of the QMS beziehungsweise Durchführung des QMS suggerierte die Vollkosten des gesamten QMS, obwohl nur vier Stunden Ablageaufwand angesetzt waren. | D39: In Dokumentenlenkung umbenannt. Die 120 EUR decken nur Dokumentenlenkung und -pflege; andere Teilprozesse des QMS beziehungsweise IKS bleiben eigene, überschneidungsfreie Blöcke. | E39: Beide Voll- und Kurzblätter; Kostenrechnung; SankeyMATIC-Codes; Annahmen | F39: Empirische Validierung des 4-Stunden-Werts bleibt sinnvoll. | G39: BEL-006 bis BEL-007
A40: 2026-07-31 | B40: Fehlende administrative Teilaufgaben des QMS beziehungsweise IKS ergänzt | C40: Mehrere normative Pflichten zu Zulassung, Schulung, Auditorenqualifikation, Inspektionsplanung, Mitgliederfreigabe, Meldungen und Funktionstest waren nicht atomar sichtbar. | D40: Als zertifizierungsspezifische Anforderungen mit Quellenbeleg ergänzt; mangels belastbarer Zeitansätze nicht monetarisiert und nicht in Sankey-Codes aufgenommen. | E40: Anforderungen_QZBW; Anforderungen_BioZBW; beide reduzierten Anforderungsblätter; Quellen | F40: Für eine erweiterte Vollkostenrechnung Zeitansätze empirisch erheben. | G40: BEL-008 bis BEL-012
A41: 2026-07-31 | B41: Rückstandsuntersuchungen aus QZBW-Weinaggregation entfernt | C41: Der allgemeine Abschnitt 6.6 wurde als QZBW-spezifische Weinpflicht der Genossenschaft interpretiert. | D41: Die produktspezifische Tabelle 6.9 enthält für Wein, Sekt und Perlwein keinen Rückstandsuntersuchungsplan. Die 240-EUR-Position bleibt nur im Ausschlussregister/Vollblatt nachvollziehbar. | E41: Anforderungen_QZBW; Anford_QZBW_zert_spez; Kostenrechnung; SankeyMATIC-Codes; Annahmen | F41: Nur bei Vorlage eines gesonderten, verbindlichen Wein-Prüfplans erneut bewerten. | G41: BEL-013 bis BEL-015
A42: 2026-08-02 | B42: QMS und IKS programmspezifisch getrennt und Sankey-Kategorien bereinigt | C42: QMS und IKS wurden teilweise synonym verwendet; dadurch standen ein vermeintliches internes Kontrollsystem und die Dokumentenpflege unklar auf derselben Sankey-Ebene. | D42: QZBW verwendet QMS als Oberbegriff, EU-Bio verwendet IKS. Die monetarisierten Äste heißen neutral 'Interne Prüfungen innerhalb der Gruppe' und 'Dokumentenlenkung'; programmspezifische Begriffe bleiben in den konkreten Tätigkeiten erhalten. Rollen-Kürzel in Klammern wurden aus beiden Codes entfernt. | E42: Beide Voll- und Kurzblätter; Kostenrechnung; Annahmen; Protokoll; SankeyMATIC-Codes | F42: Öffentliche SankeyMATIC-Links und PNG-Referenzbilder nach Neugenerierung aus den aktualisierten Codes ersetzen. | G42: BEL-016 bis BEL-018
A44: Quellenbelege zu den fachlichen Entscheidungen vom 31.07. und 02.08.2026
A45: Leselogik: Direkter Beleg = Aussage ist ausdrücklich formuliert; kombinierte Herleitung = Schlussfolgerung aus mehreren Regelungen; Tabellenbefund = Aussage ergibt sich aus der belegten Tabellenstruktur beziehungsweise einer leeren Tabellenzelle.
A46: Beleg-ID | B46: Bezug zum Protokolleintrag | C46: Programmbereich | D46: Quelldokument | E46: Genaue Fundstelle | F46: Wörtliches Zitat / Tabellenbefund | G46: Einordnung des Belegs | H46: Offizielle URL / Bezugsquelle
A47: BEL-001 | B47: Rollenmodell Erzeugergruppe, Zeichennutzer und Lizenznehmer | C47: QZBW | D47: QZBW - Programmbestimmungen, Stand 01.01.2025 | E47: S. 9, Abschnitt 3.4 'Erzeugergruppe' | F47: Die Erzeugergruppe ist als juristische Einheit der Zertifikatinhaber und fungiert als Zeichennutzer. | G47: Direkter QZBW-Beleg für die Rollen als Zertifikatinhaber und Zeichennutzer. | H47: https://mbw.imageplant.de/
A48: BEL-002 | B48: Rollenmodell Erzeugergruppe, Zeichennutzer und Lizenznehmer | C48: QZBW | D48: QZBW - Programmbestimmungen, Stand 01.01.2025 | E48: S. 9, Abschnitt 3.5 'Zeichennutzer' | F48: Zeichennutzer sind Erzeugergruppen, Verarbeitungs- und Vermarktungsbetriebe [...]. Dazu schließen sie mit einem Lizenznehmer je nach Produktbereich einen entsprechenden Zeichennutzungsvertrag ab. | G48: Direkter Beleg: Die Erzeugergruppe wird nicht selbst zum Lizenznehmer, sondern schließt als Zeichennutzer mit einem Lizenznehmer den Vertrag. | H48: https://mbw.imageplant.de/
A49: BEL-003 | B49: Rollenmodell Erzeugergruppe, Zeichennutzer und Lizenznehmer | C49: QZBW | D49: QZBW - Anforderungen an Erzeugergruppen, Stand 01.01.2023 | E49: S. 4, Abschnitt 2.1.1 'Systemteilnahme' | F49: Die Erzeugergruppe fungiert als Zeichennutzer. Ein gültiger Zeichennutzungsvertrag mit einem QZBW-Lizenznehmer liegt vor. | G49: Zusätzlicher direkter QZBW-Beleg für den weiterhin separaten Lizenznehmer. | H49: https://mbw.imageplant.de/
A50: BEL-004 | B50: Rollenmodell Erzeugergruppe, Zeichennutzer und Lizenznehmer | C50: BioZBW | D50: BioZBW - Programmbestimmungen, Stand 01.01.2025 | E50: S. 8, Abschnitt 3.4 'Zeichennutzer' | F50: Zeichennutzer sind Verarbeitungs- und Vermarktungsbetriebe [...]. Dazu schließen sie mit einem Lizenznehmer einen entsprechenden Zeichennutzungsvertrag ab. | G50: Direkter BioZBW-Beleg für die Trennung von Zeichennutzer und Lizenznehmer; auf die Unternehmergruppe als BioZBW-Zeichennutzer funktional angewendet. | H50: https://mbw.imageplant.de/
A51: BEL-005 | B51: Rollenmodell Erzeugergruppe, Zeichennutzer und Lizenznehmer | C51: EU-Öko / BioZBW | D51: Verordnung (EU) 2018/848 | E51: Art. 35 Abs. 1; Art. 36 Abs. 1 Buchst. d und g sowie Abs. 2; ABl. L 150, S. 40-42 | F51: Art. 35 Abs. 1: ‚Die zuständigen Behörden oder gegebenenfalls die Kontrollbehörden oder Kontrollstellen stellen allen Unternehmern oder Unternehmergruppen [...] ein Zertifikat aus.‘ Art. 36 Abs. 1 Buchst. d und g: ‚besitzt Rechtspersönlichkeit‘; ‚richtet ein System für interne Kontrollen ein‘. Art. 36 Abs. 2: ‚das Zertifikat nach Artikel 35 für die gesamte Gruppe‘. | G51: Kombinierte Herleitung: Die Unternehmergruppe ist selbst Zertifikatssubjekt mit IKS. Die Pflicht zu einem separaten BioZBW-Lizenznehmer folgt ergänzend aus den BioZBW-Programmbestimmungen (BEL-004). | H51: https://eur-lex.europa.eu/eli/reg/2018/848/oj?locale=de
A52: BEL-006 | B52: QMS-Kostenblock abgegrenzt und umbenannt | C52: QZBW | D52: QZBW - Anforderungen an Erzeugergruppen, Stand 01.01.2023 | E52: S. 10-11, Abschnitte 7.1.1 'Inhalte' und 7.1.2 'Lenkung und Pflege' | F52: Das QMS muss durch Verfahren, Arbeitsanweisungen, Formulare und ggf. weitere Aufzeichnungen entsprechend seiner Größe angemessen dokumentiert sein. Die Dokumente werden regelmäßig auf Aktualität überprüft. Es ist sicherzustellen, dass alle Dokumente des QMS gepflegt werden und die verantwortlichen Personen jeweils die aktuellen Versionen verwenden. | G52: Direkter Beleg für den engen Restblock Dokumentenablage, Aktualitätsprüfung und Versionspflege. Er belegt nicht die Vollkosten des gesamten QMS. | H52: https://mbw.imageplant.de/
A53: BEL-007 | B53: QMS-Kostenblock abgegrenzt und umbenannt | C53: EU-Öko / BioZBW | D53: Delegierte Verordnung (EU) 2021/715 | E53: Art. 1 Nr. 1 Buchst. b Ziff. vi und Buchst. c Ziff. iii; ABl. L 151, S. 2-3 | F53: Kontrolle der Unterlagen und Aufzeichnungen. Entwicklung der IKS-Verfahren und Ausarbeitung der entsprechenden Unterlagen und Aufzeichnungen, Aktualisierung und Verfügbar machen dieser für die IKS-Inspektoren und gegebenenfalls die Mitglieder der Gruppe. | G53: Direkter EU-Beleg für Dokumentenlenkung und -pflege im Bio-IKS; die übrigen IKS-Aufgaben sind gesonderte Teilprozesse. | H53: https://eur-lex.europa.eu/legal-content/DE/ALL/?uri=CELEX:32021R0715
A54: BEL-008 | B54: Fehlende administrative Teilaufgaben des QMS beziehungsweise IKS ergänzt | C54: QZBW | D54: QZBW - Anforderungen an Erzeugergruppen, Stand 01.01.2023 | E54: S. 6-7, Abschnitte 3.2.4, 3.3.2 und 3.3.3 | F54: Es muss ein dokumentiertes Verfahren über die Aufnahme neuer Mitgliedsbetriebe geben. Bevor interne Audits/Kontrollen selbstständig durchgeführt werden, muss der interne Auditor/Kontrolleur mindestens ein/e Audit/Kontrolle als Beobachter begleitet haben. Die Mitarbeiter/das Personal und die Mitglieder der Erzeugergruppe werden regelmäßig geschult. | G54: Direkte Belege für Zulassungsmanagement, Qualifikation und Schulungsdokumentation. | H54: https://mbw.imageplant.de/
A55: BEL-009 | B55: Fehlende administrative Teilaufgaben des QMS beziehungsweise IKS ergänzt | C55: QZBW | D55: QZBW - Anforderungen an Erzeugergruppen, Stand 01.01.2023 | E55: S. 8, Abschnitte 4.1.5 bis 4.1.8; S. 10, Abschnitt 6.1.2 | F55: Interne Audits/Kontrollen können in Teilaudits erfolgen. In diesem Fall muss ein Zeitplan vorliegen. Diese Freigabe ist dokumentiert. Das System muss mindestens jährlich getestet werden. Der Test ist zu dokumentieren. | G55: Direkte Belege für Inspektionsplanung, dokumentierte Mitgliederfreigabe im Vier-Augen-Prinzip und den jährlichen Funktionstest der Rückverfolgbarkeit. | H55: https://mbw.imageplant.de/
A56: BEL-010 | B56: Fehlende administrative Teilaufgaben des QMS beziehungsweise IKS ergänzt | C56: EU-Öko / BioZBW | D56: Delegierte Verordnung (EU) 2021/715 | E56: Art. 1 Nr. 1 Buchst. b; ABl. L 151, S. 2 | F56: Das System für interne Kontrollen (IKS) umfasst dokumentierte Verfahren zu folgenden Aspekten: Registrierung der Mitglieder, interne Inspektionen, Zulassung neuer Mitglieder, Schulungen, Kontrolle der Unterlagen und Aufzeichnungen, Maßnahmen bei Verstößen und interne Rückverfolgbarkeit. | G56: Direkter EU-Beleg dafür, dass das Bio-IKS mehr umfasst als reine Dokumentenablage. | H56: https://eur-lex.europa.eu/legal-content/DE/ALL/?uri=CELEX:32021R0715
A57: BEL-011 | B57: Fehlende administrative Teilaufgaben des QMS beziehungsweise IKS ergänzt | C57: EU-Öko / BioZBW | D57: Delegierte Verordnung (EU) 2021/715 | E57: Art. 1 Nr. 1 Buchst. c Ziff. vii bis xi; ABl. L 151, S. 3 | F57: Jährliche Überprüfung der Erklärungen zu Interessenkonflikten der IKS-Inspektoren; Anberaumung interner Inspektionen; Sicherstellung angemessener Schulungen; Zulassung neuer Mitglieder oder neuer Produktionseinheiten oder neuer Tätigkeiten bestehender Mitglieder; Festlegung und Weiterverfolgung von Maßnahmen bei Verstößen. | G57: Direkte EU-Belege für Rollenpflege, Planung, Kompetenzbewertung, Zulassung und Maßnahmenmanagement. | H57: https://eur-lex.europa.eu/legal-content/DE/ALL/?uri=CELEX:32021R0715
... A77: 2026-08-02 | B77: Informationspflichten präzisiert und Lizenznehmermeldung ergänzt | C77: Jahres-, Änderungs- und Prüfergebnismeldungen waren teilweise nur unter allgemeinen Meldetätigkeiten erfasst. | D77: BIO-0016 und BIO-0044 präzisiert; BIO-0063 ergänzt; bedingte Informationspflichten in BIO-0065 sichtbar, aber nicht monetarisiert. | E77: BioZBW-Anforderungsblätter; Kostenrechnung; Sankey-Code; Annahmen | F77: Tatsächlicher Lizenznehmeraufwand empirisch zu prüfen. | G77: BioZBW-Programmbestimmungen 2026, S. 27–28, Abschnitte 11.3–11.5 | H77: Wörtliche Zitate in den jeweiligen Zeilen
A78: 2026-08-21 | B78: Kontrollstellenkosten auf n=150 Mitglieder umgelegt | C78: V12 weist den gruppenfixen Kontrollstellenblock von 270,00 EUR ohne Pro-Kopf-Allokation aus. | D78: Nur die acht gruppenfixen Kontrollstellenpositionen wurden über den Faktor 1/150 einem Mitglied zugerechnet; alle übrigen Kostenpositionen blieben unverändert. | E78: Anford_QZBW_zert_spez; Anford_BioZBW_zert_spez; Kostenrechnung; Annahmen | F78: SankeyMATIC-Code, Bericht und zusätzliche Kontrolltätigkeiten werden erst nach Freigabe dieses Zwischenschritts angepasst. | G78: ANN-040; QZ-0046; QZ-0047; QZ-0064; QZ-0065; BIO-0043; BIO-0044; BIO-0057; BIO-0058
A79: 2026-08-22 | B79: Administrative Kontrolltätigkeiten bei Zeichennutzer und Mitgliederstichprobe ergänzt | C79: V12 enthielt nur den gruppenfixen QMS-Prüfblock; die jährliche Zeichennutzerkontrolle und administrative Vor-/Nachbereitung der externen Mitgliederstichprobe fehlten. | D79: Je Programm fünf Tätigkeiten ergänzt: Zeichennutzerkontrolle vorbereiten und dokumentenbasiert bearbeiten; Mitgliederstichprobe auswählen sowie je Stichprobenmitglied administrativ vor- und nachbereiten. Physische Vor-Ort-Zeit bleibt ausgeschlossen. | E79: Anford_QZBW_zert_spez; Anford_BioZBW_zert_spez; Kostenrechnung; Annahmen; SankeyMATIC-Codes | F79: Zeitansätze sind transparente Ex-ante-Annahmen. Anlassbezogene Nachkontrollen/Sanktionen und Schritt 3 zu Lizenznehmertätigkeiten bleiben offen. | G79: ANN-041 bis ANN-048; QZ-0068 bis QZ-0072; BIO-0065 bis BIO-0069 | H79: QZBW-Programmbestimmungen 2026; BioZBW-Programmbestimmungen 2026; VO (EU) 2021/279; BioZBW-Kombicheckliste 2025 | I79: QZBW: 13 Standard-Stichproben; BioZBW: 10 Nachinspektionen; Referenzgruppe n=150 | J79: Schritt 2 – zur fachlichen Freigabe
A80: 2026-08-23 | B80: Laufende Lizenznehmertätigkeiten für QZBW und BioZBW symmetrisch ergänzt | C80: V12 erfasste bei QZBW nur die einmalige Vertragsprüfung und bei BioZBW zusätzlich eine mit 60 Minuten angesetzte Jahresmeldung; der weitergehende laufende Aufgabenbereich des Lizenznehmers fehlte. | D80: Je Programm 60 Minuten je Mitglied und Jahr auf fünf Routinebausteine verteilt: Programm-/Vertragsüberwachung 10, Kontrollorganisation 15, Prüfergebnisnachverfolgung 15, Stamm-/Neuanmeldungsmanagement 15 und Jahresmeldung 5 Minuten. Einmalige Vertragsprüfung bleibt separat; Sanktionen sind dokumentiert, im Standardjahr aber nicht monetarisiert. | E80: Anford_QZBW_zert_spez; Anford_BioZBW_zert_spez; Kostenrechnung; Annahmen; SankeyMATIC-Codes | F80: Zeitansätze sind transparente Ex-ante-Annahmen. Die Programmbestimmungen belegen Aufgaben und Häufigkeiten, nicht die angesetzten Minuten. | G80: ANN-049 bis ANN-055; QZ-0073 bis QZ-0078; BIO-0063; BIO-0070 bis BIO-0074 | H80: QZBW-Programmbestimmungen 2026; BioZBW-Programmbestimmungen 2026; https://www.gemeinschaftsmarketing-bw.de/qualitaetszeichen-bw/was-ist-das-qualitaetszeichen/; https://www.gemeinschaftsmarketing-bw.de/bio-zeichen-bw/was-ist-das-bio-zeichen-2/ | I80: Laufend: 30,00 EUR je Mitglied und Jahr in beiden Programmen; einmalige Vertragsprüfung: 30,00 EUR je Genossenschaft/Zeichennutzerin in beiden Programmen. | J80: Schritt 3 – zur fachlichen Freigabe
A81: 23.08.2026 | B81: Veröffentlichungsstand | C81: Kostenmodell Schritt 3 | D81: BIOZBW-Stichprobe konsistent mit der programmspezifischen 10-%-Quote auf 15 Mitglieder gesetzt; EU-Öko-Nachinspektionsregel aus der Zusatzkostenrechnung abgegrenzt. SankeyMATIC-Kommentare und Verweise auf den digitalen Anhang präzisiert; Referenzwerte wegen gemischter Wiederholungslogik ausdrücklich nicht als reine Jahressummen bezeichnet. | E81: Sabrina Del Basso | F81: Finaler Stand für Abschlussbericht und digitalen Anhang

Sheet SankeyMATIC-Codes
A1: SankeyMATIC-Codes – zertifizierungsspezifische Szenarien
A2: Diagramm 1: QZBW – nur zertifizierungsspezifisch
A3: Nummer | B3: 1
A4: Programm | B4: QZBW
A5: Szenario | B5: nur zertifizierungsspezifisch
A6: Vollständiger SankeyMATIC-Code | B6: // SankeyMATIC – QZBW – nur zertifizierungsspezifische administrative Zusatzaufwände // Aktualisiert: 23.08.2026 // Monetarisierte Tätigkeiten: 53; modellierter Referenzwert: 1099.7 EUR je Mitglied (Gruppe n=150); wegen gemischter Wiederholungslogik keine reine Jahressumme. // Lizenznehmer: 30 EUR laufende Verwaltung je Mitglied und Jahr; die einmalige Vertragsprüfung von 30 EUR bleibt als eigener Flow getrennt sichtbar. // Anlassbezogene Sanktionen/Ausschlüsse sowie physische Vor-Ort-, Reise- und Probenahmezeiten sind nicht monetarisiert. // QMS ist der einheitliche Oberbegriff. Interne Kontrollen sind Teilprozesse des QMS. // === Nodes and Flows === Gesamt [1099.7] QZBW QZBW [137.5] Traubenerzeuger Traubenerzeuger [12.5] Teilnahmevereinbarung mit der Erzeugergruppe prüfen, unterzeichnen und übermitteln Traubenerzeuger [25] Eigenkontroll-Checkliste des landwirtschaftlichen Betriebs ausfüllen und ablegen Traubenerzeuger [50] GVO-Freiheitsbescheinigung ausfüllen beziehungsweise einholen und zusammen mit den zugehörigen Nachweisen ablegen Traubenerzeuger [12.5] Datenschutzhinweise zur Teilnahmevereinbarung lesen und unterzeichnen Traubenerzeuger [25] Vorhandene Betriebsnachweise für das QMS zusammenstellen und der Erzeugergruppe übermitteln Traubenerzeuger [12.5] Umsetzung von Korrekturmaßnahmen dokumentieren und der Erzeugergruppe melden QZBW [898.75] Genossenschaft Genossenschaft [772.5] Administrative Tätigkeiten im QMS der Erzeugergruppe Administrative Tätigkeiten im QMS der Erzeugergruppe [12.5] Teilnahmevereinbarung mit dem Gruppenmitglied ausfüllen, unterzeichnen und ablegen Administrative Tätigkeiten im QMS der Erzeugergruppe [120] Excel-Meldedatei für jedes Gruppenmitglied ausfüllen und übermitteln Administrative Tätigkeiten im QMS der Erzeugergruppe [60] Eigenkontrollcheckliste des Traubenerzeugers prüfen und Prüfergebnis dokumentieren Administrative Tätigkeiten im QMS der Erzeugergruppe [15] Maßnahmenpläne prüfen und Prüfergebnis dokumentieren Administrative Tätigkeiten im QMS der Erzeugergruppe [30] Pflanzenschutzaufzeichnungen prüfen und Prüfergebnis dokumentieren Administrative Tätigkeiten im QMS der Erzeugergruppe [30] Düngemittelaufzeichnungen prüfen und Prüfergebnis dokumentieren Administrative Tätigkeiten im QMS der Erzeugergruppe [15] Ernteaufzeichnungen prüfen und Prüfergebnis dokumentieren Administrative Tätigkeiten im QMS der Erzeugergruppe [15] Verkaufszahlen prüfen und Prüfergebnis dokumentieren Administrative Tätigkeiten im QMS der Erzeugergruppe [30] Flächenangaben prüfen und Prüfergebnis dokumentieren Administrative Tätigkeiten im QMS der Erzeugergruppe [15] Lieferscheine prüfen und Prüfergebnis dokumentieren Administrative Tätigkeiten im QMS der Erzeugergruppe [15] Wareneingangsdokumente prüfen und Prüfergebnis dokumentieren Administrative Tätigkeiten im QMS der Erzeugergruppe [15] Rechnungsunterlagen prüfen und Prüfergebnis dokumentieren Administrative Tätigkeiten im QMS der Erzeugergruppe [15] Korrekturmaßnahmen definieren und Umsetzungsfristen dokumentieren Administrative Tätigkeiten im QMS der Erzeugergruppe [15] Nachkontrolle durchführen und Ergebnis dokumentieren Administrative Tätigkeiten im QMS der Erzeugergruppe [15] Beschwerden erfassen, untersuchen, klären und dokumentieren Administrative Tätigkeiten im QMS der Erzeugergruppe [45] Kontroll- und Abweichungsprotokolle führen Administrative Tätigkeiten im QMS der Erzeugergruppe [15] Abweichungen kategorisieren und dokumentieren Administrative Tätigkeiten im QMS der Erzeugergruppe [120] QMS-Verfahren, Arbeitsanweisungen, Formulare und Aufzeichnungen ablegen, auf Aktualität prüfen und pflegen Administrative Tätigkeiten im QMS der Erzeugergruppe [15] Verfahren zur Aufnahme neuer Mitglieder pflegen und Neuaufnahme dokumentieren Administrative Tätigkeiten im QMS der Erzeugergruppe [15] Qualifikations-, Zulassungs- und Begleitnachweise interner Auditoren und Kontrolleure pflegen Administrative Tätigkeiten im QMS der Erzeugergruppe [30] Schulungen planen sowie Inhalte und Teilnehmende dokumentieren Administrative Tätigkeiten im QMS der Erzeugergruppe [15] Interne Audits terminieren und Auditzeitplan pflegen Administrative Tätigkeiten im QMS der Erzeugergruppe [7.5] Mitgliedsfreigabe im Vier-Augen-Prinzip prüfen und dokumentieren Administrative Tätigkeiten im QMS der Erzeugergruppe [30] Rückverfolgbarkeitssystem anhand eines Warenbeispiels testen und Ergebnis dokumentieren Administrative Tätigkeiten im QMS der Erzeugergruppe [25] Kontrollvertrag beziehungsweise Kontrollauftrag prüfen, unterzeichnen und ablegen Administrative Tätigkeiten im QMS der Erzeugergruppe [30] QMS-Kontrollunterlagen zusammenstellen und der Zertifizierungsstelle bereitstellen Administrative Tätigkeiten im QMS der Erzeugergruppe [7.5] Gruppenzertifikat prüfen, intern zuordnen und im QMS ablegen Genossenschaft [126.25] Administrative Tätigkeiten als Zeichennutzer Administrative Tätigkeiten als Zeichennutzer [25] Zeichennutzungsvertrag lesen, unterzeichnen und ablegen Administrative Tätigkeiten als Zeichennutzer [6.25] Datenschutzhinweise zum Zeichennutzungsvertrag lesen und unterzeichnen Administrative Tätigkeiten als Zeichennutzer [30] Eigenkontrollcheckliste des Zeichennutzers ausfüllen und ablegen Administrative Tätigkeiten als Zeichennutzer [15] QZBW-Qualitätsnachweis beschaffen und für die Eigen- beziehungsweise Zertifizierungskontrolle bereithalten Administrative Tätigkeiten als Zeichennutzer [50] Warenflüsse zwischen QZBW- und Nicht-QZBW-Ware trennen und nachvollziehbar dokumentieren QZBW [3.45] Kontroll-/Zertifizierungsstelle Kontroll-/Zertifizierungsstelle [1.8] Administrative Prüfung des Gruppen-QMS Administrative Prüfung des Gruppen-QMS [0.8] QMS einschließlich interner Kontrollen anhand der Unterlagen verifizieren und Ergebnis dokumentieren Administrative Prüfung des Gruppen-QMS [0.8] Prüfergebnisse dokumentieren, an auditierten Betrieb und Lizenznehmer übermitteln sowie Quartalsbericht an die MBW erstellen Administrative Prüfung des Gruppen-QMS [0.1] Externen QMS-Kontrolltermin abstimmen und erforderliche Kontrollunterlagen anfordern Administrative Prüfung des Gruppen-QMS [0.1] Zertifizierungsentscheidung dokumentieren und Gruppenzertifikat beziehungsweise Zertifikatsdaten übermitteln Kontroll-/Zertifizierungsstelle [0.25] Administrative Tätigkeiten der Zeichennutzerkontrolle Administrative Tätigkeiten der Zeichennutzerkontrolle [0.05] Jährliche Zeichennutzerkontrolle terminieren und programmspezifische Unterlagen anfordern Administrative Tätigkeiten der Zeichennutzerkontrolle [0.2] Eigenkontrollsystem, Produkt- und Qualitätsnachweise, Waren- und Herkunftsdokumentation, Rückverfolgbarkeit und Kennzeichnung prüfen und Kontrollcheckliste vervollständigen Kontroll-/Zertifizierungsstelle [1.4] Administrative Vor- und Nachbereitung der Mitgliederstichprobe Administrative Vor- und Nachbereitung der Mitgliederstichprobe [0.1] Risikobasierte Mitgliederstichprobe auswählen und jährlichen Kontrollplan dokumentieren Administrative Vor- und Nachbereitung der Mitgliederstichprobe [0.65] Termin und Unterlagen je ausgewähltem Mitglied koordinieren und Kontrollakte vorbereiten Administrative Vor- und Nachbereitung der Mitgliederstichprobe [0.65] Kontrollcheckliste je Stichprobenmitglied abschließen, Ergebnis und gegebenenfalls Abweichungen dokumentieren und Kontrollakte schließen QZBW [60] Externer Lizenznehmer Externer Lizenznehmer [30] Einmalige Vertragsprüfung und Programmanmeldung Einmalige Vertragsprüfung und Programmanmeldung [30] Zeichennutzungsvertrag der Erzeugergruppe prüfen und gegenzeichnen sowie Programmanmeldung weiterleiten Externer Lizenznehmer [30] Laufende teilnehmerbezogene Lizenznehmerverwaltung Laufende teilnehmerbezogene Lizenznehmerverwaltung [5] Programminhalte und vertragliche Verpflichtungen der angeschlossenen Teilnehmer laufend überwachen Laufende teilnehmerbezogene Lizenznehmerverwaltung [7.5] Vorgesehene Kontrollen veranlassen und deren Durchführung administrativ überwachen Laufende teilnehmerbezogene Lizenznehmerverwaltung [7.5] Prüfergebnisse zuordnen, Teilnehmerstatus aktualisieren und gewöhnliche Korrekturhinweise nachverfolgen Laufende teilnehmerbezogene Lizenznehmerverwaltung [7.5] Neuanmeldungen und Stammdatenänderungen verwalten und unverzüglich an die MBW melden Laufende teilnehmerbezogene Lizenznehmerverwaltung [2.5] Jahresmeldung der angeschlossenen Erzeuger und Zeichennutzer erstellen, plausibilisieren und an die MBW übermitteln // === Settings === size w 2000 h 1200 margin l 8 r 2 t 18 b 20 bg color #ffffff transparent N node w 2 h 44 spacing 73 border 0 theme c color #888888 opacity 1 flow curvature 0.26 inheritfrom target color #999999 opacity 0.45 layout order exact justifyorigins N justifyends Y reversegraph N attachincompletesto nearest labels color #000000 hide N highlight 0.55 fontface sans-serif linespacing 0 relativesize 100 magnify 96 labelname appears Y size 9 weight 400 labelvalue appears Y fullprecision Y position before weight 400 labelposition autoalign 0 scheme auto first before breakpoint 7 value format '.,' prefix '' suffix ' €' themeoffset a 6 meta mentionsankeymatic N listimbalances Y
A7: Link zum interaktiven Diagramm | B7: https://sankeymatic.com/build/?i=PTAEGUEMDsGsFMCeBZAggFQJIGFSGQCUARQC0AhAdX1GgFcAnUAL3joBcBLAM3cfZZugBzAM7CADvF7dhAYwAW8UJAAmAW3bR2w1nUgcAbouI1hexpBqcA7gBPoy%2BACgQoVLFY1IAGy182ALlAAJgBmADoABgAOMKCIoIA2ZzBkAHtoeFZIOl8WVkV0Gw5BBHZ86ECAVhCAblBVVIcvHzyWUAAleE4WeGhGKzzAgEYIgE5RsIB2UABRAFV20AArRWQywRblUAAKAHE6GjEJagBeIcqIgEo6gcFe0Dv1WTl8hnI%2BBzo5VK8BES9UoJ2LBQKUMqA6PANIoAFKQOSQ0Q0VSqeBhZKgAAyPF6jAyclRdECIQiswWoC8Fm69kUADUWFZvB4hMtVutNqABFs4Qi6so%2BKAodBVN52HdQPS2LoRGI6AAfzh%2DUD6dKgElkxYAIy8UM1rCUXmEgrFvTaADEAVYHplIdBoPrhOx5KxNdl0S5UNBKaJNZJAaaIDB3Ox0r1gKgTM8vHLRIphKkrAKxHJEI7nnTUnQALQAeTYWYANB0ocJ4FnOfZQAAFOipX3QeGo5hle6OyuaZ31UNZHKOvLusCEZDgUBafWfY3QBRlHzyRQ5310X2CHKcThhUCYe0scEAaXSOh%2BOugoDbW3QUK8stSzFjoAcRqH4HRjkcu3gplU%2BoA2iNxlMAF0iDIchHBIChQF%2DEJJjCSogPQXQaHrFhmBoO46EcBCLGQuhUPQyChiCWD4MvBsCXgQxIQ0V0DhZdRxzaGZcPgNCWBXQ5jllBVeiLARXmbeQMhPLlQDlRd6PyLxoEwxCcLwtpvyCODZhNOAD1rZos2wBQZFgHxtEUB8KRgZREzYZ5IE4VhZwUE9SBtPhNSNCxhE4OVmnuETIG1eA7mkrCkNNZjWIYb8LiA3ZaRzLMzSo6dWGEX10w0MUlRctyPJPX1eHgOQ%2DmEAYtEUIVvmPCstkYExIBRe56Pve5KruOQADecj80AADlIHkQrSxPbydT8mTsKC%2BTQsI4jQAAET0XpnhoVhGDkDResUSqGAvdgpMbCiemo7IlR1PryorfioUE3phsCjJgvwxTlNpTM5BMgN7J0RzhAbHqS0UNyGGUSBH2HJgqpq6ADMyk6JyYsb2KORQxJYCT4Ckq65JYu6JuUuZVFLRalRVE99zoSF3HoEUAH2yNRE9lFSWBkV6DgemEytodutiDnh%2BoUYcaTwMob8olGGJJmU99oFSWNwfkSzWDfXopb6iyrMgyZJiI5TUDUFLtF0AwCiKMVSnKUdVCIYH2dhrmJEcbX1E0PW9HYQxQEKYoTfudhzafeqGBhjHOY4xRf01kitup3aqOgGilTqhxzf2YPhXZD4lBMDLj147dmKdOQhJOgbfMu%2B3dZ0Z3Xfd42oVN72LZHK3A7oOHjlDiIgJmAAPGQUazZBefgAH8nYUA%2DtZIyk%2DhlPWA2NP0vcsqRMRuhkdR0vHfLg23aNkoa69n3LcYjnm5tkOEnblS%2DNgdSjznXT9PyeqjQC9GQqNLjqROmtuOb%2BBNUd%2B89NGb2j8CXHWG99Yu0Nh7PeJ466%2B0biFFuIdzhAWQJAKmO1oBiC8HYRQH9PKVm%2Dt0X%2B%2D8tCAIZjTZmto7bgLHJAyuO9PZwIPg3I%2B1tg6QRJEBKsnBKR9DmvIBa5hLACXzn8e4BDWZbGIWxP%2BAC6aUKZqA6S696EV2gdXFsLD65%2B1mMfZBXCL5TTlEIeAq8qRiNoGYk8Uiv7yhIXcMhRpFHAOoWAh26it5V13tos2ujEHoUMb%2BZSTFtyWPOuImxoA7EiVkaQhRQCqEqNoZ4p23imGwP8Qg9hTdgmoIlCwWAVJhDmDkGVWJRCHFyOcRQtxKS1HpKgdvGBfj4GH39gY0%2BRigIWhsHOBsQhvKSOqdI6s1SEnkNccklmqSy4MM0b42urC9EByQd0kJQFsRdBYMlcElSZETKcYkpRIDZmNM3s0nxzDskdP0Rw7mmzQDkGyKaDQggYAiGmUzfBoz7E%2D2OVMpJyjzl0KaYw1pyyAm5PWZwp5nRBL5T4iwSk7UDnjIBfIoFpz3GqLBZciFWioU5M6Q81uBTiakw8CvDBkdaZdBSizE6OM8aVSEK5XsptvlnJoRchZLSiX72haSvJGyCldXkNfe0GkdT3noPINyCJCFbCYoClxwKeUePmRogVSyhUkvuaKuFBT7LPAGHQPmgo6CcEBn1bOrxhA0AGUWPSNhbRQw1biuZECdXXKye0thIrYWPIACzKX3NKo85YRKoE1IVIR7LrysHpkeX6colV4rSQSxZNyA2rK6carWcbIkSJPMU%2DIghMy5HdSJblXq%2BW%2BsyW0lZgSg6PMIhfJ8WZJQ2ozUWVAS4a6mGgL1UtRYzSZlUDQSkkIToRk4FY0tSgfJ%2BSLFSVwZNRSsCKDEv5IkxB8OLpm7VGTIX6ruWsoJYqHosF7e69arhLCR2oCxNoawZ6bDaAewayrOosSpM%2ButDT8X8r9c24Vhrg3kuUoQTwPhuDlpDODQsoBjDekdey6NlZ7IbBrl9OQq1Rw5xuo%2B%2Dkyaa2VgjYeDy9B8GHqGg209gqdEGsvW21u3CIBCN%2BNEnBMBWwJgFFuZ6XhH4iU2lJXKNMHB1JmbykDjaz0sYvQW9tyktyvHBBGMjRpXieKZTGmgZHmysD47Y%2BjWqfVMb1cpwNkGr1wpgspd9s9B4cqhB830%2DjaR%2BCzBGPyWYawaF4GIXd3ExlAdBVm0DTbiUqbJSHTj7Q5S6UopwH4ggaIm1EKmfI5sYDPUrEKD8zzXkxxLGIPghpQD5AMmM1VWL1U4uA9FxTzHbl2bYyfOFSkgJUZlZRcughQDZT4HldlhH%2BtHipENsL1J7UoUiQXLyK7LNeKubF89nXVMcc7cOLMU3mjIroKihqoMaYQ0XmzNoxA8hcB4H4fKl3FCLiHZJY83r1uEpsx1%2DNCW1aTUnhIARbB7vlrmzxIjmmQaZmUMtyseai5DQlkrQRz1VahwSLELWCnrM3O8EaW7edei0EWiwT74Kc1ZIJ6hyJJPhEKV67T4ndphH5UG9KCkH5IfHasb%2BpHa3Ke6vx9VonAzSfMFCljpnM1yjzUWstEdP0QbmzF7ZCX7O8ic6Or%2B3nS3BfZuF9T0XdPWdk9CpxmYqkpXUa8HfPSY5DIlbV%2DT83zkM4L356t49VmNtKYNIT03EuFIFIFlmWDW6iifW6gRksI2PyyzXL%2Bse%2DJFBW4C%2DHnK42RCEdu6D7gOVaIiBtzKl7e1WAifKBTw3YHTY05d2byXkFwqldtHwmMpYmCJnTCeMPJ0Op51YOHkCWYXmzp0CT39%2BGVTNCzzRWTIKaECy4WEMNfWb6aWAHnjgBfHvsue44Q7Xgsxb7u7v%2Dg%2B%2D3soLCFEICjHmnEKVBPU%2B0Bw%2DDmr%2Dyx%2DLJn%2DJzfyOb8EQN%2BQEvsQoUYfAFMNkUOO4bQR%2B9wBWJkeicwOcp2J4lE92hev6DWtSkW8mrWW8X%2Bw2P%2BU8f%2BkEgBt%2BGKjijWneOBkOMA6cZGfgpsb0OQf8J02IzAfQ%2BIhIok4kZQkkJ48YiYigEebABOi4g%2BSgtMAoyAEEuyV%2BPuX2igBBT8oAQOvQJBABYQQwHcncmm9wXaR%2BemGgy62g3sNMJ0t6sOKKxOoAR%2Bx2KBkh6WFqO4H%2BOqyhRBwOGhgB2htO%2BeD2F%2BIgTMyUygT%2BnqKiJ0ahIOO%2BwIegmeY2%2BUueZ%2BMRCUQ89wy8q80kR%2BJ%2B2%2B6Be%2BIgz2pB2Od%2BuOfu7WE4DewedAJeqarheOWS5RQeDOVRG%2BsqmhEQykMINgCINkRgjR5u1RHkNWSMjKFGWw14K41UuMEgUgWgc4oASBrwDhMAThnwChQute9wDRLOlRAxrRgBQQHc1uLRwguW5iRYNYjQNA7gWGWwEePg26CU%2BGq0RYY%2B6hJ0AAEkUgIFZMIHWs7OkEWMlqlpYV4JltkCbCdLuCTouiyOikfvbg%2DIoJRDPoaNuvYKpIfi0dkUkYXk9lfgRKvsUXgc0o9NmP3jHq9mUE%2Dm%2BqnIPHIXnNeL6LUSSZmDcZ1BSeXtSQwC5p%2BnQKYfIIySHN4UBO0L4NfK6H2GwGyB%2Bh8PSQKbWF5i5LYOUr%2BksF0SdizrYS0WZgvpqmsYbqSWyRKnIJScyIQTSTKXSXyRwPKXWEKWEAkMpBeCvMYSJAsSipAO1CsOnMIHcMqaJuYqADyWnNfLDiMb%2BkfpAO4EiZmKaQbvyoaeSfIKaVyUGbSZ8PyXIIKYUY6evpGs0AiY7qyBADaVmQqb0PRK5lsN5GAfABTJDlgQAiJHcE4qaNADas0EaLGvGtnpsWEQZpRi0VGY%2DLWfWfzCBJBOfDoXoQwOwbiFweTl3DOViDiJwVJgpJbhoCKD4OKJKENuIA4kqHErWBMSiDAKiF4CEUII4FbsKKKLuVrp6QeQqEeVUoCLoGecKLzEqN%2BJxhUWzuyhzp6X9katzOii2biPrgIYJkoSeR%2BSKF%2BZeUqIVIsbAjebodAbOauXiOuRbhfJiFSL0DJsPJJuRIOowP6OCHOWuWRZRIyKJn8I4ARZYERYoCRQueRZRYoNRThbRQyEyD%2BcpBcaeQ7JXooCJEBbPHMZKN%2BoPkuhOJ8gnuUqjgXBJhxcZCxZWMvIyAMkxYRTSEMRHLhdlFxSuRwbxYSHRQJSyN%2BE5kBKSXcKWLZIoLAagSwDAOhr%2Bp8PcFNPKnIIqkXkoCUfoDwfxbpcxdSMRaRMZX6H5NxdhRxVZQxTZXZRQTUo7J3pVLDkJEWGpbhdoHoCYEoJuvpOEc2fAFYM1PnD0VqSTPAGTF8CtMrtPiCUNBFaxYZaRYSCZXFWZfObhUlWaQDspB1P%2BohVee1CJOAFkCiKkdAHYJ8EuoNbrtAJRIwHKFJXIJIfeNIRBBeXzHpZpVFUZWRT1QGDxYlfxclcNopJNDyIiPtamYpVGCpfcF1idP%2Beblas9tAEWHxiYOwJqFtNWvzlIasBBOkXwSjNJI6MwKAFaHEBEBEI4KAKAFtR2sjSKM3MYV4KAFECjRCMEATfqEMPjajZqMEMjZqMNjID8JmKAAAMRrjM2cDE26DgxiBlb6gdSOCSwyYI0E1bUhohoE3iDdTvKgCTAhAE2ahWEMDI2o0V7mKKAyAE200AgMAM1RDa060E2pCc0yBlCICgBDCOB8IJigAyD0D6CFWzr7FJCo0aAKA5CsCcC1jmw9h3Dyyo3q300M3jAB2jB60G1G2gCAFhqOCUiICpALSgBy2CidzdTe3LAmA77R1tQaBGg82o1LCp1cCIBEVGgACaBNkIlEpYExyYnUBNegWQ8gGgtNqgOCmQH4yaL6ry2gkdwy1WvtmtSN%2DdCtaN7AMm2dQ9gg5SYoLwYdsElQBN6W9oNqPcp4MAwgWYpYq4BNPgGQYthtLIg9kIlIBssNigIwg9IoggmgnAxtowSQlIvo20qISg8M2QxdotOIoAQdqNhU49%2BoIaSNXd99NtvwigkAz9fJoAJdqNiozQso8AhtjoqokDMSUsZQSG8eThTgX9HmU9f9yNd9KMYgKDHAqoFgya95J4g96Yj9pDqQc97A1p6DmYmDI2kIUZhDGg%2BoSQQDNAv0k6sRAA5GEAWPwwTbA9wJ3KAPwyI6jY6muOwBI%2Dw6AIADUEIjStqIqQa4eMSgoADtI2Ydat%2BjqNWwmNmQkAPMIC6Qw6CAiAIoNp1dqND83sro%2DCPcxdQAA
A8: Diagramm 2: BioZBW – nur zertifizierungsspezifisch
A9: Nummer | B9: 2
A10: Programm | B10: BioZBW
A11: Szenario | B11: nur zertifizierungsspezifisch
A12: Vollständiger SankeyMATIC-Code | B12: // SankeyMATIC – BioZBW – nur zertifizierungsspezifische administrative Zusatzaufwände // Aktualisiert: 23.08.2026 // Monetarisierte Tätigkeiten: 53; modellierter Referenzwert: 1049.9 EUR je Mitglied (Gruppe n=150); wegen gemischter Wiederholungslogik keine reine Jahressumme. // Lizenznehmer: 30 EUR laufende Verwaltung je Mitglied und Jahr; die einmalige Vertragsprüfung von 30 EUR bleibt als eigener Flow getrennt sichtbar. // Anlassbezogene Sanktionen/Ausschlüsse sowie physische Vor-Ort-, Reise- und Probenahmezeiten sind nicht monetarisiert. // QMS ist der einheitliche Oberbegriff. Interne Kontrollen sind Teilprozesse des QMS. // === Nodes and Flows === Gesamt [1049.9] BioZBW BioZBW [87.5] Traubenerzeuger Traubenerzeuger [12.5] Teilnahmeerklärung gegenüber der Genossenschaft als Zeichennutzerin und Unternehmergruppe prüfen, unterzeichnen und übermitteln Traubenerzeuger [12.5] Datenschutzhinweise zur Teilnahmevereinbarung lesen und unterzeichnen Traubenerzeuger [25] Vorhandene Betriebsnachweise für das QMS zusammenstellen und der Unternehmergruppe übermitteln Traubenerzeuger [12.5] Umsetzung von Korrekturmaßnahmen dokumentieren und der Unternehmergruppe melden Traubenerzeuger [25] Eigenkontrollcheckliste des landwirtschaftlichen Betriebs ausfüllen und ablegen BioZBW [898.75] Genossenschaft Genossenschaft [757.5] Administrative Tätigkeiten im QMS der Erzeugergruppe Administrative Tätigkeiten im QMS der Erzeugergruppe [12.5] Teilnahmevereinbarung mit dem Gruppenmitglied ausfüllen, unterzeichnen und ablegen Administrative Tätigkeiten im QMS der Erzeugergruppe [120] Mitglieder- und Meldedatei aktualisieren und jährlich an den Lizenznehmer übermitteln Administrative Tätigkeiten im QMS der Erzeugergruppe [60] Eigenkontrollcheckliste und betriebliche Nachweise des Gruppenmitglieds prüfen, Prüfergebnis dokumentieren und Mitglied freigeben Administrative Tätigkeiten im QMS der Erzeugergruppe [15] Maßnahmenpläne prüfen und Prüfergebnis dokumentieren Administrative Tätigkeiten im QMS der Erzeugergruppe [30] Pflanzenschutzaufzeichnungen prüfen und Prüfergebnis dokumentieren Administrative Tätigkeiten im QMS der Erzeugergruppe [30] Düngemittelaufzeichnungen prüfen und Prüfergebnis dokumentieren Administrative Tätigkeiten im QMS der Erzeugergruppe [15] Ernteaufzeichnungen prüfen und Prüfergebnis dokumentieren Administrative Tätigkeiten im QMS der Erzeugergruppe [15] Verkaufszahlen prüfen und Prüfergebnis dokumentieren Administrative Tätigkeiten im QMS der Erzeugergruppe [30] Flächenangaben prüfen und Prüfergebnis dokumentieren Administrative Tätigkeiten im QMS der Erzeugergruppe [15] Lieferscheine prüfen und Prüfergebnis dokumentieren Administrative Tätigkeiten im QMS der Erzeugergruppe [15] Wareneingangsdokumente prüfen und Prüfergebnis dokumentieren Administrative Tätigkeiten im QMS der Erzeugergruppe [15] Rechnungsunterlagen prüfen und Prüfergebnis dokumentieren Administrative Tätigkeiten im QMS der Erzeugergruppe [15] Korrekturmaßnahmen definieren und Umsetzungsfristen dokumentieren Administrative Tätigkeiten im QMS der Erzeugergruppe [15] Nachkontrolle durchführen und Ergebnis dokumentieren Administrative Tätigkeiten im QMS der Erzeugergruppe [15] Beschwerden erfassen, untersuchen, klären und dokumentieren Administrative Tätigkeiten im QMS der Erzeugergruppe [45] Kontroll- und Abweichungsprotokolle führen Administrative Tätigkeiten im QMS der Erzeugergruppe [15] Abweichungen kategorisieren und dokumentieren Administrative Tätigkeiten im QMS der Erzeugergruppe [120] QMS-Verfahren, Unterlagen und Aufzeichnungen erstellen, aktualisieren und bereitstellen Administrative Tätigkeiten im QMS der Erzeugergruppe [7.5] Mitgliederliste mit Kontrollstatus und Versionsstand aktualisieren Administrative Tätigkeiten im QMS der Erzeugergruppe [15] interne QMS-Kontrolleure ernennen sowie Interessenkonflikte und Qualifikation dokumentieren Administrative Tätigkeiten im QMS der Erzeugergruppe [30] interne QMS-Kontrolleure und Mitglieder schulen und Schulungsnachweise pflegen Administrative Tätigkeiten im QMS der Erzeugergruppe [15] Interne Inspektionen terminieren und Inspektionsplan pflegen Administrative Tätigkeiten im QMS der Erzeugergruppe [15] Neue Mitglieder, Produktionseinheiten oder Tätigkeiten prüfen und Zulassung dokumentieren Administrative Tätigkeiten im QMS der Erzeugergruppe [15] Erhebliche Verstöße, Mitgliedssperren und Vermarktungsverbote an die Kontrollstelle melden Administrative Tätigkeiten im QMS der Erzeugergruppe [25] Kontrollvertrag beziehungsweise Kontrollauftrag prüfen, unterzeichnen und ablegen Administrative Tätigkeiten im QMS der Erzeugergruppe [30] QMS-Kontrollunterlagen zusammenstellen und der Kontrollstelle bereitstellen Administrative Tätigkeiten im QMS der Erzeugergruppe [7.5] Gruppenzertifikat prüfen, intern zuordnen und im QMS ablegen Genossenschaft [141.25] Administrative Tätigkeiten als Zeichennutzer Administrative Tätigkeiten als Zeichennutzer [25] Zeichennutzungsvertrag lesen, unterzeichnen und ablegen Administrative Tätigkeiten als Zeichennutzer [6.25] Datenschutzhinweise zum Zeichennutzungsvertrag lesen und unterzeichnen Administrative Tätigkeiten als Zeichennutzer [30] Eigenkontrollcheckliste des Zeichennutzers ausfüllen, aktualisieren und ablegen Administrative Tätigkeiten als Zeichennutzer [50] Warenflüsse zwischen zertifizierten und nicht zertifizierten Produkten trennen und nachvollziehbar dokumentieren Administrative Tätigkeiten als Zeichennutzer [15] BioZBW-Produktaufstellung aktualisieren und für Kontrollen bereitstellen Administrative Tätigkeiten als Zeichennutzer [15] Qualitätsprüfung administrativ anmelden sowie Ergebnisnachweis zuordnen und bereithalten BioZBW [3.65] Kontroll-/Zertifizierungsstelle Kontroll-/Zertifizierungsstelle [1.8] Administrative Prüfung des Gruppen-QMS Administrative Prüfung des Gruppen-QMS [0.8] QMS anhand der Unterlagen verifizieren und Ergebnis dokumentieren Administrative Prüfung des Gruppen-QMS [0.8] Prüfergebnisse dokumentieren und Quartalsmeldung an die MBW übermitteln Administrative Prüfung des Gruppen-QMS [0.1] Externen QMS-Kontrolltermin abstimmen und erforderliche Kontrollunterlagen anfordern Administrative Prüfung des Gruppen-QMS [0.1] Zertifizierungsentscheidung dokumentieren und Gruppenzertifikat beziehungsweise Zertifikatsdaten übermitteln Kontroll-/Zertifizierungsstelle [0.25] Administrative Tätigkeiten der Zeichennutzerkontrolle Administrative Tätigkeiten der Zeichennutzerkontrolle [0.05] Jährliche Zeichennutzerkontrolle terminieren und programmspezifische Unterlagen anfordern Administrative Tätigkeiten der Zeichennutzerkontrolle [0.2] Eigenkontrollsystem, Produkt- und Qualitätsnachweise, Waren- und Herkunftsdokumentation, Rückverfolgbarkeit und Kennzeichnung prüfen und Kontrollcheckliste vervollständigen Kontroll-/Zertifizierungsstelle [1.6] Administrative Vor- und Nachbereitung der Mitgliederstichprobe Administrative Vor- und Nachbereitung der Mitgliederstichprobe [0.1] Risikobasierte Mitgliederstichprobe auswählen und jährlichen Kontrollplan dokumentieren Administrative Vor- und Nachbereitung der Mitgliederstichprobe [0.75] Termin und Unterlagen je ausgewähltem Mitglied koordinieren und Kontrollakte vorbereiten Administrative Vor- und Nachbereitung der Mitgliederstichprobe [0.75] Kontrollcheckliste je Stichprobenmitglied abschließen, Ergebnis und gegebenenfalls Abweichungen dokumentieren und Kontrollakte schließen BioZBW [60] Externer Lizenznehmer Externer Lizenznehmer [30] Einmalige Vertragsprüfung und Programmanmeldung Einmalige Vertragsprüfung und Programmanmeldung [30] Zeichennutzungsvertrag der Genossenschaft prüfen und gegenzeichnen sowie Programmanmeldung weiterleiten Externer Lizenznehmer [30] Laufende teilnehmerbezogene Lizenznehmerverwaltung Laufende teilnehmerbezogene Lizenznehmerverwaltung [2.5] Jahresmeldung der angeschlossenen Erzeuger und Zeichennutzer erstellen, plausibilisieren und an die MBW übermitteln Laufende teilnehmerbezogene Lizenznehmerverwaltung [5] Programminhalte und vertragliche Verpflichtungen der angeschlossenen Teilnehmer laufend überwachen Laufende teilnehmerbezogene Lizenznehmerverwaltung [7.5] Vorgesehene Kontrollen veranlassen und deren Durchführung administrativ überwachen Laufende teilnehmerbezogene Lizenznehmerverwaltung [7.5] Prüfergebnisse zuordnen, Teilnehmerstatus aktualisieren und gewöhnliche Korrekturhinweise nachverfolgen Laufende teilnehmerbezogene Lizenznehmerverwaltung [7.5] Neuanmeldungen und Stammdatenänderungen verwalten und unverzüglich an die MBW melden // === Settings === size w 2000 h 1200 margin l 8 r 2 t 18 b 20 bg color #ffffff transparent N node w 2 h 44 spacing 73 border 0 theme c color #888888 opacity 1 flow curvature 0.26 inheritfrom target color #999999 opacity 0.45 layout order exact justifyorigins N justifyends Y reversegraph N attachincompletesto nearest labels color #000000 hide N highlight 0.55 fontface sans-serif linespacing 0 relativesize 100 magnify 96 labelname appears Y size 9 weight 400 labelvalue appears Y fullprecision Y position before weight 400 labelposition autoalign 0 scheme auto first before breakpoint 7 value format '.,' prefix '' suffix ' €' themeoffset a 6 meta mentionsankeymatic N listimbalances Y
A13: Link zum interaktiven Diagramm | B13: https://sankeymatic.com/build/?i=PTAEGUEMDsGsFMCeBZAggFQJIGFSGQCUAIQEsB7ALUIHV9RoBXAJ1AC95GAXYgM2JePb1oAcwDOogA7x%2BvUQGMAFvFCQAJgFti0YqI6NIXAG7Ly9UQZaR63AO4AT6KvgAoEKFSwO9SABsdAzgAuUAAmAGYAOgAGAA4IkKiQgDZXMGRSaHgOSEZ%2Ddg5ldDsuYQRiAuhggFYwgG5QdVInHz989lAAJXhudnhoFht84IBGKIAWAE4IidAAUQBVDtAAK2VkcuFW1VAACgBxRnoJKToAXmGqqIBKesHhPtB7zXkFAuYqASdGBVIfITEfKRhMRYKAyplQIx4FplAApSAKKHiejqdTwCKpUAAGT4fRYmQUaMYwTCUTmi1APisPUcygAauwbL4vCIVmsNltQEJtvDEfVVAJQNDoOpfMR7qAGZx9GIJIwAD%2Dcf6gQwZUCk8lLABGPmhWo4Kh8oiF4r67QAYoCbI8slDoNADaJiIoOFqchi3KhoFTxFrpECzRAYJ4yJloMBUGYXj55eJlKJSDZBRIFIgnS96aRGABaADynGzABpOtDRPBs1zHKAAAqMUh%2B6AItFscoPJ1V7QuhoZLI5PKcD1gACKyHAoB0Bq%2BJugSnKfkUylzfsYfuEuW43AioEwDvYEIA0hk9L9ddBQO3tuhoT45aQ2HHQE5jSPwBjnM49vBzOoDQBtUaTNMAC6RBkJQVDOCQFDUKAv4xAA7BEVQgeg%2Bj0A27BsPQ9yMM4qFWBhjBYThsHDCESEodejaEvA7CwD4diHKy9z3NA8rLo%2B7SftApBxtALyQNwBq%2BMa5DQgu9r0BwbC5Ge3KgPMu6MASRJrkcJxyoqfTFkIbwtooYaVts7HsJoHAFD40B4WhhHEe0%2D7kchoAACIGH0LxSSwChaIMOjKCwTCgFexCWU28DGFCWhukxwiUl%2BDzybpmHiQoYbWQRZpEfA2H2SETl0lmCgwE4EKELaAhaqIjaKL5ZagNw8rMKokDPqOrBmJAqLuRZp5GZxzCKW8KnsGpxzKCZjBmRZVn4ehmV2cwDkUQp6hltJyqqmeh6MFCnhMKKAD71FomeqikLAKJ9FwvRyVWU6DXu8A0Ywo0nGiPglelc2ZFlOWLXlIGzKacBHnWLQLnI9ETsoT6UsVSacAJQnzkoZ5lXoFXGlYogNS0CVVpAOrwKxkFgTBcETHE8FOdxvFlvxiiCRwH59HT7mM0JsHU4hTmoBoWgTvoRiFMU4plBU47qKAL79XMv04a9Lh85o2i6ELxDGEFoulNCEvEFLMtTrM8sjYcY2kY5lEhcd4W9FFOTKmZnFSwc6l9GZmyfCoZi46eOlKfpqX49shO6iTysC2rBgayLJTiw8%2BvS21Rsmy9ZsnA5UQgesHCe%2DAXwVvJyDwB9%2BducQKh7WKTo3X1yx2IiKMqKdDw4mw%2DTDcwE1TSXVkR6rejR5rRRx7rCcG8n7TGwtiuwUkWdzMDsCgyeENQ7oyjyX6GPwDqzpKKAABykA1aWMNfqArtjSKHKfMamk0sWtZaS9u%2Bq4%2B52XQ6ATB6AOd59sbgkV7gNmcP3QWQ9Y5izHmeROhsp6p1nv%2BJyyBIBHTCtACQDEIQP1%2Ds%2DHor8tTvzOhdE6107RgP5gPdWw9tbx1gRPMcKcZ7p2UL%2BUkIFqzcCpP0dmChPLUkDgwEQDxcG3W2Pgkab8dAf1IVdH%2BfcqEQOFlrUerYGFJyYQglhbtYIcJcvKERPcqTWCEf8URCoaR9UkYQ4hn8yEKMoSrZRMdVHQPUZLTRstp7ZQVqw0iTlja7kESlYRrFQBiOsZYqRRCZEkK%2DuQvoTjI6DxUSPdxetGHeMQf45BIEpSwGpKISwCheqRPkjYkBdi5Hfxusk6hkC3E6w8XAyezAfF%2DSQfoy0dgJIwGEITCxWlxE1mibYuJ9j5F1PAVHNJdCYGePge0nJui8nYgEAQjMMIInRJGZU6Rxp4kOOmUo2Zrj0nNMyV45hvjTarIuCBKgOQzRaAGSIUQRyrrKHKVWfZsTDmTNqRQmZqTznzJaVkm5nTckPJLAZf4ogkqMCpOEn5EixlVImTUxJijnFnNoWoq5Sy5Y6PNms7au0vCTTQTbFuvBtC13kvMVaWQArvKAdDU6gKcX1JcQSjJ49rnaNuWne5Tlj6KGXg6MGupHxMEUA1REv9jaYoBdixxIKaFQMuYK4lHS%2DFipAmVF4gxGAlSFIwbgLV6b%2BzeIiiSxZ6KMV%2Dp8oFSTNWNIufQxZbSSUiqQWMJyh5pUnkLlWVAWpfKKARbeDg50TzKEVcC05oL%2BU6o0XqlZZLYURqjfwkRZ5CkFGEFmfsLruUapTVqpp3rWlaOWaSjOZEF4vmzFKK1SroDFgesiyA4T5KRm4GYgtFqN54y7ZXLw1cFF9WXLrMdp5eX4u1bWyFwroWrJ5tnW%2B%2Bd2B%2BA3g0cooBg3HhaLoAwZg%2BpSidBkcQ2QCZV33ZWvFqaV0LLrdkxtbDYVaCGsoVtJ6ZXZShBasMhkExJmUDuN4X56ZSu4SCAofUhzeD8LwItoZZEJOfSk6tXr31robf63J%2Bjf2PU0dmQDCamCbyrP%2DLY7QPK9XkuAaNfx3nVQULVb53DibuqrZ68FRLfX6rudmpy0HyM7kkPAEMPYzxvGcYyqs0mpByf4lgmAETePhwE3MwluqRNZqbeK7K7Jc4McYE%2DOsqh6DqbLFoWcEsmjtHwx4tFoBTA%2BkRayV1PKPX6YFRmozX6AmA2%2BLvFG9J2C6AAG8HXgMWejd8ZM7V%2DlKUUjA9rvIilqUgSGtMCmUFRs9PVlDvU%2BgFsFBngv1r9RuslANj0rxaBFQesU%2DT8Cegi7jzWQ0tGpO1nZwzbXJX3oZeSoc%2BO4tw4JmrPq6uidFWS%2DRAGWvsbeCih4AVvwnQXS69oJWjRldAHO8o%2B2ZsNMC%2Bmhbn7iObuWlfKQvDOA8BBAYYbj9xxKTPAFLMqgJtVg%2DVNkmtM%2BJIz%2DMMMYwx4i8z09VoLhpRIpT6AwaS7Al2vprQskSnmUeSXR%2D9JyYl96o88gitrMo4o2srHpUJv8Qf8ZfXhoTDxcck4kmjmSc9YcgVchUDy0lvLQF6wFKWHPUZc4p%2DkKnup6Z9SRUIpns3rvevZ%2Djrn9l9FA1YlK09Pg177qQ7DCXZPCdYx9vKcdxZICPrLSMxnl2%2BVvo8er0nBPue%2DkuI8550BuGxjqgMHQElWD5De11zgv9OyvFD693gEeJa1iaHZiWehUdR5PgoVULQusKGilh45ybmdzcR27znnl7KwqguBbMSfbOeCKT1ZUtup1PuU4AxqfX9cPDOxwC7mOWfzbL5Livi1YUobFBwYokhLHN%2Dh4YZuFW2yJkFCqg5nHartX%2B4D7Yveio%2BAqKTaCNB2ERCSEG9b2ZgBiTj3wAICL9vOCO1fm%2DXB4%2D3%2Deft0iEQYggSq5rfBZUWGJ7PobMF8AfRpQA3zC%2BEA6AMAtqX8KIH%2DECGWGAIqO6doHtLbM8CKcPGdeSNff5AvKZIvFXVxKA2KYA1hOAmWRA5A0ZF%2BVVOqPzfAqsCfTgESCrZvU6QUZAGCbucoaaCAlRCgziY0WA%2BAscOg4YQGAADz%2DTPDW36wP1Mi0BUEqi4C6hGXYG4H%2Bz3VJy7xlSRWwObl0LNT3GEPINn2gPEOoMkNgiQJkLx1vwjwRSui2Vs18wrXb0vmoJkjf3ewNE6wEHzTEF61fzeyLQ%2BTcjPAEPMl7if0v2vzD3f0EE%2DxOzoKa3%2DxdwlinFNw9zonWyVnnxyIeDyI11Hz1yAwcOiCclhAbmRQMPyM1yyyKNAEUwFh8NvDXE6lWikBkGDwPiwL7TZz9z0OUksLTW9XKPdxaKqITRqJCEBiXnW1EDTAKHUGs2T08DDW2Anz8Cnz7w3zPmLCeTtF2NAAAAk6IhAhIPluVo4MhiwOh5RIYIpdCfBhBopxY%2Bp9xUdh1YoPMjtDdoYVR2Bs9jsHABQSZn9kiXCP8xAv9%2Dwz8%2D8SjJQswLiJU887YWRKD2hktd1GBdB95bw%2DRJjMwcw%2BosTe8gD8Sd0vhiTFBSS2FHCQIOh%2DBl43Qa5I8%2D56SYsuAmS6w%2DRvZRB7BSlf565G53dDCTxNMuV1UTli8VECpKT5JqScTaTmACSGSBSFBmSajqZKJJo1CmUlITDVgRT7gxSVCpZtSwRSB%2DtOi7Rfj1sW9lBVQVwcTlcrtXEVTMTM8aToCtS%2BSiTdT9S6DDSZTwYlBIYjdlALTwAwyhT3Z6T1DowBAEsJ1CD355IWJd4zQ%2DdfAjR3BI0UpzF5TsMfCjs3TzxFBWhMyj9wI54F5Zh5DHpmA248RO5nBWy%2D0OzcQO4noiQ9EWytBRQ%2DAJQpR2sZ9FRlQKk6wejUQYAuCRAeyxyxRJyZc%2B0ZylRWR5ygR9AlyRQS5PDYp2EF5mjyccsty8TmAwd6YIdPtf48zeFxtl9INRkDzejlyTzlRfJNsYEey2zlJ2hOzBznoRyQIsRqQ%2BgnB2iqIhz2BOsAwIQwL8RELGAIomQD9%2DhnBoLrBYLlAChrYMLkLWJlA0LO4sLmRlRfxLZQBeQkQVzbzm57how2ZDIls%2BpLzCdR0ysJ1NMzBiAtQQp7c%2BpCteD%2BDlxjErJ8KaQ4LiLLJSL%2DRyL1l250LnpqKcLWQvdOEFzDyVZ98kN5JKc%2B0otJR2AJAEMXRyzZZ%2Bkvw6yOKHhgolKIKTF5LQAJomQJI8KYLaR4KSLnoyLAxKKMKtLcSuZloVS2KnpAwjsHgIoYBvMDtnTnJ5UFAk058lSNZPLlxvLUZfKCL%2DLFLO5grUKByNKiRwraKt0GCCEmD%2DJ6Bt9tIgoELnpz0vAsY7duTnz4AbBYtUpzKKVZMqVhdetON3jfgSY5LCKArXKiQyqKKKqqLGQaKdLarD5sofyPpbKWNshURmoKgoS0jwlwrf4hAIoWB5RPZFBm5HxJKaAl8rInQ2BQBrQEgogohnBQBQAFBQBm0vrMtgQzwfBQAYhvrIRQgIaDRhhwafqtRQgvqtRYo5BfgsxQAABiDcbG7gaG%2DQDTX3A0Q%2BZwHiOC96iGv6sYMYCGyQE%2BV5UAeCMICGvLcw5gL6n6jgJQNEUAOQCG1GwEZgDGmIYWkWiG0gCQOmjgRAf65wbhRMHmpgQwC9EDJA5ICGxzdgcoIBUgKWbIV%2BZmH6%2Dm9GjGiYU2s2sWiWuQcoaWpAwNZwKkRAUgKSUAcYoUWQk%2BA2lYMwN%2DR23IYG40Ymn65Yb2ngRAWC40AATQhqhAijLB6JTCPghoMGyEUC0FRvUCwSyC%2DDjToHgGeV0HtsGWLKNsFs%2BrLvZt%2BuIDgsDsruEFKXFBjyQKqCqAht0IdCtTkHjBgFEGzDLHXAhr8EyFpqttZArqhCpGFheuUFGArtFGEG0G4GlomBSCpD9FCm5sgDGhyEjpptxFAAmAht8jroNDGE%2BsLrXqVr%2BGUE3qkG3tACjp%2BqVBaDlHgCtpvTPAfoiV4nKEwz9DMJcB%2BqPpj1Pq%2BtXpLgkG%2Dq4DVCsDjQ3LPArozA3qklIFbuIFDNO26CzAAdOyhFtwgd%2DVABSEvvoETSzFFANAAHIIhCwKGIaX7eBZDQAKHaGfrEUNxiBGGKHQBAAagloc5vgDRFIA3DWhUEIeZtAArrkAkYhu2EBt7AaHkVvWDCQHIedETp%2BqN31jdB4U7sjqAA

Sheet Anforderungen_admin_QZBW
A1: ID | B1: Programm | C1: Akteur | D1: Rolle | E1: Prozesskategorie | F1: Fachliche Anforderung / erforderlicher Nachweis | G1: Administrative Tätigkeit (Objekt + Verb) | H1: Ohnehin bestehende Pflicht / Referenzzustand | I1: Zertifizierungsspezifischer Zusatzaufwand | J1: In enger Kostenrechnung enthalten | K1: Häufigkeit | L1: Fallzahl / Bezugsgröße | M1: Zeitaufwand je Vorgang (Min.) | N1: Gesamter Zeitaufwand (Std.) | O1: Stundensatz (EUR/Std.) | P1: Arbeitszeitkosten (EUR) | Q1: Datenstatus | R1: Annahme oder empirischer Wert | S1: Zahlenherkunft | T1: Übertragungsstatus | U1: Begründung der Annahme | V1: Quelldokument | W1: Wörtliches Zitat | X1: Genaue Fundstelle | Y1: Kommentar / offene Frage | Z1: Quelldaten-Zeile | AA1: Kostenperspektive / Gebührenabgrenzung
A2: QZ-0001 | B2: QZBW | C2: Traubenerzeuger / landwirtschaftlicher Betrieb | D2: Traubenerzeuger; Bezugsform: Gruppe | E2: Verträge | F2: Unterzeichnete Teilnahmevereinbarung zwischen Traubenerzeuger und Erzeugergruppe | G2: Teilnahmevereinbarung mit der Erzeugergruppe prüfen, unterzeichnen und übermitteln | H2: Ohne QZBW nicht erforderlich. | I2: Ja | J2: Ja | K2: einmalig | L2: 1 | M2: 15 | N2: =IF(OR(L2="",M2=""),"",L2*M2/60) -> 0.25 | O2: 50 | P2: =IF(OR(N2="",O2=""),"",N2*O2) -> 12.5 | Q2: Modellwert beibehalten – abweichender Kommentar als Unsicherheitsbereich dokumentiert | R2: Modellwert aus Ausgangsdatei; empirischer Status nicht belegt | S2: Ausgangsmodell – direkt übernommen beziehungsweise formelbasiert daraus berechnet | T2: Keine Programmübertragung | U2: Bei der Gruppenzertifizierung ersetzt die unmittelbare Einbindung über die Erzeugergruppe die frühere einzelbetriebliche Teilnahmevereinbarung mit einem Lizenznehmer. | V2: QZBW – Teilnahmevereinbarung Gruppenzertifizierung (pflanzliche Bereiche), Stand 2023 | W2: Der Erzeugerbetrieb erklärt seine Teilnahme am Gruppenzertifizierungssystem des oben genannten gruppenführenden Unternehmens. […] Mit dieser Erklärung treten alle früheren einzelbetrieblichen Teilnahmevereinbarungen des Erzeugers gegenüber einem Lizenznehmer […] außer Kraft. | X2: S. 1, Ziff. I.1; S. 2, Ziff. I.11 | Y2: Rollenbeziehung in V8 korrigiert: Vertragspartner des Gruppenmitglieds ist die Erzeugergruppe. | Z2: Quellenprüfung 2026-08-02 | AA2: Ressourcenperspektive: Arbeitszeit des ausführenden Akteurs | Nein - keine Zahlungsströme oder Gebühren modelliert
A3: QZ-0002 | B3: QZBW | C3: Traubenerzeuger / landwirtschaftlicher Betrieb | D3: Traubenerzeuger; Bezugsform: Gruppe | E3: Ausfüllen von Checklisten und Formulare | F3: Vollständig bearbeitete Eigenkontroll-Checkliste des landwirtschaftlichen Betriebs | G3: Eigenkontroll-Checkliste des landwirtschaftlichen Betriebs ausfüllen und ablegen | H3: Ohne QZBW nicht erforderlich. | I3: Ja | J3: Ja | K3: einmalig | L3: 1 | M3: 30 | N3: =IF(OR(L3="",M3=""),"",L3*M3/60) -> 0.5 | O3: 50 | P3: =IF(OR(N3="",O3=""),"",N3*O3) -> 25 | Q3: Szenariozuordnung korrigiert; Zeitansatz aus Ursprungsmodell | R3: Modellwert aus Ausgangsdatei; empirischer Status nicht belegt | S3: Ausgangsmodell – direkt übernommen beziehungsweise formelbasiert daraus berechnet | T3: Keine Programmübertragung | U3: Methode im Ursprungsmodell: Formularbasierte Zeitschätzung. QZBW-spezifische Eigenkontrollcheckliste; nicht pauschal auf BioZBW übertragen. | V3: QZBW – Programmbestimmungen, Stand 01.01.2025 | W3: Die Eigenkontrolle ist obligatorischer Bestandteil des Qualitätssicherungskonzeptes im „System Qualitätszeichen Baden-Württemberg“. Alle Teilnehmer müssen die Durchführung der Eigenkontrolle dokumentieren und nachweisen. | X3: Programmbestimmungen QZBW 2025, S. 14, Abschnitt 5.5 | Y3: Zeitaufwand geschätzt auf 20–30 Minuten für Lesen und Ausfüllen der Eigenkontroll-Checkliste (ca. 1.250 Wörter, strukturierte Tabellenform). Basis: durchschnittliche Lesegeschwindigkeit von 200 Wörtern/Minute und Bearbeitungszeit. | Z3: Kostenpositionen_korr!3:3 | AA3: Ressourcenperspektive: Arbeitszeit des ausführenden Akteurs | Nein - keine Zahlungsströme oder Gebühren modelliert
A4: QZ-0003 | B4: QZBW | C4: Traubenerzeuger / landwirtschaftlicher Betrieb | D4: Traubenerzeuger; Bezugsform: Gruppe | E4: Ausfüllen von Checklisten und Formulare | F4: Vollständiger Nachweis der GVO-Freiheit einschließlich Bescheinigung und zugehöriger Unterlagen | G4: GVO-Freiheitsbescheinigung ausfüllen beziehungsweise einholen und zusammen mit den zugehörigen Nachweisen ablegen | H4: Ohne QZBW nicht erforderlich. | I4: Ja | J4: Ja | K4: einmalig | L4: 1 | M4: 60 | N4: =IF(OR(L4="",M4=""),"",L4*M4/60) -> 1 | O4: 50 | P4: =IF(OR(N4="",O4=""),"",N4*O4) -> 50 | Q4: Szenariozuordnung korrigiert; Zeitansatz aus Ursprungsmodell | R4: Modellwert aus Ausgangsdatei; empirischer Status nicht belegt | S4: Ausgangsmodell – direkt übernommen beziehungsweise formelbasiert daraus berechnet | T4: Keine Programmübertragung | U4: Methode im Ursprungsmodell: Prozentuale Verteilung Adminaufwand. GVO-Freiheitsbescheinigung ist in diesem Kostenmodell QZBW-spezifisch. | V4: QZBW – Zusatzanforderungen Wein 2025; Bescheinigung über GVO-Freiheit | W4: Produkte mit dem Qualitätszeichen müssen die Anforderungen für die Kennzeichnung „Ohne Gentechnik“ erfüllen. | X4: QZBW ZA Wein 2025, S. 3, Abschnitt Gentechnik | Y4: Die frühere separate Position „Nachweise zur GVO-Freiheit“ wurde als Doppelzählung erkannt und in dieses gemeinsame Nachweispaket integriert. Es bleibt ein einmaliger Zeitansatz von 60 Minuten beziehungsweise 50 EUR. | Z4: Kostenpositionen_korr!4:4 | AA4: Ressourcenperspektive: Arbeitszeit des ausführenden Akteurs | Nein - keine Zahlungsströme oder Gebühren modelliert
A5: QZ-0004 | B5: QZBW | C5: Traubenerzeuger / landwirtschaftlicher Betrieb | D5: Traubenerzeuger; Bezugsform: Gruppe | E5: Ausfüllen von Checklisten und Formulare | F5: Dokumentierte Kenntnisnahme der Datenschutzhinweise zur Teilnahmevereinbarung | G5: Datenschutzhinweise zur Teilnahmevereinbarung lesen und unterzeichnen | H5: Ohne QZBW nicht erforderlich. | I5: Ja | J5: Ja | K5: einmalig | L5: 1 | M5: 15 | N5: =IF(OR(L5="",M5=""),"",L5*M5/60) -> 0.25 | O5: 50 | P5: =IF(OR(N5="",O5=""),"",N5*O5) -> 12.5 | Q5: Modellwert beibehalten – abweichender Kommentar als Unsicherheitsbereich dokumentiert | R5: Modellwert aus Ausgangsdatei; empirischer Status nicht belegt | S5: Ausgangsmodell – direkt übernommen beziehungsweise formelbasiert daraus berechnet | T5: Keine Programmübertragung | U5: Methode im Ursprungsmodell: Formularbasierte Zeitschätzung. Administrative Zertifizierungs-/Kontrollaufgabe gemäß Ursprungsmodell; keine inhaltliche Änderung des Zeitansatzes. | V5: QZBW – Datenschutzhinweise zur Teilnahmevereinbarung, Stand 02.07.2021 | W5: Ihre personenbezogenen Daten werden erhoben, um die Teilnahmevereinbarung abschließen und erfüllen zu können. | X5: Datenschutzhinweise Teilnahmevereinbarung QZBW, S. 1, Abschnitt 4 | Y5: Geschätzte Bearbeitungszeit basiert auf einem durchschnittlichen Lesetempo von 200 Wörtern/Minute. Das Dokument umfasst ca. 900 Wörter, daher beträgt die geschätzte Lesezeit rund 5 Minuten. Zusätzliche Zeit für das Verstehen und ggf. Eintragen von Informationen wurde mit 5 Minuten angesetzt. Gesamtaufwand: ca. 10 Minuten. Zeitannahme prüfen: Modellwert 15 Min.; Quellkommentar nennt ca. 10 Min. | Z5: Kostenpositionen_korr!5:5 | AA5: Ressourcenperspektive: Arbeitszeit des ausführenden Akteurs | Nein - keine Zahlungsströme oder Gebühren modelliert
A6: QZ-0005 | B6: QZBW | C6: Traubenerzeuger / landwirtschaftlicher Betrieb | D6: Traubenerzeuger; Bezugsform: Gruppe | E6: Datenaufzeichnung und -pflege | F6: Vollständige und aktuelle Ernteaufzeichnungen | G6: Ernteaufzeichnungen führen und ablegen | H6: Fachrechtlich oder regulär betrieblich ohnehin erforderlich; zusätzlicher Zertifizierungsanteil nicht belastbar isoliert. | I6: Nein | J6: Nein | K6: fortlaufend | L6: 1 | M6: 30 | N6: =IF(OR(L6="",M6=""),"",L6*M6/60) -> 0.5 | O6: 25 | P6: =IF(OR(N6="",O6=""),"",N6*O6) -> 12.5 | Q6: Nur Gesamtszenario – inkrementeller Anteil nicht isoliert | R6: Modellwert aus Ausgangsdatei; empirischer Status nicht belegt | S6: Ausgangsmodell – direkt übernommen beziehungsweise formelbasiert daraus berechnet | T6: Keine Programmübertragung | U6: Methode im Ursprungsmodell: Prozentuale Verteilung Adminaufwand. Gesamter Zeitansatz für Ernteaufzeichnungen enthält fachrechtliche bzw. betriebliche Basisdokumentation; kein belastbarer inkrementeller Zertifizierungsanteil. | V6: QZBW – Eigenkontrolle Erzeuger: Wein, Sekt und Perlwein – Erzeugung von Keltertrauben, Version 2024 | W6: Betriebsheft vor Anlieferung der Ernte, spätestens aber bis 30.09. des laufenden Jahres, zur Prüfung vorgelegt. | X6: Eigenkontrolle Erzeuger – Wein/Keltertrauben 2024, S. 2, Abschnitt 2.4 | Z6: Kostenpositionen_korr!6:6 | AA6: Ressourcenperspektive: Arbeitszeit des ausführenden Akteurs | Nein - keine Zahlungsströme oder Gebühren modelliert
A7: QZ-0006 | B7: QZBW | C7: Traubenerzeuger / landwirtschaftlicher Betrieb | D7: Traubenerzeuger; Bezugsform: Einzel | E7: Datenaufzeichnung und -pflege | F7: Vollständig dokumentierte Verkaufszahlen | G7: Verkaufszahlen dokumentieren und ablegen | H7: Fachrechtlich oder regulär betrieblich ohnehin erforderlich; zusätzlicher Zertifizierungsanteil nicht belastbar isoliert. | I7: Nein | J7: Nein | K7: fortlaufend | L7: 4 | M7: 60 | N7: =IF(OR(L7="",M7=""),"",L7*M7/60) -> 4 | O7: 50 | P7: =IF(OR(N7="",O7=""),"",N7*O7) -> 200 | Q7: Nur Gesamtszenario – inkrementeller Anteil nicht isoliert | R7: Modellwert aus Ausgangsdatei; empirischer Status nicht belegt | S7: Ausgangsmodell – direkt übernommen beziehungsweise formelbasiert daraus berechnet | T7: Keine Programmübertragung | U7: Methode im Ursprungsmodell: Prozentuale Verteilung Adminaufwand. Gesamter Zeitansatz für Verkaufszahlen enthält betriebliche Basisdokumentation; kein belastbarer inkrementeller Zertifizierungsanteil. | V7: QZBW – Programmbestimmungen, Stand 01.01.2025 | W7: Zeichennutzer sind verpflichtet, eine stets aktuelle Aufstellung der Produkte vorzuhalten, die mit dem Qualitätszeichen Baden-Württemberg gekennzeichnet und vermarktet werden. | X7: Programmbestimmungen QZBW 2025, S. 39, Abschnitt 12.3. Die Fundstelle verlangt eine aktuelle Produktaufstellung; eine gesonderte Pflicht zur Aufstellung von Verkaufszahlen wird nicht wörtlich genannt. | Z7: Kostenpositionen_korr!7:7 | AA7: Ressourcenperspektive: Arbeitszeit des ausführenden Akteurs | Nein - keine Zahlungsströme oder Gebühren modelliert
A8: QZ-0007 | B8: QZBW | C8: Traubenerzeuger / landwirtschaftlicher Betrieb | D8: Traubenerzeuger; Bezugsform: Gruppe | E8: Datenaufzeichnung und -pflege | F8: Vollständige und aktuelle Flächendaten | G8: Flächendaten pflegen und aktualisieren | H8: Fachrechtlich oder regulär betrieblich ohnehin erforderlich; zusätzlicher Zertifizierungsanteil nicht belastbar isoliert. | I8: Nein | J8: Nein | K8: einmalig | L8: 1 | M8: 60 | N8: =IF(OR(L8="",M8=""),"",L8*M8/60) -> 1 | O8: 25 | P8: =IF(OR(N8="",O8=""),"",N8*O8) -> 25 | Q8: Nur Gesamtszenario – inkrementeller Anteil nicht isoliert | R8: Modellwert aus Ausgangsdatei; empirischer Status nicht belegt | S8: Ausgangsmodell – direkt übernommen beziehungsweise formelbasiert daraus berechnet | T8: Keine Programmübertragung | U8: Methode im Ursprungsmodell: Prozentuale Verteilung Adminaufwand. Gesamter Zeitansatz für Flächendaten enthält fachrechtliche bzw. betriebliche Basisdokumentation; kein belastbarer inkrementeller Zertifizierungsanteil. | V8: QZBW – Anforderungen an Erzeugergruppen, Stand 01.01.2023 | W8: Die Erzeugergruppe hat ein Mitgleiderverzeichnis mit folgenden Stammdaten zu führen: […] Verzeichnis der aktuellen Anbauflächen der zertifizierten Produkte [und] Größe der aktuellen Anbaufläche (ha) der zertifizierten Produkte. | X8: Anforderungen an Erzeugergruppen 2023, S. 6, Abschnitt 3.2.3; Schreibweise „Mitgleiderverzeichnis“ entspricht dem Original | Z8: Kostenpositionen_korr!8:8 | AA8: Ressourcenperspektive: Arbeitszeit des ausführenden Akteurs | Nein - keine Zahlungsströme oder Gebühren modelliert
A9: QZ-0008 | B9: QZBW | C9: Traubenerzeuger / landwirtschaftlicher Betrieb | D9: Traubenerzeuger; Bezugsform: Gruppe | E9: Datenaufzeichnung und -pflege | F9: Nachvollziehbar dokumentierte Verfahrensschritte im Produktionsprozess auf Betriebsebene | G9: Verfahrensschritte im Produktionsprozess auf Betriebsebene dokumentieren | H9: Fachrechtlich oder regulär betrieblich ohnehin erforderlich; zusätzlicher Zertifizierungsanteil nicht belastbar isoliert. | I9: Nein | J9: Nein | K9: einmalig | L9: 1 | M9: 180 | N9: =IF(OR(L9="",M9=""),"",L9*M9/60) -> 3 | O9: 50 | P9: =IF(OR(N9="",O9=""),"",N9*O9) -> 150 | Q9: Nur Gesamtszenario – inkrementeller Anteil nicht isoliert | R9: Modellwert aus Ausgangsdatei; empirischer Status nicht belegt | S9: Ausgangsmodell – direkt übernommen beziehungsweise formelbasiert daraus berechnet | T9: Keine Programmübertragung | U9: Methode im Ursprungsmodell: Prozentuale Verteilung Adminaufwand. Dokumentation der Produktionsschritte ist nicht vollständig als zusätzlicher Zertifizierungsaufwand isoliert. | V9: QZBW – Programmbestimmungen, Stand 01.01.2025 | W9: Bei der Eigenkontrolle müssen alle betriebsspezifischen Prozesse der betreffenden Produktbereiche Berücksichtigung finden. | X9: Programmbestimmungen QZBW 2025, S. 17, Abschnitt 6.1 | Z9: Kostenpositionen_korr!9:9 | AA9: Ressourcenperspektive: Arbeitszeit des ausführenden Akteurs | Nein - keine Zahlungsströme oder Gebühren modelliert
A10: QZ-0009 | B10: QZBW | C10: Zeichennutzer / Verarbeitungsstufe | D10: Zeichennutzer; Bezugsform: Gruppe | E10: Datenaufzeichnung und -pflege | F10: Dokumentiertes und aktuelles HACCP-Konzept für Weinbereitung beziehungsweise Verarbeitung | G10: HACCP-Konzept für Weinbereitung beziehungsweise Verarbeitung dokumentieren und aktuell halten | H10: Ein HACCP-basiertes Verfahren ist für Weinbereitung/Verarbeitung bereits nach allgemeinem Lebensmittelhygienerecht erforderlich. | I10: noch zu klären | J10: Nein | K10: einmalig | L10: 1 | M10: 60 | N10: =IF(OR(L10="",M10=""),"",L10*M10/60) -> 1 | O10: 50 | P10: =IF(OR(N10="",O10=""),"",N10*O10) -> 50 | Q10: Fachlich belegt – als fachrechtliche Baseline nicht monetarisiert | R10: Modellwert aus Ausgangsdatei; empirischer Status nicht belegt | S10: Ausgangsmodell – direkt übernommen beziehungsweise formelbasiert daraus berechnet | T10: Keine Programmübertragung | U10: Methode im Ursprungsmodell: Prozentuale Verteilung Adminaufwand. HACCP gehört zur Verarbeitungs-/Zeichennutzerstufe, nicht zum reinen Traubenerzeuger; im Modell zudem Überschneidung mit Zeile 43. Bis zur Neuabgrenzung aus Summen ausgeschlossen. | V10: QZBW – Zusatzanforderungen Wein 2025; Verordnung (EG) Nr. 852/2004 | W10: „…nur in Betrieben erlaubt, die ein dokumentiertes HACCP-Konzept umsetzen.“ | X10: QZBW ZA Wein 2025, S. 7, Abschnitt Hygiene; Art. 5 der VO (EG) 852/2004: https://eur-lex.europa.eu/legal-content/DE/ALL/?uri=CELEX%3A02004R0852-20210324 | Y10: HACCP ist für die Weinbereitung/Verarbeitung fachlich relevant, aber bereits nach allgemeinem Lebensmittelhygienerecht erforderlich. Die QZBW-/BioZBW-Regel macht den vorhandenen Nachweis zur Teilnahmevoraussetzung, erzeugt jedoch keinen isolierten zusätzlichen HACCP-Aufwand. | Z10: Kostenpositionen_korr!10:10 | AA10: Ressourcenperspektive: Arbeitszeit des ausführenden Akteurs | Nein - keine Zahlungsströme oder Gebühren modelliert
A11: QZ-0010 | B11: QZBW | C11: Weinbereitung / Verarbeitung | D11: Weinhersteller; Antragsteller der amtlichen Qualitätsweinprüfung | E11: Archivierung von Nachweisen | F11: Untersuchungsbefund der amtlichen Qualitätsweinprüfung mit analytischen Angaben zu Alkohol, vergärbarem Zucker und Gesamtsäure sowie sensorischem Befund | G11: Untersuchungsbefund beschaffen, prüfen und zusammen mit dem Prüfbescheid ablegen | H11: Für Qualitätswein bereits nach Weinrecht erforderlich; Untersuchung, Probenahme und Laborleistung sind keine zusätzlichen QZBW-Schreibtischtätigkeiten. | I11: Nein | J11: Nein | K11: je Antrag beziehungsweise Charge | N11: =IF(OR(L11="",M11=""),"",L11*M11/60) | P11: =IF(OR(N11="",O11=""),"",N11*O11) | Q11: Fachlich belegt – fachrechtliche Baseline nicht monetarisiert | R11: Kein belastbarer separater administrativer Zeit- oder Kostenansatz | S11: Ausgangsmodell – 500-EUR-Mischposition fachrechtlich bereinigt; Altwert nicht übernommen | T11: Keine Programmübertragung | U11: Zucker, Säure, Alkohol und Sensorik werden nicht als vier QZBW-Zusatzanforderungen behandelt, sondern als Bestandteile des fachrechtlichen Untersuchungsbefunds. | V11: Weinverordnung | W11: Der Untersuchungsbefund umfasst einen sensorischen Befund sowie unter anderem vorhandenen Alkohol, vergärbaren Zucker und Gesamtsäure. | X11: §§ 22 und 23 sowie Anlage 10 Weinverordnung; https://www.gesetze-im-internet.de/weinv_1995/BJNR063010995.html; https://www.gesetze-im-internet.de/weinv_1995/anlage_10.html | Y11: Die frühere Sammelposition verband fachrechtliche Qualitätsparameter mit Nmin und mehreren Akteuren. Sie wurde nicht monetarisiert. Nmin ist nun bei Düngebedarfsermittlung/Düngemittelaufzeichnungen eingeordnet. | Z11: Kostenpositionen_korr!12:12 | AA11: Ressourcenperspektive; keine Labor-, Probenahme- oder Prüfgebühr angesetzt
A12: QZ-0011 | B12: QZBW | C12: Traubenerzeuger / landwirtschaftlicher Betrieb | D12: Traubenerzeuger; Bezugsform: Gruppe | E12: Archivierung von Nachweisen | F12: Vollständige Liefer- und Erntebelege | G12: Liefer- und Erntebelege dokumentieren und ablegen | H12: Fachrechtlich oder regulär betrieblich ohnehin erforderlich; zusätzlicher Zertifizierungsanteil nicht belastbar isoliert. | I12: Nein | J12: Nein | K12: fortlaufend | L12: 1 | M12: 30 | N12: =IF(OR(L12="",M12=""),"",L12*M12/60) -> 0.5 | O12: 50 | P12: =IF(OR(N12="",O12=""),"",N12*O12) -> 25 | Q12: Nur Gesamtszenario – inkrementeller Anteil nicht isoliert | R12: Modellwert aus Ausgangsdatei; empirischer Status nicht belegt | S12: Ausgangsmodell – direkt übernommen beziehungsweise formelbasiert daraus berechnet | T12: Keine Programmübertragung | U12: Methode im Ursprungsmodell: Prozentuale Verteilung Adminaufwand. Liefer-/Erntebelege fallen auch betrieblich bzw. fachrechtlich an; inkrementeller Zertifizierungsanteil nicht getrennt erhoben. | V12: QZBW – Programmbestimmungen, Stand 01.01.2025 | W12: Der Erzeuger darf seine selbst erzeugten Agrarerzeugnisse nur im direkten Handelsverkehr mit Wiederverkäufern (Zeichennutzern) als Programmware bezeichnen, z. B. auf Rechnungen und Lieferscheinen. | X12: Programmbestimmungen QZBW 2025, S. 34, Abschnitt 10.1 | Z12: Kostenpositionen_korr!14:14 | AA12: Ressourcenperspektive: Arbeitszeit des ausführenden Akteurs | Nein - keine Zahlungsströme oder Gebühren modelliert
A13: QZ-0012 | B13: QZBW | C13: Traubenerzeuger / landwirtschaftlicher Betrieb | D13: Traubenerzeuger; Bezugsform: Gruppe | E13: Archivierung von Nachweisen | F13: Vollständige und nachvollziehbare Rechnungsunterlagen | G13: Rechnungsunterlagen dokumentieren und ablegen | H13: Fachrechtlich oder regulär betrieblich ohnehin erforderlich; zusätzlicher Zertifizierungsanteil nicht belastbar isoliert. | I13: Nein | J13: Nein | K13: fortlaufend | L13: 12 | M13: 60 | N13: =IF(OR(L13="",M13=""),"",L13*M13/60) -> 12 | O13: 50 | P13: =IF(OR(N13="",O13=""),"",N13*O13) -> 600 | Q13: Nur Gesamtszenario – inkrementeller Anteil nicht isoliert | R13: Modellwert aus Ausgangsdatei; empirischer Status nicht belegt | S13: Ausgangsmodell – direkt übernommen beziehungsweise formelbasiert daraus berechnet | T13: Keine Programmübertragung | U13: Methode im Ursprungsmodell: Prozentuale Verteilung Adminaufwand. Rechnungsablage ist reguläre betriebliche Administration; nur zusätzlicher Bereitstellungs-/Kennzeichnungsaufwand wäre zertifizierungsspezifisch, wurde aber nicht getrennt erhoben. | V13: QZBW – Programmbestimmungen, Stand 01.01.2025 | W13: Der Erzeuger darf seine selbst erzeugten Agrarerzeugnisse nur im direkten Handelsverkehr mit Wiederverkäufern (Zeichennutzern) als Programmware bezeichnen, z. B. auf Rechnungen und Lieferscheinen. | X13: Programmbestimmungen QZBW 2025, S. 34, Abschnitt 10.1 | Z13: Kostenpositionen_korr!15:15 | AA13: Ressourcenperspektive: Arbeitszeit des ausführenden Akteurs | Nein - keine Zahlungsströme oder Gebühren modelliert
A14: QZ-0013 | B14: QZBW | C14: Traubenerzeuger / landwirtschaftlicher Betrieb | D14: Traubenerzeuger; Bezugsform: Gruppe | E14: Archivierung von Nachweisen | F14: Vollständige und aktuelle Pflanzenschutzaufzeichnungen | G14: Pflanzenschutzaufzeichnungen führen und ablegen | H14: Fachrechtlich oder regulär betrieblich ohnehin erforderlich; zusätzlicher Zertifizierungsanteil nicht belastbar isoliert. | I14: Nein | J14: Nein | K14: fortlaufend | L14: 12 | M14: 60 | N14: =IF(OR(L14="",M14=""),"",L14*M14/60) -> 12 | O14: 50 | P14: =IF(OR(N14="",O14=""),"",N14*O14) -> 600 | Q14: Nur Gesamtszenario – inkrementeller Anteil nicht isoliert | R14: Modellwert aus Ausgangsdatei; empirischer Status nicht belegt | S14: Ausgangsmodell – direkt übernommen beziehungsweise formelbasiert daraus berechnet | T14: Keine Programmübertragung | U14: Methode im Ursprungsmodell: Prozentuale Verteilung Adminaufwand. Pflanzenschutzaufzeichnungen sind fachrechtlich erforderlich; nur im Szenario inklusive fachrechtlicher Basisadministration. | V14: QZBW – Programmbestimmungen, Stand 01.01.2025 | W14: Besondere Dokumentationspflichten gelten für Erzeugerbetriebe […] beim Bezug und beim Einsatz von Pflanzenschutzmitteln und Düngemitteln. | X14: Programmbestimmungen QZBW 2025, S. 17–18, Abschnitt 6.1 | Z14: Kostenpositionen_korr!16:16 | AA14: Ressourcenperspektive: Arbeitszeit des ausführenden Akteurs | Nein - keine Zahlungsströme oder Gebühren modelliert
A15: QZ-0014 | B15: QZBW | C15: Traubenerzeuger / landwirtschaftlicher Betrieb | D15: Traubenerzeuger; Bezugsform: Gruppe | E15: Archivierung von Nachweisen | F15: Dokumentierte Düngebedarfsermittlung und Düngemittelaufzeichnungen einschließlich Ermittlung des verfügbaren Stickstoffs | G15: Stickstoffdüngebedarf ermitteln sowie Düngemittelaufzeichnungen führen und ablegen | H15: Fachrechtliche Pflicht: Der verfügbare Bodenstickstoff und der Düngebedarf sind zu ermitteln und zu dokumentieren; eine eigene Nmin-Laboranalyse ist nur eine mögliche Ermittlungsmethode. | I15: Nein | J15: Nein | K15: fortlaufend | L15: 12 | M15: 120 | N15: =IF(OR(L15="",M15=""),"",L15*M15/60) -> 24 | O15: 50 | P15: =IF(OR(N15="",O15=""),"",N15*O15) -> 1200 | Q15: Nur Gesamtszenario – inkrementeller Anteil nicht isoliert | R15: Modellwert aus Ausgangsdatei; empirischer Status nicht belegt | S15: Ausgangsmodell – direkt übernommen beziehungsweise formelbasiert daraus berechnet | T15: Keine Programmübertragung | U15: Methode im Ursprungsmodell: Prozentuale Verteilung Adminaufwand. Düngemittelaufzeichnungen sind fachrechtlich erforderlich; nur im Szenario inklusive fachrechtlicher Basisadministration. | V15: Düngeverordnung | W15: Der im Boden verfügbare Stickstoff ist vor dem Aufbringen wesentlicher Nährstoffmengen zu ermitteln. | X15: § 4 Abs. 4 Düngeverordnung; https://www.gesetze-im-internet.de/d_v_2017/__4.html | Y15: Nmin wird nicht als separate QZBW-Analyse geführt. Fachrechtlich erforderlich ist die Ermittlung und Dokumentation des verfügbaren Stickstoffs beziehungsweise Düngebedarfs; eine eigene Bodenanalyse ist nur eine mögliche Methode. Probenahme und Laborleistung liegen außerhalb der administrativen Kostenrechnung. | Z15: Kostenpositionen_korr!17:17 | AA15: Ressourcenperspektive: Arbeitszeit des ausführenden Akteurs | Nein - keine Zahlungsströme oder Gebühren modelliert
